Workbook
Name Actuality: 'P&L Month by CC summary'!#REF!
Name Actuality: 'P&L Month YTD by CC summary'!#REF!
Name Actuality_1: 'P&L Month by CC detailed'!$D$22
Name Actuality_1: 'P&L Month by CC summary'!$D$21
Name Actuality_1: 'P&L Month YTD by CC detailed'!$D$22
Name Actuality_1: 'P&L Month YTD by CC summary'!$D$21
Name Actuality_2: 'P&L Month by CC detailed'!$E$22
Name Actuality_2: 'P&L Month by CC summary'!#REF!
Name Actuality_2: 'P&L Month YTD by CC detailed'!$E$22
Name Actuality_2: 'P&L Month YTD by CC summary'!#REF!
Name Actuality_3: 'P&L Month by CC detailed'!$H$22
Name Actuality_3: 'P&L Month by CC summary'!#REF!
Name Actuality_3: 'P&L Month YTD by CC detailed'!$H$22
Name Actuality_3: 'P&L Month YTD by CC summary'!#REF!
Name company: 'P&L Month by CC detailed'!$C$17
Name company: 'P&L Month by CC summary'!$C$17
Name company: 'P&L Month YTD by CC detailed'!$C$17
Name company: 'P&L Month YTD by CC summary'!$C$17
Name Month: 'P&L Month by CC detailed'!$C$19
Name Month: 'P&L Month by CC summary'!#REF!
Name Month: 'P&L Month YTD by CC detailed'!$C$19
Name Month: 'P&L Month YTD by CC summary'!#REF!
Name Month_1: 'P&L Month by CC summary'!$D$21
Name Month_1: 'P&L Month YTD by CC summary'!$D$21
Name ori: 'P&L Month by CC detailed'!$C$18
Name ori: 'P&L Month by CC summary'!$C$18
Name ori: 'P&L Month YTD by CC detailed'!$C$18
Name ori: 'P&L Month YTD by CC summary'!$C$18
Name origine: 'P&L Month by CC summary'!$C$18
Name TM1REBUILDOPTION: 1
Name TM1RPTDATARNGARPT1: 'P&L Month by CC detailed'!$25:$78
Name TM1RPTDATARNGARPT1: 'P&L Month by CC summary'!$23:$41
Name TM1RPTDATARNGARPT1: 'P&L Month YTD by CC detailed'!$25:$78
Name TM1RPTDATARNGARPT1: 'P&L Month YTD by CC summary'!$23:$41
Name TM1RPTFMTIDCOL: 'P&L Month by CC detailed'!$A$1:$A$8
Name TM1RPTFMTIDCOL: 'P&L Month by CC summary'!$A$1:$A$8
Name TM1RPTFMTIDCOL: 'P&L Month YTD by CC detailed'!$A$1:$A$8
Name TM1RPTFMTIDCOL: 'P&L Month YTD by CC summary'!$A$1:$A$8
Name TM1RPTFMTRNG: 'P&L Month by CC detailed'!$B$1:$L$8
Name TM1RPTFMTRNG: 'P&L Month by CC summary'!$B$1:$D$8
Name TM1RPTFMTRNG: 'P&L Month YTD by CC detailed'!$B$1:$L$8
Name TM1RPTFMTRNG: 'P&L Month YTD by CC summary'!$B$1:$D$8

Sheet P&L Month by CC summary
B18: Origin_Company | C18: =_xll.SUBNM("CXMD:DIM_Origin_Company","","Total Origin Company") -> Total Origin Company | H18: P&L Month _ summary
B19: Actuality | C19: =_xll.SUBNM("CXMD:Actuality","","AC2022","Description EN") -> AC2022
B20: Allocation | C20: =_xll.SUBNM("CXMD:DIM_Allocation","","Total Allocation") -> Total Allocation
C21: in K Local Currency | D21: January | E21: February | F21: March | G21: April | H21: May | I21: June | J21: July | K21: August | L21: September | M21: October | N21: November | O21: December | P21: TOTAL YEAR
B22: Bucher Account
B23: G - 309000 - NET SALES | C23: Profit and Loss | D23: =_xll.DBR("CXMD:FTM_DATA_BALANCE_SHEET","Total_Customer_Supplier",D$21,$C$19,ori,"TOTAL PRODUCT","B-300010",$C$20,"Amount_BS")*-1/1000 -> 359843.49 | E23: =_xll.DBR("CXMD:FTM_DATA_BALANCE_SHEET","Total_Customer_Supplier",E$21,$C$19,ori,"TOTAL PRODUCT","B-300010",$C$20,"Amount_BS")*-1/1000 -> 340351.87 | F23: =_xll.DBR("CXMD:FTM_DATA_BALANCE_SHEET","Total_Customer_Supplier",F$21,$C$19,ori,"TOTAL PRODUCT","B-300010",$C$20,"Amount_BS")*-1/1000 -> 353866.18 | G23: =_xll.DBR("CXMD:FTM_DATA_BALANCE_SHEET","Total_Customer_Supplier",G$21,$C$19,ori,"TOTAL PRODUCT","B-300010",$C$20,"Amount_BS")*-1/1000 -> 323237.93 | H23: =_xll.DBR("CXMD:FTM_DATA_BALANCE_SHEET","Total_Customer_Supplier",H$21,$C$19,ori,"TOTAL PRODUCT","B-300010",$C$20,"Amount_BS")*-1/1000 -> 359434.3 | I23: =_xll.DBR("CXMD:FTM_DATA_BALANCE_SHEET","Total_Customer_Supplier",I$21,$C$19,ori,"TOTAL PRODUCT","B-300010",$C$20,"Amount_BS")*-1/1000 -> 379893.72 | J23: =_xll.DBR("CXMD:FTM_DATA_BALANCE_SHEET","Total_Customer_Supplier",J$21,$C$19,ori,"TOTAL PRODUCT","B-300010",$C$20,"Amount_BS")*-1/1000 -> 380094.44 | K23: =_xll.DBR("CXMD:FTM_DATA_BALANCE_SHEET","Total_Customer_Supplier",K$21,$C$19,ori,"TOTAL PRODUCT","B-300010",$C$20,"Amount_BS")*-1/1000 -> 362873.71 | ... O23: =_xll.DBR("CXMD:FTM_DATA_BALANCE_SHEET","Total_Customer_Supplier",O$21,$C$19,ori,"TOTAL PRODUCT","B-300010",$C$20,"Amount_BS")*-1/1000 -> 252037.44 | P23: =SUM(D23:O23) -> 4072661.1
B24: G - 319000 - NET VARIATION OF STOCK | C24: Profit and Loss | D24: =_xll.DBR("CXMD:FTM_DATA_BALANCE_SHEET","Total_Customer_Supplier",D$21,$C$19,ori,"TOTAL PRODUCT","B-310010",$C$20,"Amount_BS")*-1/1000 -> -30807.778 | E24: =_xll.DBR("CXMD:FTM_DATA_BALANCE_SHEET","Total_Customer_Supplier",E$21,$C$19,ori,"TOTAL PRODUCT","B-310010",$C$20,"Amount_BS")*-1/1000 -> -7700.917 | F24: =_xll.DBR("CXMD:FTM_DATA_BALANCE_SHEET","Total_Customer_Supplier",F$21,$C$19,ori,"TOTAL PRODUCT","B-310010",$C$20,"Amount_BS")*-1/1000 -> 17816.846 | G24: =_xll.DBR("CXMD:FTM_DATA_BALANCE_SHEET","Total_Customer_Supplier",G$21,$C$19,ori,"TOTAL PRODUCT","B-310010",$C$20,"Amount_BS")*-1/1000 -> -5525.5791 | H24: =_xll.DBR("CXMD:FTM_DATA_BALANCE_SHEET","Total_Customer_Supplier",H$21,$C$19,ori,"TOTAL PRODUCT","B-310010",$C$20,"Amount_BS")*-1/1000 -> 23479.517 | I24: =_xll.DBR("CXMD:FTM_DATA_BALANCE_SHEET","Total_Customer_Supplier",I$21,$C$19,ori,"TOTAL PRODUCT","B-310010",$C$20,"Amount_BS")*-1/1000 -> -8578.8464 | J24: =_xll.DBR("CXMD:FTM_DATA_BALANCE_SHEET","Total_Customer_Supplier",J$21,$C$19,ori,"TOTAL PRODUCT","B-310010",$C$20,"Amount_BS")*-1/1000 -> -18897.088 | K24: =_xll.DBR("CXMD:FTM_DATA_BALANCE_SHEET","Total_Customer_Supplier",K$21,$C$19,ori,"TOTAL PRODUCT","B-310010",$C$20,"Amount_BS")*-1/1000 -> -224.62734 | ... O24: =_xll.DBR("CXMD:FTM_DATA_BALANCE_SHEET","Total_Customer_Supplier",O$21,$C$19,ori,"TOTAL PRODUCT","B-310010",$C$20,"Amount_BS")*-1/1000 -> 3887.5685 | P24: =SUM(D24:O24) -> 10475.845
B25: G-329000 Corporate output | D25: =D23+D24 -> 329035.72 | E25: =E23+E24 -> 332650.95 | F25: =F23+F24 -> 371683.02 | G25: =G23+G24 -> 317712.35 | H25: =H23+H24 -> 382913.81 | I25: =I23+I24 -> 371314.88 | J25: =J23+J24 -> 361197.35 | K25: =K23+K24 -> 362649.08 | ... P25: =P23+P24 -> 4083136.9
B26: G - 339000 - OPERATING INCOME | C26: Profit and Loss | D26: =_xll.DBR("CXMD:FTM_DATA_BALANCE_SHEET","Total_Customer_Supplier",D$21,$C$19,ori,"TOTAL PRODUCT","B-330010",$C$20,"Amount_BS")*-1/1000 -> 4042.3655 | E26: =_xll.DBR("CXMD:FTM_DATA_BALANCE_SHEET","Total_Customer_Supplier",E$21,$C$19,ori,"TOTAL PRODUCT","B-330010",$C$20,"Amount_BS")*-1/1000 -> 4540.9253 | F26: =_xll.DBR("CXMD:FTM_DATA_BALANCE_SHEET","Total_Customer_Supplier",F$21,$C$19,ori,"TOTAL PRODUCT","B-330010",$C$20,"Amount_BS")*-1/1000 -> 4848.1721 | G26: =_xll.DBR("CXMD:FTM_DATA_BALANCE_SHEET","Total_Customer_Supplier",G$21,$C$19,ori,"TOTAL PRODUCT","B-330010",$C$20,"Amount_BS")*-1/1000 -> 4398.9568 | H26: =_xll.DBR("CXMD:FTM_DATA_BALANCE_SHEET","Total_Customer_Supplier",H$21,$C$19,ori,"TOTAL PRODUCT","B-330010",$C$20,"Amount_BS")*-1/1000 -> 4382.8768 | I26: =_xll.DBR("CXMD:FTM_DATA_BALANCE_SHEET","Total_Customer_Supplier",I$21,$C$19,ori,"TOTAL PRODUCT","B-330010",$C$20,"Amount_BS")*-1/1000 -> 4726.6561 | J26: =_xll.DBR("CXMD:FTM_DATA_BALANCE_SHEET","Total_Customer_Supplier",J$21,$C$19,ori,"TOTAL PRODUCT","B-330010",$C$20,"Amount_BS")*-1/1000 -> 4529.6568 | K26: =_xll.DBR("CXMD:FTM_DATA_BALANCE_SHEET","Total_Customer_Supplier",K$21,$C$19,ori,"TOTAL PRODUCT","B-330010",$C$20,"Amount_BS")*-1/1000 -> 4356.6035 | ... O26: =_xll.DBR("CXMD:FTM_DATA_BALANCE_SHEET","Total_Customer_Supplier",O$21,$C$19,ori,"TOTAL PRODUCT","B-330010",$C$20,"Amount_BS")*-1/1000 -> 2890.2751 | P26: =SUM(D26:O26) -> 52175.87
B27: REVENUE | D27: =D25+D26 -> 333078.08 | E27: =E25+E26 -> 337191.88 | F27: =F25+F26 -> 376531.2 | G27: =G25+G26 -> 322111.3 | H27: =H25+H26 -> 387296.69 | I27: =I25+I26 -> 376041.53 | J27: =J25+J26 -> 365727.01 | K27: =K25+K26 -> 367005.68 | ... P27: =P25+P26 -> 4135312.8
B28: G - 452000 - VARIATION OF PROVISIONS | C28: Profit and Loss | D28: =(_xll.DBR("CXMD:FTM_DATA_BALANCE_SHEET","Total_Customer_Supplier",D$21,$C$19,ori,"TOTAL PRODUCT","B-452010",$C$20,"Amount_BS")/1000)+(_xll.DBR("CXMD:FTM_DATA_BALANCE_SHEET","Total_Customer_Supplier",D$21,$C$19,ori,"TOTAL PRODUCT","B-452210",$C$20,"Amount_BS")/1000) -> 442.07326 | E28: =(_xll.DBR("CXMD:FTM_DATA_BALANCE_SHEET","Total_Customer_Supplier",E$21,$C$19,ori,"TOTAL PRODUCT","B-452010",$C$20,"Amount_BS")/1000)+(_xll.DBR("CXMD:FTM_DATA_BALANCE_SHEET","Total_Customer_Supplier",E$21,$C$19,ori,"TOTAL PRODUCT","B-452210",$C$20,"Amount_BS")/1000) -> -194.91658 | F28: =(_xll.DBR("CXMD:FTM_DATA_BALANCE_SHEET","Total_Customer_Supplier",F$21,$C$19,ori,"TOTAL PRODUCT","B-452010",$C$20,"Amount_BS")/1000)+(_xll.DBR("CXMD:FTM_DATA_BALANCE_SHEET","Total_Customer_Supplier",F$21,$C$19,ori,"TOTAL PRODUCT","B-452210",$C$20,"Amount_BS")/1000) -> 1613.4027 | G28: =(_xll.DBR("CXMD:FTM_DATA_BALANCE_SHEET","Total_Customer_Supplier",G$21,$C$19,ori,"TOTAL PRODUCT","B-452010",$C$20,"Amount_BS")/1000)+(_xll.DBR("CXMD:FTM_DATA_BALANCE_SHEET","Total_Customer_Supplier",G$21,$C$19,ori,"TOTAL PRODUCT","B-452210",$C$20,"Amount_BS")/1000) -> 1257.8317 | H28: =(_xll.DBR("CXMD:FTM_DATA_BALANCE_SHEET","Total_Customer_Supplier",H$21,$C$19,ori,"TOTAL PRODUCT","B-452010",$C$20,"Amount_BS")/1000)+(_xll.DBR("CXMD:FTM_DATA_BALANCE_SHEET","Total_Customer_Supplier",H$21,$C$19,ori,"TOTAL PRODUCT","B-452210",$C$20,"Amount_BS")/1000) -> -66.29061 | I28: =(_xll.DBR("CXMD:FTM_DATA_BALANCE_SHEET","Total_Customer_Supplier",I$21,$C$19,ori,"TOTAL PRODUCT","B-452010",$C$20,"Amount_BS")/1000)+(_xll.DBR("CXMD:FTM_DATA_BALANCE_SHEET","Total_Customer_Supplier",I$21,$C$19,ori,"TOTAL PRODUCT","B-452210",$C$20,"Amount_BS")/1000) -> 544.75837 | J28: =(_xll.DBR("CXMD:FTM_DATA_BALANCE_SHEET","Total_Customer_Supplier",J$21,$C$19,ori,"TOTAL PRODUCT","B-452010",$C$20,"Amount_BS")/1000)+(_xll.DBR("CXMD:FTM_DATA_BALANCE_SHEET","Total_Customer_Supplier",J$21,$C$19,ori,"TOTAL PRODUCT","B-452210",$C$20,"Amount_BS")/1000) -> 1477.1387 | K28: =(_xll.DBR("CXMD:FTM_DATA_BALANCE_SHEET","Total_Customer_Supplier",K$21,$C$19,ori,"TOTAL PRODUCT","B-452010",$C$20,"Amount_BS")/1000)+(_xll.DBR("CXMD:FTM_DATA_BALANCE_SHEET","Total_Customer_Supplier",K$21,$C$19,ori,"TOTAL PRODUCT","B-452210",$C$20,"Amount_BS")/1000) -> 908.98217 | ... O28: =(_xll.DBR("CXMD:FTM_DATA_BALANCE_SHEET","Total_Customer_Supplier",O$21,$C$19,ori,"TOTAL PRODUCT","B-452010",$C$20,"Amount_BS")/1000)+(_xll.DBR("CXMD:FTM_DATA_BALANCE_SHEET","Total_Customer_Supplier",O$21,$C$19,ori,"TOTAL PRODUCT","B-452210",$C$20,"Amount_BS")/1000) -> 9764.6165 | P28: =SUM(D28:O28) -> 29689.028
B29: Total Material expenses + net var. stock | D29: =(_xll.DBR("CXMD:FTM_DATA_BALANCE_SHEET","Total_Customer_Supplier",D$21,$C$19,ori,"TOTAL PRODUCT","B-401010",$C$20,"Amount_BS")/1000)+(_xll.DBR("CXMD:FTM_DATA_BALANCE_SHEET","Total_Customer_Supplier",D$21,$C$19,ori,"TOTAL PRODUCT","B-401020",$C$20,"Amount_BS")/1000)+(_xll.DBR("CXMD:FTM_DATA_BALANCE_SHEET","Total_Customer_Supplier",D$21,$C$19,ori,"TOTAL PRODUCT","B-402110",$C$20,"Amount_BS")/1000)+(_xll.DBR("CXMD:FTM_DATA_BALANCE_SHEET","Total_Customer_Supplier",D$21,$C$19,ori,"TOTAL PRODUCT","B-402111",$C$20,"Amount_BS")/1000)+(_xll.DBR("CXMD:FTM_DATA_BALANCE_SHEET","Total_Customer_Supplier",D$21,$C$19,ori,"TOTAL PRODUCT","B-407010",$C$20,"Amount_BS")/1000) -> 190042.62 | E29: =(_xll.DBR("CXMD:FTM_DATA_BALANCE_SHEET","Total_Customer_Supplier",E$21,$C$19,ori,"TOTAL PRODUCT","B-401010",$C$20,"Amount_BS")/1000)+(_xll.DBR("CXMD:FTM_DATA_BALANCE_SHEET","Total_Customer_Supplier",E$21,$C$19,ori,"TOTAL PRODUCT","B-401020",$C$20,"Amount_BS")/1000)+(_xll.DBR("CXMD:FTM_DATA_BALANCE_SHEET","Total_Customer_Supplier",E$21,$C$19,ori,"TOTAL PRODUCT","B-402110",$C$20,"Amount_BS")/1000)+(_xll.DBR("CXMD:FTM_DATA_BALANCE_SHEET","Total_Customer_Supplier",E$21,$C$19,ori,"TOTAL PRODUCT","B-402111",$C$20,"Amount_BS")/1000)+(_xll.DBR("CXMD:FTM_DATA_BALANCE_SHEET","Total_Customer_Supplier",E$21,$C$19,ori,"TOTAL PRODUCT","B-407010",$C$20,"Amount_BS")/1000) -> 192852.16 | F29: =(_xll.DBR("CXMD:FTM_DATA_BALANCE_SHEET","Total_Customer_Supplier",F$21,$C$19,ori,"TOTAL PRODUCT","B-401010",$C$20,"Amount_BS")/1000)+(_xll.DBR("CXMD:FTM_DATA_BALANCE_SHEET","Total_Customer_Supplier",F$21,$C$19,ori,"TOTAL PRODUCT","B-401020",$C$20,"Amount_BS")/1000)+(_xll.DBR("CXMD:FTM_DATA_BALANCE_SHEET","Total_Customer_Supplier",F$21,$C$19,ori,"TOTAL PRODUCT","B-402110",$C$20,"Amount_BS")/1000)+(_xll.DBR("CXMD:FTM_DATA_BALANCE_SHEET","Total_Customer_Supplier",F$21,$C$19,ori,"TOTAL PRODUCT","B-402111",$C$20,"Amount_BS")/1000)+(_xll.DBR("CXMD:FTM_DATA_BALANCE_SHEET","Total_Customer_Supplier",F$21,$C$19,ori,"TOTAL PRODUCT","B-407010",$C$20,"Amount_BS")/1000) -> 252392.84 | G29: =(_xll.DBR("CXMD:FTM_DATA_BALANCE_SHEET","Total_Customer_Supplier",G$21,$C$19,ori,"TOTAL PRODUCT","B-401010",$C$20,"Amount_BS")/1000)+(_xll.DBR("CXMD:FTM_DATA_BALANCE_SHEET","Total_Customer_Supplier",G$21,$C$19,ori,"TOTAL PRODUCT","B-401020",$C$20,"Amount_BS")/1000)+(_xll.DBR("CXMD:FTM_DATA_BALANCE_SHEET","Total_Customer_Supplier",G$21,$C$19,ori,"TOTAL PRODUCT","B-402110",$C$20,"Amount_BS")/1000)+(_xll.DBR("CXMD:FTM_DATA_BALANCE_SHEET","Total_Customer_Supplier",G$21,$C$19,ori,"TOTAL PRODUCT","B-402111",$C$20,"Amount_BS")/1000)+(_xll.DBR("CXMD:FTM_DATA_BALANCE_SHEET","Total_Customer_Supplier",G$21,$C$19,ori,"TOTAL PRODUCT","B-407010",$C$20,"Amount_BS")/1000) -> 210140.84 | H29: =(_xll.DBR("CXMD:FTM_DATA_BALANCE_SHEET","Total_Customer_Supplier",H$21,$C$19,ori,"TOTAL PRODUCT","B-401010",$C$20,"Amount_BS")/1000)+(_xll.DBR("CXMD:FTM_DATA_BALANCE_SHEET","Total_Customer_Supplier",H$21,$C$19,ori,"TOTAL PRODUCT","B-401020",$C$20,"Amount_BS")/1000)+(_xll.DBR("CXMD:FTM_DATA_BALANCE_SHEET","Total_Customer_Supplier",H$21,$C$19,ori,"TOTAL PRODUCT","B-402110",$C$20,"Amount_BS")/1000)+(_xll.DBR("CXMD:FTM_DATA_BALANCE_SHEET","Total_Customer_Supplier",H$21,$C$19,ori,"TOTAL PRODUCT","B-402111",$C$20,"Amount_BS")/1000)+(_xll.DBR("CXMD:FTM_DATA_BALANCE_SHEET","Total_Customer_Supplier",H$21,$C$19,ori,"TOTAL PRODUCT","B-407010",$C$20,"Amount_BS")/1000) -> 243390.75 | I29: =(_xll.DBR("CXMD:FTM_DATA_BALANCE_SHEET","Total_Customer_Supplier",I$21,$C$19,ori,"TOTAL PRODUCT","B-401010",$C$20,"Amount_BS")/1000)+(_xll.DBR("CXMD:FTM_DATA_BALANCE_SHEET","Total_Customer_Supplier",I$21,$C$19,ori,"TOTAL PRODUCT","B-401020",$C$20,"Amount_BS")/1000)+(_xll.DBR("CXMD:FTM_DATA_BALANCE_SHEET","Total_Customer_Supplier",I$21,$C$19,ori,"TOTAL PRODUCT","B-402110",$C$20,"Amount_BS")/1000)+(_xll.DBR("CXMD:FTM_DATA_BALANCE_SHEET","Total_Customer_Supplier",I$21,$C$19,ori,"TOTAL PRODUCT","B-402111",$C$20,"Amount_BS")/1000)+(_xll.DBR("CXMD:FTM_DATA_BALANCE_SHEET","Total_Customer_Supplier",I$21,$C$19,ori,"TOTAL PRODUCT","B-407010",$C$20,"Amount_BS")/1000) -> 235213 | J29: =(_xll.DBR("CXMD:FTM_DATA_BALANCE_SHEET","Total_Customer_Supplier",J$21,$C$19,ori,"TOTAL PRODUCT","B-401010",$C$20,"Amount_BS")/1000)+(_xll.DBR("CXMD:FTM_DATA_BALANCE_SHEET","Total_Customer_Supplier",J$21,$C$19,ori,"TOTAL PRODUCT","B-401020",$C$20,"Amount_BS")/1000)+(_xll.DBR("CXMD:FTM_DATA_BALANCE_SHEET","Total_Customer_Supplier",J$21,$C$19,ori,"TOTAL PRODUCT","B-402110",$C$20,"Amount_BS")/1000)+(_xll.DBR("CXMD:FTM_DATA_BALANCE_SHEET","Total_Customer_Supplier",J$21,$C$19,ori,"TOTAL PRODUCT","B-402111",$C$20,"Amount_BS")/1000)+(_xll.DBR("CXMD:FTM_DATA_BALANCE_SHEET","Total_Customer_Supplier",J$21,$C$19,ori,"TOTAL PRODUCT","B-407010",$C$20,"Amount_BS")/1000) -> 221949.36 | K29: =(_xll.DBR("CXMD:FTM_DATA_BALANCE_SHEET","Total_Customer_Supplier",K$21,$C$19,ori,"TOTAL PRODUCT","B-401010",$C$20,"Amount_BS")/1000)+(_xll.DBR("CXMD:FTM_DATA_BALANCE_SHEET","Total_Customer_Supplier",K$21,$C$19,ori,"TOTAL PRODUCT","B-401020",$C$20,"Amount_BS")/1000)+(_xll.DBR("CXMD:FTM_DATA_BALANCE_SHEET","Total_Customer_Supplier",K$21,$C$19,ori,"TOTAL PRODUCT","B-402110",$C$20,"Amount_BS")/1000)+(_xll.DBR("CXMD:FTM_DATA_BALANCE_SHEET","Total_Customer_Supplier",K$21,$C$19,ori,"TOTAL PRODUCT","B-402111",$C$20,"Amount_BS")/1000)+(_xll.DBR("CXMD:FTM_DATA_BALANCE_SHEET","Total_Customer_Supplier",K$21,$C$19,ori,"TOTAL PRODUCT","B-407010",$C$20,"Amount_BS")/1000) -> 199063.85 | ... O29: =(_xll.DBR("CXMD:FTM_DATA_BALANCE_SHEET","Total_Customer_Supplier",O$21,$C$19,ori,"TOTAL PRODUCT","B-401010",$C$20,"Amount_BS")/1000)+(_xll.DBR("CXMD:FTM_DATA_BALANCE_SHEET","Total_Customer_Supplier",O$21,$C$19,ori,"TOTAL PRODUCT","B-401020",$C$20,"Amount_BS")/1000)+(_xll.DBR("CXMD:FTM_DATA_BALANCE_SHEET","Total_Customer_Supplier",O$21,$C$19,ori,"TOTAL PRODUCT","B-402110",$C$20,"Amount_BS")/1000)+(_xll.DBR("CXMD:FTM_DATA_BALANCE_SHEET","Total_Customer_Supplier",O$21,$C$19,ori,"TOTAL PRODUCT","B-402111",$C$20,"Amount_BS")/1000)+(_xll.DBR("CXMD:FTM_DATA_BALANCE_SHEET","Total_Customer_Supplier",O$21,$C$19,ori,"TOTAL PRODUCT","B-407010",$C$20,"Amount_BS")/1000) -> 161641.24 | P29: =SUM(D29:O29) -> 2543662.2
C30: % of corporate output | D30: =IF(D25<>0,D29/D25,0) -> 0.57757445 | E30: =IF(E25<>0,E29/E25,0) -> 0.57974328 | F30: =IF(F25<>0,F29/F25,0) -> 0.679054 | G30: =IF(G25<>0,G29/G25,0) -> 0.66141854 | H30: =IF(H25<>0,H29/H25,0) -> 0.63562803 | I30: =IF(I25<>0,I29/I25,0) -> 0.63345967 | J30: =IF(J25<>0,J29/J25,0) -> 0.61448226 | K30: =IF(K25<>0,K29/K25,0) -> 0.54891592 | ... P30: =IF(P25<>0,P29/P25,0) -> 0.62296765
B31: G-429999-GROSS MARGIN | D31: =D27-D29 -> 143035.46 | E31: =E27-E29 -> 144339.72 | F31: =F27-F29 -> 124138.35 | G31: =G27-G29 -> 111970.47 | H31: =H27-H29 -> 143905.94 | I31: =I27-I29 -> 140828.54 | J31: =J27-J29 -> 143777.64 | K31: =K27-K29 -> 167941.83 | ... P31: =P27-P29 -> 1591650.6
C32: % of corporate output | D32: =IF(D25<>0,D31/D25,0) -> 0.43471105 | E32: =IF(E25<>0,E31/E25,0) -> 0.43390744 | F32: =IF(F25<>0,F31/F25,0) -> 0.33398984 | G32: =IF(G25<>0,G31/G25,0) -> 0.35242718 | H32: =IF(H25<>0,H31/H25,0) -> 0.37581809 | I32: =IF(I25<>0,I31/I25,0) -> 0.37926984 | J32: =IF(J25<>0,J31/J25,0) -> 0.39805841 | K32: =IF(K25<>0,K31/K25,0) -> 0.46309736 | ... P32: =IF(P25<>0,P31/P25,0) -> 0.38981073
B33: G - 439000 - PERSONNEL COSTS | C33: Profit and Loss | D33: =(_xll.DBR("CXMD:FTM_DATA_BALANCE_SHEET","Total_Customer_Supplier",D$21,$C$19,ori,"TOTAL PRODUCT","B-430010",$C$20,"Amount_BS")/1000)+(_xll.DBR("CXMD:FTM_DATA_BALANCE_SHEET","Total_Customer_Supplier",D$21,$C$19,ori,"TOTAL PRODUCT","B-430040",$C$20,"Amount_BS")/1000)+(_xll.DBR("CXMD:FTM_DATA_BALANCE_SHEET","Total_Customer_Supplier",D$21,$C$19,ori,"TOTAL PRODUCT","B-431040",$C$20,"Amount_BS")/1000)+(_xll.DBR("CXMD:FTM_DATA_BALANCE_SHEET","Total_Customer_Supplier",D$21,$C$19,ori,"TOTAL PRODUCT","B-437010",$C$20,"Amount_BS")/1000)+(_xll.DBR("CXMD:FTM_DATA_BALANCE_SHEET","Total_Customer_Supplier",D$21,$C$19,ori,"TOTAL PRODUCT","B-438010",$C$20,"Amount_BS")/1000) -> 37400.484 | E33: =(_xll.DBR("CXMD:FTM_DATA_BALANCE_SHEET","Total_Customer_Supplier",E$21,$C$19,ori,"TOTAL PRODUCT","B-430010",$C$20,"Amount_BS")/1000)+(_xll.DBR("CXMD:FTM_DATA_BALANCE_SHEET","Total_Customer_Supplier",E$21,$C$19,ori,"TOTAL PRODUCT","B-430040",$C$20,"Amount_BS")/1000)+(_xll.DBR("CXMD:FTM_DATA_BALANCE_SHEET","Total_Customer_Supplier",E$21,$C$19,ori,"TOTAL PRODUCT","B-431040",$C$20,"Amount_BS")/1000)+(_xll.DBR("CXMD:FTM_DATA_BALANCE_SHEET","Total_Customer_Supplier",E$21,$C$19,ori,"TOTAL PRODUCT","B-437010",$C$20,"Amount_BS")/1000)+(_xll.DBR("CXMD:FTM_DATA_BALANCE_SHEET","Total_Customer_Supplier",E$21,$C$19,ori,"TOTAL PRODUCT","B-438010",$C$20,"Amount_BS")/1000) -> 40241.933 | F33: =(_xll.DBR("CXMD:FTM_DATA_BALANCE_SHEET","Total_Customer_Supplier",F$21,$C$19,ori,"TOTAL PRODUCT","B-430010",$C$20,"Amount_BS")/1000)+(_xll.DBR("CXMD:FTM_DATA_BALANCE_SHEET","Total_Customer_Supplier",F$21,$C$19,ori,"TOTAL PRODUCT","B-430040",$C$20,"Amount_BS")/1000)+(_xll.DBR("CXMD:FTM_DATA_BALANCE_SHEET","Total_Customer_Supplier",F$21,$C$19,ori,"TOTAL PRODUCT","B-431040",$C$20,"Amount_BS")/1000)+(_xll.DBR("CXMD:FTM_DATA_BALANCE_SHEET","Total_Customer_Supplier",F$21,$C$19,ori,"TOTAL PRODUCT","B-437010",$C$20,"Amount_BS")/1000)+(_xll.DBR("CXMD:FTM_DATA_BALANCE_SHEET","Total_Customer_Supplier",F$21,$C$19,ori,"TOTAL PRODUCT","B-438010",$C$20,"Amount_BS")/1000) -> 41481.869 | G33: =(_xll.DBR("CXMD:FTM_DATA_BALANCE_SHEET","Total_Customer_Supplier",G$21,$C$19,ori,"TOTAL PRODUCT","B-430010",$C$20,"Amount_BS")/1000)+(_xll.DBR("CXMD:FTM_DATA_BALANCE_SHEET","Total_Customer_Supplier",G$21,$C$19,ori,"TOTAL PRODUCT","B-430040",$C$20,"Amount_BS")/1000)+(_xll.DBR("CXMD:FTM_DATA_BALANCE_SHEET","Total_Customer_Supplier",G$21,$C$19,ori,"TOTAL PRODUCT","B-431040",$C$20,"Amount_BS")/1000)+(_xll.DBR("CXMD:FTM_DATA_BALANCE_SHEET","Total_Customer_Supplier",G$21,$C$19,ori,"TOTAL PRODUCT","B-437010",$C$20,"Amount_BS")/1000)+(_xll.DBR("CXMD:FTM_DATA_BALANCE_SHEET","Total_Customer_Supplier",G$21,$C$19,ori,"TOTAL PRODUCT","B-438010",$C$20,"Amount_BS")/1000) -> 38295.867 | H33: =(_xll.DBR("CXMD:FTM_DATA_BALANCE_SHEET","Total_Customer_Supplier",H$21,$C$19,ori,"TOTAL PRODUCT","B-430010",$C$20,"Amount_BS")/1000)+(_xll.DBR("CXMD:FTM_DATA_BALANCE_SHEET","Total_Customer_Supplier",H$21,$C$19,ori,"TOTAL PRODUCT","B-430040",$C$20,"Amount_BS")/1000)+(_xll.DBR("CXMD:FTM_DATA_BALANCE_SHEET","Total_Customer_Supplier",H$21,$C$19,ori,"TOTAL PRODUCT","B-431040",$C$20,"Amount_BS")/1000)+(_xll.DBR("CXMD:FTM_DATA_BALANCE_SHEET","Total_Customer_Supplier",H$21,$C$19,ori,"TOTAL PRODUCT","B-437010",$C$20,"Amount_BS")/1000)+(_xll.DBR("CXMD:FTM_DATA_BALANCE_SHEET","Total_Customer_Supplier",H$21,$C$19,ori,"TOTAL PRODUCT","B-438010",$C$20,"Amount_BS")/1000) -> 40150.205 | I33: =(_xll.DBR("CXMD:FTM_DATA_BALANCE_SHEET","Total_Customer_Supplier",I$21,$C$19,ori,"TOTAL PRODUCT","B-430010",$C$20,"Amount_BS")/1000)+(_xll.DBR("CXMD:FTM_DATA_BALANCE_SHEET","Total_Customer_Supplier",I$21,$C$19,ori,"TOTAL PRODUCT","B-430040",$C$20,"Amount_BS")/1000)+(_xll.DBR("CXMD:FTM_DATA_BALANCE_SHEET","Total_Customer_Supplier",I$21,$C$19,ori,"TOTAL PRODUCT","B-431040",$C$20,"Amount_BS")/1000)+(_xll.DBR("CXMD:FTM_DATA_BALANCE_SHEET","Total_Customer_Supplier",I$21,$C$19,ori,"TOTAL PRODUCT","B-437010",$C$20,"Amount_BS")/1000)+(_xll.DBR("CXMD:FTM_DATA_BALANCE_SHEET","Total_Customer_Supplier",I$21,$C$19,ori,"TOTAL PRODUCT","B-438010",$C$20,"Amount_BS")/1000) -> 43584.553 | J33: =(_xll.DBR("CXMD:FTM_DATA_BALANCE_SHEET","Total_Customer_Supplier",J$21,$C$19,ori,"TOTAL PRODUCT","B-430010",$C$20,"Amount_BS")/1000)+(_xll.DBR("CXMD:FTM_DATA_BALANCE_SHEET","Total_Customer_Supplier",J$21,$C$19,ori,"TOTAL PRODUCT","B-430040",$C$20,"Amount_BS")/1000)+(_xll.DBR("CXMD:FTM_DATA_BALANCE_SHEET","Total_Customer_Supplier",J$21,$C$19,ori,"TOTAL PRODUCT","B-431040",$C$20,"Amount_BS")/1000)+(_xll.DBR("CXMD:FTM_DATA_BALANCE_SHEET","Total_Customer_Supplier",J$21,$C$19,ori,"TOTAL PRODUCT","B-437010",$C$20,"Amount_BS")/1000)+(_xll.DBR("CXMD:FTM_DATA_BALANCE_SHEET","Total_Customer_Supplier",J$21,$C$19,ori,"TOTAL PRODUCT","B-438010",$C$20,"Amount_BS")/1000) -> 37568.565 | K33: =(_xll.DBR("CXMD:FTM_DATA_BALANCE_SHEET","Total_Customer_Supplier",K$21,$C$19,ori,"TOTAL PRODUCT","B-430010",$C$20,"Amount_BS")/1000)+(_xll.DBR("CXMD:FTM_DATA_BALANCE_SHEET","Total_Customer_Supplier",K$21,$C$19,ori,"TOTAL PRODUCT","B-430040",$C$20,"Amount_BS")/1000)+(_xll.DBR("CXMD:FTM_DATA_BALANCE_SHEET","Total_Customer_Supplier",K$21,$C$19,ori,"TOTAL PRODUCT","B-431040",$C$20,"Amount_BS")/1000)+(_xll.DBR("CXMD:FTM_DATA_BALANCE_SHEET","Total_Customer_Supplier",K$21,$C$19,ori,"TOTAL PRODUCT","B-437010",$C$20,"Amount_BS")/1000)+(_xll.DBR("CXMD:FTM_DATA_BALANCE_SHEET","Total_Customer_Supplier",K$21,$C$19,ori,"TOTAL PRODUCT","B-438010",$C$20,"Amount_BS")/1000) -> 31559.169 | ... O33: =(_xll.DBR("CXMD:FTM_DATA_BALANCE_SHEET","Total_Customer_Supplier",O$21,$C$19,ori,"TOTAL PRODUCT","B-430010",$C$20,"Amount_BS")/1000)+(_xll.DBR("CXMD:FTM_DATA_BALANCE_SHEET","Total_Customer_Supplier",O$21,$C$19,ori,"TOTAL PRODUCT","B-430040",$C$20,"Amount_BS")/1000)+(_xll.DBR("CXMD:FTM_DATA_BALANCE_SHEET","Total_Customer_Supplier",O$21,$C$19,ori,"TOTAL PRODUCT","B-431040",$C$20,"Amount_BS")/1000)+(_xll.DBR("CXMD:FTM_DATA_BALANCE_SHEET","Total_Customer_Supplier",O$21,$C$19,ori,"TOTAL PRODUCT","B-437010",$C$20,"Amount_BS")/1000)+(_xll.DBR("CXMD:FTM_DATA_BALANCE_SHEET","Total_Customer_Supplier",O$21,$C$19,ori,"TOTAL PRODUCT","B-438010",$C$20,"Amount_BS")/1000) -> 33483.778 | P33: =SUM(D33:O33) -> 460087.47
C34: % of corporate output | D34: =IF(D25<>0,D33/D25,0) -> 0.11366694 | E34: =IF(E25<>0,E33/E25,0) -> 0.12097345 | F34: =IF(F25<>0,F33/F25,0) -> 0.1116055 | G34: =IF(G25<>0,G33/G25,0) -> 0.12053629 | H34: =IF(H25<>0,H33/H25,0) -> 0.10485442 | I34: =IF(I25<>0,I33/I25,0) -> 0.11737896 | J34: =IF(J25<>0,J33/J25,0) -> 0.10401119 | K34: =IF(K25<>0,K33/K25,0) -> 0.087023987 | ... P34: =IF(P25<>0,P33/P25,0) -> 0.1126799
B35: G - 459000 - OTHER EXPENSES | C35: Profit and Loss | D35: =(_xll.DBR("CXMD:FTM_DATA_BALANCE_SHEET","Total_Customer_Supplier",D$21,$C$19,ori,"TOTAL PRODUCT","B-451010",$C$20,"Amount_BS")/1000)+(_xll.DBR("CXMD:FTM_DATA_BALANCE_SHEET","Total_Customer_Supplier",D$21,$C$19,ori,"TOTAL PRODUCT","B-451020",$C$20,"Amount_BS")/1000)+(_xll.DBR("CXMD:FTM_DATA_BALANCE_SHEET","Total_Customer_Supplier",D$21,$C$19,ori,"TOTAL PRODUCT","B-451030",$C$20,"Amount_BS")/1000)+(_xll.DBR("CXMD:FTM_DATA_BALANCE_SHEET","Total_Customer_Supplier",D$21,$C$19,ori,"TOTAL PRODUCT","B-451110",$C$20,"Amount_BS")/1000)+(_xll.DBR("CXMD:FTM_DATA_BALANCE_SHEET","Total_Customer_Supplier",D$21,$C$19,ori,"TOTAL PRODUCT","B-451210",$C$20,"Amount_BS")/1000)+(_xll.DBR("CXMD:FTM_DATA_BALANCE_SHEET","Total_Customer_Supplier",D$21,$C$19,ori,"TOTAL PRODUCT","B-451220",$C$20,"Amount_BS")/1000)+(_xll.DBR("CXMD:FTM_DATA_BALANCE_SHEET","Total_Customer_Supplier",D$21,$C$19,ori,"TOTAL PRODUCT","B-451310",$C$20,"Amount_BS")/1000)+(_xll.DBR("CXMD:FTM_DATA_BALANCE_SHEET","Total_Customer_Supplier",D$21,$C$19,ori,"TOTAL PRODUCT","B-451450",$C$20,"Amount_BS")/1000)+(_xll.DBR("CXMD:FTM_DATA_BALANCE_SHEET","Total_Customer_Supplier",D$21,$C$19,ori,"TOTAL PRODUCT","B-451510",$C$20,"Amount_BS")/1000)+(_xll.DBR("CXMD:FTM_DATA_BALANCE_SHEET","Total_Customer_Supplier",D$21,$C$19,ori,"TOTAL PRODUCT","B-451610",$C$20,"Amount_BS")/1000)+(_xll.DBR("CXMD:FTM_DATA_BALANCE_SHEET","Total_Customer_Supplier",D$21,$C$19,ori,"TOTAL PRODUCT","B-451620",$C$20,"Amount_BS")/1000) -> 29278.132 | E35: =(_xll.DBR("CXMD:FTM_DATA_BALANCE_SHEET","Total_Customer_Supplier",E$21,$C$19,ori,"TOTAL PRODUCT","B-451010",$C$20,"Amount_BS")/1000)+(_xll.DBR("CXMD:FTM_DATA_BALANCE_SHEET","Total_Customer_Supplier",E$21,$C$19,ori,"TOTAL PRODUCT","B-451020",$C$20,"Amount_BS")/1000)+(_xll.DBR("CXMD:FTM_DATA_BALANCE_SHEET","Total_Customer_Supplier",E$21,$C$19,ori,"TOTAL PRODUCT","B-451030",$C$20,"Amount_BS")/1000)+(_xll.DBR("CXMD:FTM_DATA_BALANCE_SHEET","Total_Customer_Supplier",E$21,$C$19,ori,"TOTAL PRODUCT","B-451110",$C$20,"Amount_BS")/1000)+(_xll.DBR("CXMD:FTM_DATA_BALANCE_SHEET","Total_Customer_Supplier",E$21,$C$19,ori,"TOTAL PRODUCT","B-451210",$C$20,"Amount_BS")/1000)+(_xll.DBR("CXMD:FTM_DATA_BALANCE_SHEET","Total_Customer_Supplier",E$21,$C$19,ori,"TOTAL PRODUCT","B-451220",$C$20,"Amount_BS")/1000)+(_xll.DBR("CXMD:FTM_DATA_BALANCE_SHEET","Total_Customer_Supplier",E$21,$C$19,ori,"TOTAL PRODUCT","B-451310",$C$20,"Amount_BS")/1000)+(_xll.DBR("CXMD:FTM_DATA_BALANCE_SHEET","Total_Customer_Supplier",E$21,$C$19,ori,"TOTAL PRODUCT","B-451450",$C$20,"Amount_BS")/1000)+(_xll.DBR("CXMD:FTM_DATA_BALANCE_SHEET","Total_Customer_Supplier",E$21,$C$19,ori,"TOTAL PRODUCT","B-451510",$C$20,"Amount_BS")/1000)+(_xll.DBR("CXMD:FTM_DATA_BALANCE_SHEET","Total_Customer_Supplier",E$21,$C$19,ori,"TOTAL PRODUCT","B-451610",$C$20,"Amount_BS")/1000)+(_xll.DBR("CXMD:FTM_DATA_BALANCE_SHEET","Total_Customer_Supplier",E$21,$C$19,ori,"TOTAL PRODUCT","B-451620",$C$20,"Amount_BS")/1000) -> 26426.217 | F35: =(_xll.DBR("CXMD:FTM_DATA_BALANCE_SHEET","Total_Customer_Supplier",F$21,$C$19,ori,"TOTAL PRODUCT","B-451010",$C$20,"Amount_BS")/1000)+(_xll.DBR("CXMD:FTM_DATA_BALANCE_SHEET","Total_Customer_Supplier",F$21,$C$19,ori,"TOTAL PRODUCT","B-451020",$C$20,"Amount_BS")/1000)+(_xll.DBR("CXMD:FTM_DATA_BALANCE_SHEET","Total_Customer_Supplier",F$21,$C$19,ori,"TOTAL PRODUCT","B-451030",$C$20,"Amount_BS")/1000)+(_xll.DBR("CXMD:FTM_DATA_BALANCE_SHEET","Total_Customer_Supplier",F$21,$C$19,ori,"TOTAL PRODUCT","B-451110",$C$20,"Amount_BS")/1000)+(_xll.DBR("CXMD:FTM_DATA_BALANCE_SHEET","Total_Customer_Supplier",F$21,$C$19,ori,"TOTAL PRODUCT","B-451210",$C$20,"Amount_BS")/1000)+(_xll.DBR("CXMD:FTM_DATA_BALANCE_SHEET","Total_Customer_Supplier",F$21,$C$19,ori,"TOTAL PRODUCT","B-451220",$C$20,"Amount_BS")/1000)+(_xll.DBR("CXMD:FTM_DATA_BALANCE_SHEET","Total_Customer_Supplier",F$21,$C$19,ori,"TOTAL PRODUCT","B-451310",$C$20,"Amount_BS")/1000)+(_xll.DBR("CXMD:FTM_DATA_BALANCE_SHEET","Total_Customer_Supplier",F$21,$C$19,ori,"TOTAL PRODUCT","B-451450",$C$20,"Amount_BS")/1000)+(_xll.DBR("CXMD:FTM_DATA_BALANCE_SHEET","Total_Customer_Supplier",F$21,$C$19,ori,"TOTAL PRODUCT","B-451510",$C$20,"Amount_BS")/1000)+(_xll.DBR("CXMD:FTM_DATA_BALANCE_SHEET","Total_Customer_Supplier",F$21,$C$19,ori,"TOTAL PRODUCT","B-451610",$C$20,"Amount_BS")/1000)+(_xll.DBR("CXMD:FTM_DATA_BALANCE_SHEET","Total_Customer_Supplier",F$21,$C$19,ori,"TOTAL PRODUCT","B-451620",$C$20,"Amount_BS")/1000) -> 33087.795 | G35: =(_xll.DBR("CXMD:FTM_DATA_BALANCE_SHEET","Total_Customer_Supplier",G$21,$C$19,ori,"TOTAL PRODUCT","B-451010",$C$20,"Amount_BS")/1000)+(_xll.DBR("CXMD:FTM_DATA_BALANCE_SHEET","Total_Customer_Supplier",G$21,$C$19,ori,"TOTAL PRODUCT","B-451020",$C$20,"Amount_BS")/1000)+(_xll.DBR("CXMD:FTM_DATA_BALANCE_SHEET","Total_Customer_Supplier",G$21,$C$19,ori,"TOTAL PRODUCT","B-451030",$C$20,"Amount_BS")/1000)+(_xll.DBR("CXMD:FTM_DATA_BALANCE_SHEET","Total_Customer_Supplier",G$21,$C$19,ori,"TOTAL PRODUCT","B-451110",$C$20,"Amount_BS")/1000)+(_xll.DBR("CXMD:FTM_DATA_BALANCE_SHEET","Total_Customer_Supplier",G$21,$C$19,ori,"TOTAL PRODUCT","B-451210",$C$20,"Amount_BS")/1000)+(_xll.DBR("CXMD:FTM_DATA_BALANCE_SHEET","Total_Customer_Supplier",G$21,$C$19,ori,"TOTAL PRODUCT","B-451220",$C$20,"Amount_BS")/1000)+(_xll.DBR("CXMD:FTM_DATA_BALANCE_SHEET","Total_Customer_Supplier",G$21,$C$19,ori,"TOTAL PRODUCT","B-451310",$C$20,"Amount_BS")/1000)+(_xll.DBR("CXMD:FTM_DATA_BALANCE_SHEET","Total_Customer_Supplier",G$21,$C$19,ori,"TOTAL PRODUCT","B-451450",$C$20,"Amount_BS")/1000)+(_xll.DBR("CXMD:FTM_DATA_BALANCE_SHEET","Total_Customer_Supplier",G$21,$C$19,ori,"TOTAL PRODUCT","B-451510",$C$20,"Amount_BS")/1000)+(_xll.DBR("CXMD:FTM_DATA_BALANCE_SHEET","Total_Customer_Supplier",G$21,$C$19,ori,"TOTAL PRODUCT","B-451610",$C$20,"Amount_BS")/1000)+(_xll.DBR("CXMD:FTM_DATA_BALANCE_SHEET","Total_Customer_Supplier",G$21,$C$19,ori,"TOTAL PRODUCT","B-451620",$C$20,"Amount_BS")/1000) -> 31767.686 | H35: =(_xll.DBR("CXMD:FTM_DATA_BALANCE_SHEET","Total_Customer_Supplier",H$21,$C$19,ori,"TOTAL PRODUCT","B-451010",$C$20,"Amount_BS")/1000)+(_xll.DBR("CXMD:FTM_DATA_BALANCE_SHEET","Total_Customer_Supplier",H$21,$C$19,ori,"TOTAL PRODUCT","B-451020",$C$20,"Amount_BS")/1000)+(_xll.DBR("CXMD:FTM_DATA_BALANCE_SHEET","Total_Customer_Supplier",H$21,$C$19,ori,"TOTAL PRODUCT","B-451030",$C$20,"Amount_BS")/1000)+(_xll.DBR("CXMD:FTM_DATA_BALANCE_SHEET","Total_Customer_Supplier",H$21,$C$19,ori,"TOTAL PRODUCT","B-451110",$C$20,"Amount_BS")/1000)+(_xll.DBR("CXMD:FTM_DATA_BALANCE_SHEET","Total_Customer_Supplier",H$21,$C$19,ori,"TOTAL PRODUCT","B-451210",$C$20,"Amount_BS")/1000)+(_xll.DBR("CXMD:FTM_DATA_BALANCE_SHEET","Total_Customer_Supplier",H$21,$C$19,ori,"TOTAL PRODUCT","B-451220",$C$20,"Amount_BS")/1000)+(_xll.DBR("CXMD:FTM_DATA_BALANCE_SHEET","Total_Customer_Supplier",H$21,$C$19,ori,"TOTAL PRODUCT","B-451310",$C$20,"Amount_BS")/1000)+(_xll.DBR("CXMD:FTM_DATA_BALANCE_SHEET","Total_Customer_Supplier",H$21,$C$19,ori,"TOTAL PRODUCT","B-451450",$C$20,"Amount_BS")/1000)+(_xll.DBR("CXMD:FTM_DATA_BALANCE_SHEET","Total_Customer_Supplier",H$21,$C$19,ori,"TOTAL PRODUCT","B-451510",$C$20,"Amount_BS")/1000)+(_xll.DBR("CXMD:FTM_DATA_BALANCE_SHEET","Total_Customer_Supplier",H$21,$C$19,ori,"TOTAL PRODUCT","B-451610",$C$20,"Amount_BS")/1000)+(_xll.DBR("CXMD:FTM_DATA_BALANCE_SHEET","Total_Customer_Supplier",H$21,$C$19,ori,"TOTAL PRODUCT","B-451620",$C$20,"Amount_BS")/1000) -> 32533.924 | I35: =(_xll.DBR("CXMD:FTM_DATA_BALANCE_SHEET","Total_Customer_Supplier",I$21,$C$19,ori,"TOTAL PRODUCT","B-451010",$C$20,"Amount_BS")/1000)+(_xll.DBR("CXMD:FTM_DATA_BALANCE_SHEET","Total_Customer_Supplier",I$21,$C$19,ori,"TOTAL PRODUCT","B-451020",$C$20,"Amount_BS")/1000)+(_xll.DBR("CXMD:FTM_DATA_BALANCE_SHEET","Total_Customer_Supplier",I$21,$C$19,ori,"TOTAL PRODUCT","B-451030",$C$20,"Amount_BS")/1000)+(_xll.DBR("CXMD:FTM_DATA_BALANCE_SHEET","Total_Customer_Supplier",I$21,$C$19,ori,"TOTAL PRODUCT","B-451110",$C$20,"Amount_BS")/1000)+(_xll.DBR("CXMD:FTM_DATA_BALANCE_SHEET","Total_Customer_Supplier",I$21,$C$19,ori,"TOTAL PRODUCT","B-451210",$C$20,"Amount_BS")/1000)+(_xll.DBR("CXMD:FTM_DATA_BALANCE_SHEET","Total_Customer_Supplier",I$21,$C$19,ori,"TOTAL PRODUCT","B-451220",$C$20,"Amount_BS")/1000)+(_xll.DBR("CXMD:FTM_DATA_BALANCE_SHEET","Total_Customer_Supplier",I$21,$C$19,ori,"TOTAL PRODUCT","B-451310",$C$20,"Amount_BS")/1000)+(_xll.DBR("CXMD:FTM_DATA_BALANCE_SHEET","Total_Customer_Supplier",I$21,$C$19,ori,"TOTAL PRODUCT","B-451450",$C$20,"Amount_BS")/1000)+(_xll.DBR("CXMD:FTM_DATA_BALANCE_SHEET","Total_Customer_Supplier",I$21,$C$19,ori,"TOTAL PRODUCT","B-451510",$C$20,"Amount_BS")/1000)+(_xll.DBR("CXMD:FTM_DATA_BALANCE_SHEET","Total_Customer_Supplier",I$21,$C$19,ori,"TOTAL PRODUCT","B-451610",$C$20,"Amount_BS")/1000)+(_xll.DBR("CXMD:FTM_DATA_BALANCE_SHEET","Total_Customer_Supplier",I$21,$C$19,ori,"TOTAL PRODUCT","B-451620",$C$20,"Amount_BS")/1000) -> 30905.344 | J35: =(_xll.DBR("CXMD:FTM_DATA_BALANCE_SHEET","Total_Customer_Supplier",J$21,$C$19,ori,"TOTAL PRODUCT","B-451010",$C$20,"Amount_BS")/1000)+(_xll.DBR("CXMD:FTM_DATA_BALANCE_SHEET","Total_Customer_Supplier",J$21,$C$19,ori,"TOTAL PRODUCT","B-451020",$C$20,"Amount_BS")/1000)+(_xll.DBR("CXMD:FTM_DATA_BALANCE_SHEET","Total_Customer_Supplier",J$21,$C$19,ori,"TOTAL PRODUCT","B-451030",$C$20,"Amount_BS")/1000)+(_xll.DBR("CXMD:FTM_DATA_BALANCE_SHEET","Total_Customer_Supplier",J$21,$C$19,ori,"TOTAL PRODUCT","B-451110",$C$20,"Amount_BS")/1000)+(_xll.DBR("CXMD:FTM_DATA_BALANCE_SHEET","Total_Customer_Supplier",J$21,$C$19,ori,"TOTAL PRODUCT","B-451210",$C$20,"Amount_BS")/1000)+(_xll.DBR("CXMD:FTM_DATA_BALANCE_SHEET","Total_Customer_Supplier",J$21,$C$19,ori,"TOTAL PRODUCT","B-451220",$C$20,"Amount_BS")/1000)+(_xll.DBR("CXMD:FTM_DATA_BALANCE_SHEET","Total_Customer_Supplier",J$21,$C$19,ori,"TOTAL PRODUCT","B-451310",$C$20,"Amount_BS")/1000)+(_xll.DBR("CXMD:FTM_DATA_BALANCE_SHEET","Total_Customer_Supplier",J$21,$C$19,ori,"TOTAL PRODUCT","B-451450",$C$20,"Amount_BS")/1000)+(_xll.DBR("CXMD:FTM_DATA_BALANCE_SHEET","Total_Customer_Supplier",J$21,$C$19,ori,"TOTAL PRODUCT","B-451510",$C$20,"Amount_BS")/1000)+(_xll.DBR("CXMD:FTM_DATA_BALANCE_SHEET","Total_Customer_Supplier",J$21,$C$19,ori,"TOTAL PRODUCT","B-451610",$C$20,"Amount_BS")/1000)+(_xll.DBR("CXMD:FTM_DATA_BALANCE_SHEET","Total_Customer_Supplier",J$21,$C$19,ori,"TOTAL PRODUCT","B-451620",$C$20,"Amount_BS")/1000) -> 28625.412 | K35: =(_xll.DBR("CXMD:FTM_DATA_BALANCE_SHEET","Total_Customer_Supplier",K$21,$C$19,ori,"TOTAL PRODUCT","B-451010",$C$20,"Amount_BS")/1000)+(_xll.DBR("CXMD:FTM_DATA_BALANCE_SHEET","Total_Customer_Supplier",K$21,$C$19,ori,"TOTAL PRODUCT","B-451020",$C$20,"Amount_BS")/1000)+(_xll.DBR("CXMD:FTM_DATA_BALANCE_SHEET","Total_Customer_Supplier",K$21,$C$19,ori,"TOTAL PRODUCT","B-451030",$C$20,"Amount_BS")/1000)+(_xll.DBR("CXMD:FTM_DATA_BALANCE_SHEET","Total_Customer_Supplier",K$21,$C$19,ori,"TOTAL PRODUCT","B-451110",$C$20,"Amount_BS")/1000)+(_xll.DBR("CXMD:FTM_DATA_BALANCE_SHEET","Total_Customer_Supplier",K$21,$C$19,ori,"TOTAL PRODUCT","B-451210",$C$20,"Amount_BS")/1000)+(_xll.DBR("CXMD:FTM_DATA_BALANCE_SHEET","Total_Customer_Supplier",K$21,$C$19,ori,"TOTAL PRODUCT","B-451220",$C$20,"Amount_BS")/1000)+(_xll.DBR("CXMD:FTM_DATA_BALANCE_SHEET","Total_Customer_Supplier",K$21,$C$19,ori,"TOTAL PRODUCT","B-451310",$C$20,"Amount_BS")/1000)+(_xll.DBR("CXMD:FTM_DATA_BALANCE_SHEET","Total_Customer_Supplier",K$21,$C$19,ori,"TOTAL PRODUCT","B-451450",$C$20,"Amount_BS")/1000)+(_xll.DBR("CXMD:FTM_DATA_BALANCE_SHEET","Total_Customer_Supplier",K$21,$C$19,ori,"TOTAL PRODUCT","B-451510",$C$20,"Amount_BS")/1000)+(_xll.DBR("CXMD:FTM_DATA_BALANCE_SHEET","Total_Customer_Supplier",K$21,$C$19,ori,"TOTAL PRODUCT","B-451610",$C$20,"Amount_BS")/1000)+(_xll.DBR("CXMD:FTM_DATA_BALANCE_SHEET","Total_Customer_Supplier",K$21,$C$19,ori,"TOTAL PRODUCT","B-451620",$C$20,"Amount_BS")/1000) -> 26762.875 | ... O35: =(_xll.DBR("CXMD:FTM_DATA_BALANCE_SHEET","Total_Customer_Supplier",O$21,$C$19,ori,"TOTAL PRODUCT","B-451010",$C$20,"Amount_BS")/1000)+(_xll.DBR("CXMD:FTM_DATA_BALANCE_SHEET","Total_Customer_Supplier",O$21,$C$19,ori,"TOTAL PRODUCT","B-451020",$C$20,"Amount_BS")/1000)+(_xll.DBR("CXMD:FTM_DATA_BALANCE_SHEET","Total_Customer_Supplier",O$21,$C$19,ori,"TOTAL PRODUCT","B-451030",$C$20,"Amount_BS")/1000)+(_xll.DBR("CXMD:FTM_DATA_BALANCE_SHEET","Total_Customer_Supplier",O$21,$C$19,ori,"TOTAL PRODUCT","B-451110",$C$20,"Amount_BS")/1000)+(_xll.DBR("CXMD:FTM_DATA_BALANCE_SHEET","Total_Customer_Supplier",O$21,$C$19,ori,"TOTAL PRODUCT","B-451210",$C$20,"Amount_BS")/1000)+(_xll.DBR("CXMD:FTM_DATA_BALANCE_SHEET","Total_Customer_Supplier",O$21,$C$19,ori,"TOTAL PRODUCT","B-451220",$C$20,"Amount_BS")/1000)+(_xll.DBR("CXMD:FTM_DATA_BALANCE_SHEET","Total_Customer_Supplier",O$21,$C$19,ori,"TOTAL PRODUCT","B-451310",$C$20,"Amount_BS")/1000)+(_xll.DBR("CXMD:FTM_DATA_BALANCE_SHEET","Total_Customer_Supplier",O$21,$C$19,ori,"TOTAL PRODUCT","B-451450",$C$20,"Amount_BS")/1000)+(_xll.DBR("CXMD:FTM_DATA_BALANCE_SHEET","Total_Customer_Supplier",O$21,$C$19,ori,"TOTAL PRODUCT","B-451510",$C$20,"Amount_BS")/1000)+(_xll.DBR("CXMD:FTM_DATA_BALANCE_SHEET","Total_Customer_Supplier",O$21,$C$19,ori,"TOTAL PRODUCT","B-451610",$C$20,"Amount_BS")/1000)+(_xll.DBR("CXMD:FTM_DATA_BALANCE_SHEET","Total_Customer_Supplier",O$21,$C$19,ori,"TOTAL PRODUCT","B-451620",$C$20,"Amount_BS")/1000) -> 31415.092 | P35: =SUM(D35:O35) -> 371754.65
C36: % of corporate output | D36: =IF(D25<>0,D35/D25,0) -> 0.088981621 | E36: =IF(E25<>0,E35/E25,0) -> 0.07944128 | F36: =IF(F25<>0,F35/F25,0) -> 0.089021541 | G36: =IF(G25<>0,G35/G25,0) -> 0.099988831 | H36: =IF(H25<>0,H35/H25,0) -> 0.084964092 | I36: =IF(I25<>0,I35/I25,0) -> 0.083232174 | J36: =IF(J25<>0,J35/J25,0) -> 0.079251445 | K36: =IF(K25<>0,K35/K25,0) -> 0.073798271 | ... P36: =IF(P25<>0,P35/P25,0) -> 0.091046334
B37: G - 453900 - FX GAIN/LOSS | C37: Profit and Loss | D37: =_xll.DBR("CXMD:FTM_DATA_BALANCE_SHEET","Total_Customer_Supplier",D$21,$C$19,ori,"TOTAL PRODUCT","B-453010",$C$20,"Amount_BS")/1000 -> -14389.183 | E37: =_xll.DBR("CXMD:FTM_DATA_BALANCE_SHEET","Total_Customer_Supplier",E$21,$C$19,ori,"TOTAL PRODUCT","B-453010",$C$20,"Amount_BS")/1000 -> 4247.0622 | F37: =_xll.DBR("CXMD:FTM_DATA_BALANCE_SHEET","Total_Customer_Supplier",F$21,$C$19,ori,"TOTAL PRODUCT","B-453010",$C$20,"Amount_BS")/1000 -> 2508.6431 | G37: =_xll.DBR("CXMD:FTM_DATA_BALANCE_SHEET","Total_Customer_Supplier",G$21,$C$19,ori,"TOTAL PRODUCT","B-453010",$C$20,"Amount_BS")/1000 -> 599.29278 | H37: =_xll.DBR("CXMD:FTM_DATA_BALANCE_SHEET","Total_Customer_Supplier",H$21,$C$19,ori,"TOTAL PRODUCT","B-453010",$C$20,"Amount_BS")/1000 -> -466.32202 | I37: =_xll.DBR("CXMD:FTM_DATA_BALANCE_SHEET","Total_Customer_Supplier",I$21,$C$19,ori,"TOTAL PRODUCT","B-453010",$C$20,"Amount_BS")/1000 -> 96.67575 | J37: =_xll.DBR("CXMD:FTM_DATA_BALANCE_SHEET","Total_Customer_Supplier",J$21,$C$19,ori,"TOTAL PRODUCT","B-453010",$C$20,"Amount_BS")/1000 -> 2041.2399 | K37: =_xll.DBR("CXMD:FTM_DATA_BALANCE_SHEET","Total_Customer_Supplier",K$21,$C$19,ori,"TOTAL PRODUCT","B-453010",$C$20,"Amount_BS")/1000 -> -1527.4297 | ... O37: =_xll.DBR("CXMD:FTM_DATA_BALANCE_SHEET","Total_Customer_Supplier",O$21,$C$19,ori,"TOTAL PRODUCT","B-453010",$C$20,"Amount_BS")/1000 -> 2811.9654 | P37: =SUM(D37:O37) -> -3499.1707
B38: G - 479000 - DEPREC. PROV. | C38: Profit and Loss | D38: =(_xll.DBR("CXMD:FTM_DATA_BALANCE_SHEET","Total_Customer_Supplier",D$21,$C$19,ori,"TOTAL PRODUCT","B-470010",$C$20,"Amount_BS")/1000)+(_xll.DBR("CXMD:FTM_DATA_BALANCE_SHEET","Total_Customer_Supplier",D$21,$C$19,ori,"TOTAL PRODUCT","B-475010",$C$20,"Amount_BS")/1000) -> 3386.485 | E38: =(_xll.DBR("CXMD:FTM_DATA_BALANCE_SHEET","Total_Customer_Supplier",E$21,$C$19,ori,"TOTAL PRODUCT","B-470010",$C$20,"Amount_BS")/1000)+(_xll.DBR("CXMD:FTM_DATA_BALANCE_SHEET","Total_Customer_Supplier",E$21,$C$19,ori,"TOTAL PRODUCT","B-475010",$C$20,"Amount_BS")/1000) -> 3446.382 | F38: =(_xll.DBR("CXMD:FTM_DATA_BALANCE_SHEET","Total_Customer_Supplier",F$21,$C$19,ori,"TOTAL PRODUCT","B-470010",$C$20,"Amount_BS")/1000)+(_xll.DBR("CXMD:FTM_DATA_BALANCE_SHEET","Total_Customer_Supplier",F$21,$C$19,ori,"TOTAL PRODUCT","B-475010",$C$20,"Amount_BS")/1000) -> 3248.5829 | G38: =(_xll.DBR("CXMD:FTM_DATA_BALANCE_SHEET","Total_Customer_Supplier",G$21,$C$19,ori,"TOTAL PRODUCT","B-470010",$C$20,"Amount_BS")/1000)+(_xll.DBR("CXMD:FTM_DATA_BALANCE_SHEET","Total_Customer_Supplier",G$21,$C$19,ori,"TOTAL PRODUCT","B-475010",$C$20,"Amount_BS")/1000) -> 3315.1649 | H38: =(_xll.DBR("CXMD:FTM_DATA_BALANCE_SHEET","Total_Customer_Supplier",H$21,$C$19,ori,"TOTAL PRODUCT","B-470010",$C$20,"Amount_BS")/1000)+(_xll.DBR("CXMD:FTM_DATA_BALANCE_SHEET","Total_Customer_Supplier",H$21,$C$19,ori,"TOTAL PRODUCT","B-475010",$C$20,"Amount_BS")/1000) -> 3356.0762 | I38: =(_xll.DBR("CXMD:FTM_DATA_BALANCE_SHEET","Total_Customer_Supplier",I$21,$C$19,ori,"TOTAL PRODUCT","B-470010",$C$20,"Amount_BS")/1000)+(_xll.DBR("CXMD:FTM_DATA_BALANCE_SHEET","Total_Customer_Supplier",I$21,$C$19,ori,"TOTAL PRODUCT","B-475010",$C$20,"Amount_BS")/1000) -> 3390.1403 | J38: =(_xll.DBR("CXMD:FTM_DATA_BALANCE_SHEET","Total_Customer_Supplier",J$21,$C$19,ori,"TOTAL PRODUCT","B-470010",$C$20,"Amount_BS")/1000)+(_xll.DBR("CXMD:FTM_DATA_BALANCE_SHEET","Total_Customer_Supplier",J$21,$C$19,ori,"TOTAL PRODUCT","B-475010",$C$20,"Amount_BS")/1000) -> 3385.8418 | K38: =(_xll.DBR("CXMD:FTM_DATA_BALANCE_SHEET","Total_Customer_Supplier",K$21,$C$19,ori,"TOTAL PRODUCT","B-470010",$C$20,"Amount_BS")/1000)+(_xll.DBR("CXMD:FTM_DATA_BALANCE_SHEET","Total_Customer_Supplier",K$21,$C$19,ori,"TOTAL PRODUCT","B-475010",$C$20,"Amount_BS")/1000) -> 3432.8227 | ... O38: =(_xll.DBR("CXMD:FTM_DATA_BALANCE_SHEET","Total_Customer_Supplier",O$21,$C$19,ori,"TOTAL PRODUCT","B-470010",$C$20,"Amount_BS")/1000)+(_xll.DBR("CXMD:FTM_DATA_BALANCE_SHEET","Total_Customer_Supplier",O$21,$C$19,ori,"TOTAL PRODUCT","B-475010",$C$20,"Amount_BS")/1000) -> 3300.1832 | P38: =SUM(D38:O38) -> 39702.352
B39: Ebit without Management fees | D39: =D27-D29-D33-D35-D37-D38-D28 -> 86917.47 | E39: =E27-E29-E33-E35-E37-E38-E28 -> 70173.044 | F39: =F27-F29-F33-F35-F37-F38-F28 -> 42198.06 | G39: =G27-G29-G33-G35-G37-G38-G28 -> 36734.624 | H39: =H27-H29-H33-H35-H37-H38-H28 -> 68398.344 | I39: =I27-I29-I33-I35-I37-I38-I28 -> 62307.064 | J39: =J27-J29-J33-J35-J37-J38-J28 -> 70679.445 | K39: =K27-K29-K33-K35-K37-K38-K28 -> 106805.41 | ... O39: =O27-O29-O33-O35-O37-O38-O28 -> 16398.408 | P39: =SUM(D39:O39) -> 693916.26
C40: % of net sales | D40: =IF(D23<>0,D39/D23,0) -> 0.24154242 | E40: =IF(E23<>0,E39/E23,0) -> 0.20617793 | F40: =IF(F23<>0,F39/F23,0) -> 0.11924864 | G40: =IF(G23<>0,G39/G23,0) -> 0.11364577 | H40: =IF(H23<>0,H39/H23,0) -> 0.19029443 | I40: =IF(I23<>0,I39/I23,0) -> 0.16401183 | J40: =IF(J23<>0,J39/J23,0) -> 0.18595233 | K40: =IF(K23<>0,K39/K23,0) -> 0.29433219 | ... P40: =IF(P23<>0,P39/P23,0) -> 0.170384
B41: G - 569199 - OTHER INCOME/EXPENSES | C41: Profit and Loss | D41: =(_xll.DBR("CXMD:FTM_DATA_BALANCE_SHEET","Total_Customer_Supplier",D$21,$C$19,ori,"TOTAL PRODUCT","B-560020",$C$20,"Amount_BS")/1000)+(_xll.DBR("CXMD:FTM_DATA_BALANCE_SHEET","Total_Customer_Supplier",D$21,$C$19,ori,"TOTAL PRODUCT","B-561010",$C$20,"Amount_BS")/1000) -> 462.46413 | E41: =(_xll.DBR("CXMD:FTM_DATA_BALANCE_SHEET","Total_Customer_Supplier",E$21,$C$19,ori,"TOTAL PRODUCT","B-560020",$C$20,"Amount_BS")/1000)+(_xll.DBR("CXMD:FTM_DATA_BALANCE_SHEET","Total_Customer_Supplier",E$21,$C$19,ori,"TOTAL PRODUCT","B-561010",$C$20,"Amount_BS")/1000) -> 462.46413 | F41: =(_xll.DBR("CXMD:FTM_DATA_BALANCE_SHEET","Total_Customer_Supplier",F$21,$C$19,ori,"TOTAL PRODUCT","B-560020",$C$20,"Amount_BS")/1000)+(_xll.DBR("CXMD:FTM_DATA_BALANCE_SHEET","Total_Customer_Supplier",F$21,$C$19,ori,"TOTAL PRODUCT","B-561010",$C$20,"Amount_BS")/1000) -> 462.46413 | G41: =(_xll.DBR("CXMD:FTM_DATA_BALANCE_SHEET","Total_Customer_Supplier",G$21,$C$19,ori,"TOTAL PRODUCT","B-560020",$C$20,"Amount_BS")/1000)+(_xll.DBR("CXMD:FTM_DATA_BALANCE_SHEET","Total_Customer_Supplier",G$21,$C$19,ori,"TOTAL PRODUCT","B-561010",$C$20,"Amount_BS")/1000) -> 799.42713 | H41: =(_xll.DBR("CXMD:FTM_DATA_BALANCE_SHEET","Total_Customer_Supplier",H$21,$C$19,ori,"TOTAL PRODUCT","B-560020",$C$20,"Amount_BS")/1000)+(_xll.DBR("CXMD:FTM_DATA_BALANCE_SHEET","Total_Customer_Supplier",H$21,$C$19,ori,"TOTAL PRODUCT","B-561010",$C$20,"Amount_BS")/1000) -> 462.46413 | I41: =(_xll.DBR("CXMD:FTM_DATA_BALANCE_SHEET","Total_Customer_Supplier",I$21,$C$19,ori,"TOTAL PRODUCT","B-560020",$C$20,"Amount_BS")/1000)+(_xll.DBR("CXMD:FTM_DATA_BALANCE_SHEET","Total_Customer_Supplier",I$21,$C$19,ori,"TOTAL PRODUCT","B-561010",$C$20,"Amount_BS")/1000) -> 462.46413 | J41: =(_xll.DBR("CXMD:FTM_DATA_BALANCE_SHEET","Total_Customer_Supplier",J$21,$C$19,ori,"TOTAL PRODUCT","B-560020",$C$20,"Amount_BS")/1000)+(_xll.DBR("CXMD:FTM_DATA_BALANCE_SHEET","Total_Customer_Supplier",J$21,$C$19,ori,"TOTAL PRODUCT","B-561010",$C$20,"Amount_BS")/1000) -> 462.46413 | K41: =(_xll.DBR("CXMD:FTM_DATA_BALANCE_SHEET","Total_Customer_Supplier",K$21,$C$19,ori,"TOTAL PRODUCT","B-560020",$C$20,"Amount_BS")/1000)+(_xll.DBR("CXMD:FTM_DATA_BALANCE_SHEET","Total_Customer_Supplier",K$21,$C$19,ori,"TOTAL PRODUCT","B-561010",$C$20,"Amount_BS")/1000) -> 462.46413 | ... O41: =(_xll.DBR("CXMD:FTM_DATA_BALANCE_SHEET","Total_Customer_Supplier",O$21,$C$19,ori,"TOTAL PRODUCT","B-560020",$C$20,"Amount_BS")/1000)+(_xll.DBR("CXMD:FTM_DATA_BALANCE_SHEET","Total_Customer_Supplier",O$21,$C$19,ori,"TOTAL PRODUCT","B-561010",$C$20,"Amount_BS")/1000) -> 98.3356 | P41: =SUM(D41:O41) -> 5895.958
B42: Ebit including Management fees | D42: =D39-D41 -> 86455.006 | E42: =E39-E41 -> 69710.58 | F42: =F39-F41 -> 41735.596 | G42: =G39-G41 -> 35935.197 | H42: =H39-H41 -> 67935.88 | I42: =I39-I41 -> 61844.6 | J42: =J39-J41 -> 70216.981 | K42: =K39-K41 -> 106342.95 | ... O42: =O39-O41 -> 16300.072 | P42: =SUM(D42:O42) -> 688020.3
C43: % of net sales | D43: =IF(D23<>0,D42/D23,0) -> 0.24025724 | E43: =IF(E23<>0,E42/E23,0) -> 0.20481915 | F43: =IF(F23<>0,F42/F23,0) -> 0.11794175 | G43: =IF(G23<>0,G42/G23,0) -> 0.11117259 | H43: =IF(H23<>0,H42/H23,0) -> 0.18900778 | I43: =IF(I23<>0,I42/I23,0) -> 0.16279448 | J43: =IF(J23<>0,J42/J23,0) -> 0.18473562 | K43: =IF(K23<>0,K42/K23,0) -> 0.29305774 | ... P43: =IF(P23<>0,P42/P23,0) -> 0.1689363

Sheet P&L Month YTD by CC summary
B18: Origin_Company | C18: =origine -> Total Origin Company | H18: P&L Month YTD _ summary
B19: Actuality | C19: ='P&L Month by CC summary'!C19 -> AC2022
B20: Allocation | C20: ='P&L Month by CC summary'!C20 -> Total Allocation
C21: in K Local Currency | D21: YTD_January | E21: YTD_February | F21: YTD_March | G21: YTD_April | H21: YTD_May | I21: YTD_June | J21: YTD_July | K21: YTD_August | L21: YTD_September | M21: YTD_October | N21: YTD_November | O21: YTD_December
B22: Bucher Account
B23: G - 309000 - NET SALES | C23: Profit and Loss | D23: =_xll.DBR("CXMD:FTM_DATA_BALANCE_SHEET","Total_Customer_Supplier",D$21,$C$19,ori,"TOTAL PRODUCT","B-300010",$C$20,"Amount_BS")*-1/1000 -> 359843.49 | E23: =_xll.DBR("CXMD:FTM_DATA_BALANCE_SHEET","Total_Customer_Supplier",E$21,$C$19,ori,"TOTAL PRODUCT","B-300010",$C$20,"Amount_BS")*-1/1000 -> 700195.37 | F23: =_xll.DBR("CXMD:FTM_DATA_BALANCE_SHEET","Total_Customer_Supplier",F$21,$C$19,ori,"TOTAL PRODUCT","B-300010",$C$20,"Amount_BS")*-1/1000 -> 1054061.5 | G23: =_xll.DBR("CXMD:FTM_DATA_BALANCE_SHEET","Total_Customer_Supplier",G$21,$C$19,ori,"TOTAL PRODUCT","B-300010",$C$20,"Amount_BS")*-1/1000 -> 1377299.5 | H23: =_xll.DBR("CXMD:FTM_DATA_BALANCE_SHEET","Total_Customer_Supplier",H$21,$C$19,ori,"TOTAL PRODUCT","B-300010",$C$20,"Amount_BS")*-1/1000 -> 1736733.8 | I23: =_xll.DBR("CXMD:FTM_DATA_BALANCE_SHEET","Total_Customer_Supplier",I$21,$C$19,ori,"TOTAL PRODUCT","B-300010",$C$20,"Amount_BS")*-1/1000 -> 2116627.5 | J23: =_xll.DBR("CXMD:FTM_DATA_BALANCE_SHEET","Total_Customer_Supplier",J$21,$C$19,ori,"TOTAL PRODUCT","B-300010",$C$20,"Amount_BS")*-1/1000 -> 2496721.9 | K23: =_xll.DBR("CXMD:FTM_DATA_BALANCE_SHEET","Total_Customer_Supplier",K$21,$C$19,ori,"TOTAL PRODUCT","B-300010",$C$20,"Amount_BS")*-1/1000 -> 2859595.6 | ... O23: =_xll.DBR("CXMD:FTM_DATA_BALANCE_SHEET","Total_Customer_Supplier",O$21,$C$19,ori,"TOTAL PRODUCT","B-300010",$C$20,"Amount_BS")*-1/1000 -> 4072661.1
B24: G - 319000 - NET VARIATION OF STOCK | C24: Profit and Loss | D24: =_xll.DBR("CXMD:FTM_DATA_BALANCE_SHEET","Total_Customer_Supplier",D$21,$C$19,ori,"TOTAL PRODUCT","B-310010",$C$20,"Amount_BS")*-1/1000 -> -30807.778 | E24: =_xll.DBR("CXMD:FTM_DATA_BALANCE_SHEET","Total_Customer_Supplier",E$21,$C$19,ori,"TOTAL PRODUCT","B-310010",$C$20,"Amount_BS")*-1/1000 -> -38508.695 | F24: =_xll.DBR("CXMD:FTM_DATA_BALANCE_SHEET","Total_Customer_Supplier",F$21,$C$19,ori,"TOTAL PRODUCT","B-310010",$C$20,"Amount_BS")*-1/1000 -> -20691.849 | G24: =_xll.DBR("CXMD:FTM_DATA_BALANCE_SHEET","Total_Customer_Supplier",G$21,$C$19,ori,"TOTAL PRODUCT","B-310010",$C$20,"Amount_BS")*-1/1000 -> -26217.428 | H24: =_xll.DBR("CXMD:FTM_DATA_BALANCE_SHEET","Total_Customer_Supplier",H$21,$C$19,ori,"TOTAL PRODUCT","B-310010",$C$20,"Amount_BS")*-1/1000 -> -2737.9111 | I24: =_xll.DBR("CXMD:FTM_DATA_BALANCE_SHEET","Total_Customer_Supplier",I$21,$C$19,ori,"TOTAL PRODUCT","B-310010",$C$20,"Amount_BS")*-1/1000 -> -11316.758 | J24: =_xll.DBR("CXMD:FTM_DATA_BALANCE_SHEET","Total_Customer_Supplier",J$21,$C$19,ori,"TOTAL PRODUCT","B-310010",$C$20,"Amount_BS")*-1/1000 -> -30213.846 | K24: =_xll.DBR("CXMD:FTM_DATA_BALANCE_SHEET","Total_Customer_Supplier",K$21,$C$19,ori,"TOTAL PRODUCT","B-310010",$C$20,"Amount_BS")*-1/1000 -> -30438.473 | ... O24: =_xll.DBR("CXMD:FTM_DATA_BALANCE_SHEET","Total_Customer_Supplier",O$21,$C$19,ori,"TOTAL PRODUCT","B-310010",$C$20,"Amount_BS")*-1/1000 -> 10475.845
B25: G-329000 Corporate output | D25: =D23+D24 -> 329035.72 | E25: =E23+E24 -> 661686.67 | F25: =F23+F24 -> 1033369.7 | G25: =G23+G24 -> 1351082 | H25: =H23+H24 -> 1733995.9 | I25: =I23+I24 -> 2105310.7 | J25: =J23+J24 -> 2466508.1 | K25: =K23+K24 -> 2829157.2 | ... O25: =O23+O24 -> 4083136.9
B26: G - 339000 - OPERATING INCOME | C26: Profit and Loss | D26: =_xll.DBR("CXMD:FTM_DATA_BALANCE_SHEET","Total_Customer_Supplier",D$21,$C$19,ori,"TOTAL PRODUCT","B-330010",$C$20,"Amount_BS")*-1/1000 -> 4042.3655 | E26: =_xll.DBR("CXMD:FTM_DATA_BALANCE_SHEET","Total_Customer_Supplier",E$21,$C$19,ori,"TOTAL PRODUCT","B-330010",$C$20,"Amount_BS")*-1/1000 -> 8583.2908 | F26: =_xll.DBR("CXMD:FTM_DATA_BALANCE_SHEET","Total_Customer_Supplier",F$21,$C$19,ori,"TOTAL PRODUCT","B-330010",$C$20,"Amount_BS")*-1/1000 -> 13431.463 | G26: =_xll.DBR("CXMD:FTM_DATA_BALANCE_SHEET","Total_Customer_Supplier",G$21,$C$19,ori,"TOTAL PRODUCT","B-330010",$C$20,"Amount_BS")*-1/1000 -> 17830.42 | H26: =_xll.DBR("CXMD:FTM_DATA_BALANCE_SHEET","Total_Customer_Supplier",H$21,$C$19,ori,"TOTAL PRODUCT","B-330010",$C$20,"Amount_BS")*-1/1000 -> 22213.297 | I26: =_xll.DBR("CXMD:FTM_DATA_BALANCE_SHEET","Total_Customer_Supplier",I$21,$C$19,ori,"TOTAL PRODUCT","B-330010",$C$20,"Amount_BS")*-1/1000 -> 26939.953 | J26: =_xll.DBR("CXMD:FTM_DATA_BALANCE_SHEET","Total_Customer_Supplier",J$21,$C$19,ori,"TOTAL PRODUCT","B-330010",$C$20,"Amount_BS")*-1/1000 -> 31469.609 | K26: =_xll.DBR("CXMD:FTM_DATA_BALANCE_SHEET","Total_Customer_Supplier",K$21,$C$19,ori,"TOTAL PRODUCT","B-330010",$C$20,"Amount_BS")*-1/1000 -> 35826.213 | ... O26: =_xll.DBR("CXMD:FTM_DATA_BALANCE_SHEET","Total_Customer_Supplier",O$21,$C$19,ori,"TOTAL PRODUCT","B-330010",$C$20,"Amount_BS")*-1/1000 -> 52175.87
B27: REVENUE | D27: =D25+D26 -> 333078.08 | E27: =E25+E26 -> 670269.96 | F27: =F25+F26 -> 1046801.2 | G27: =G25+G26 -> 1368912.5 | H27: =H25+H26 -> 1756209.2 | I27: =I25+I26 -> 2132250.7 | J27: =J25+J26 -> 2497977.7 | K27: =K25+K26 -> 2864983.4 | ... O27: =O25+O26 -> 4135312.8
B28: G - 452000 - VARIATION OF PROVISIONS | C28: Profit and Loss | D28: =(_xll.DBR("CXMD:FTM_DATA_BALANCE_SHEET","Total_Customer_Supplier",D$21,$C$19,ori,"TOTAL PRODUCT","B-452010",$C$20,"Amount_BS")/1000)+(_xll.DBR("CXMD:FTM_DATA_BALANCE_SHEET","Total_Customer_Supplier",D$21,$C$19,ori,"TOTAL PRODUCT","B-452210",$C$20,"Amount_BS")/1000) -> 442.07326 | E28: =(_xll.DBR("CXMD:FTM_DATA_BALANCE_SHEET","Total_Customer_Supplier",E$21,$C$19,ori,"TOTAL PRODUCT","B-452010",$C$20,"Amount_BS")/1000)+(_xll.DBR("CXMD:FTM_DATA_BALANCE_SHEET","Total_Customer_Supplier",E$21,$C$19,ori,"TOTAL PRODUCT","B-452210",$C$20,"Amount_BS")/1000) -> 247.15668 | F28: =(_xll.DBR("CXMD:FTM_DATA_BALANCE_SHEET","Total_Customer_Supplier",F$21,$C$19,ori,"TOTAL PRODUCT","B-452010",$C$20,"Amount_BS")/1000)+(_xll.DBR("CXMD:FTM_DATA_BALANCE_SHEET","Total_Customer_Supplier",F$21,$C$19,ori,"TOTAL PRODUCT","B-452210",$C$20,"Amount_BS")/1000) -> 1860.5594 | G28: =(_xll.DBR("CXMD:FTM_DATA_BALANCE_SHEET","Total_Customer_Supplier",G$21,$C$19,ori,"TOTAL PRODUCT","B-452010",$C$20,"Amount_BS")/1000)+(_xll.DBR("CXMD:FTM_DATA_BALANCE_SHEET","Total_Customer_Supplier",G$21,$C$19,ori,"TOTAL PRODUCT","B-452210",$C$20,"Amount_BS")/1000) -> 3118.3911 | H28: =(_xll.DBR("CXMD:FTM_DATA_BALANCE_SHEET","Total_Customer_Supplier",H$21,$C$19,ori,"TOTAL PRODUCT","B-452010",$C$20,"Amount_BS")/1000)+(_xll.DBR("CXMD:FTM_DATA_BALANCE_SHEET","Total_Customer_Supplier",H$21,$C$19,ori,"TOTAL PRODUCT","B-452210",$C$20,"Amount_BS")/1000) -> 3052.1005 | I28: =(_xll.DBR("CXMD:FTM_DATA_BALANCE_SHEET","Total_Customer_Supplier",I$21,$C$19,ori,"TOTAL PRODUCT","B-452010",$C$20,"Amount_BS")/1000)+(_xll.DBR("CXMD:FTM_DATA_BALANCE_SHEET","Total_Customer_Supplier",I$21,$C$19,ori,"TOTAL PRODUCT","B-452210",$C$20,"Amount_BS")/1000) -> 3596.8589 | J28: =(_xll.DBR("CXMD:FTM_DATA_BALANCE_SHEET","Total_Customer_Supplier",J$21,$C$19,ori,"TOTAL PRODUCT","B-452010",$C$20,"Amount_BS")/1000)+(_xll.DBR("CXMD:FTM_DATA_BALANCE_SHEET","Total_Customer_Supplier",J$21,$C$19,ori,"TOTAL PRODUCT","B-452210",$C$20,"Amount_BS")/1000) -> 5073.9976 | K28: =(_xll.DBR("CXMD:FTM_DATA_BALANCE_SHEET","Total_Customer_Supplier",K$21,$C$19,ori,"TOTAL PRODUCT","B-452010",$C$20,"Amount_BS")/1000)+(_xll.DBR("CXMD:FTM_DATA_BALANCE_SHEET","Total_Customer_Supplier",K$21,$C$19,ori,"TOTAL PRODUCT","B-452210",$C$20,"Amount_BS")/1000) -> 5982.9797 | ... O28: =(_xll.DBR("CXMD:FTM_DATA_BALANCE_SHEET","Total_Customer_Supplier",O$21,$C$19,ori,"TOTAL PRODUCT","B-452010",$C$20,"Amount_BS")/1000)+(_xll.DBR("CXMD:FTM_DATA_BALANCE_SHEET","Total_Customer_Supplier",O$21,$C$19,ori,"TOTAL PRODUCT","B-452210",$C$20,"Amount_BS")/1000) -> 29689.028
B29: Total Material expenses + net var. stock | D29: =(_xll.DBR("CXMD:FTM_DATA_BALANCE_SHEET","Total_Customer_Supplier",D$21,$C$19,ori,"TOTAL PRODUCT","B-401010",$C$20,"Amount_BS")/1000)+(_xll.DBR("CXMD:FTM_DATA_BALANCE_SHEET","Total_Customer_Supplier",D$21,$C$19,ori,"TOTAL PRODUCT","B-401020",$C$20,"Amount_BS")/1000)+(_xll.DBR("CXMD:FTM_DATA_BALANCE_SHEET","Total_Customer_Supplier",D$21,$C$19,ori,"TOTAL PRODUCT","B-402110",$C$20,"Amount_BS")/1000)+(_xll.DBR("CXMD:FTM_DATA_BALANCE_SHEET","Total_Customer_Supplier",D$21,$C$19,ori,"TOTAL PRODUCT","B-402111",$C$20,"Amount_BS")/1000)+(_xll.DBR("CXMD:FTM_DATA_BALANCE_SHEET","Total_Customer_Supplier",D$21,$C$19,ori,"TOTAL PRODUCT","B-407010",$C$20,"Amount_BS")/1000) -> 190042.62 | E29: =(_xll.DBR("CXMD:FTM_DATA_BALANCE_SHEET","Total_Customer_Supplier",E$21,$C$19,ori,"TOTAL PRODUCT","B-401010",$C$20,"Amount_BS")/1000)+(_xll.DBR("CXMD:FTM_DATA_BALANCE_SHEET","Total_Customer_Supplier",E$21,$C$19,ori,"TOTAL PRODUCT","B-401020",$C$20,"Amount_BS")/1000)+(_xll.DBR("CXMD:FTM_DATA_BALANCE_SHEET","Total_Customer_Supplier",E$21,$C$19,ori,"TOTAL PRODUCT","B-402110",$C$20,"Amount_BS")/1000)+(_xll.DBR("CXMD:FTM_DATA_BALANCE_SHEET","Total_Customer_Supplier",E$21,$C$19,ori,"TOTAL PRODUCT","B-402111",$C$20,"Amount_BS")/1000)+(_xll.DBR("CXMD:FTM_DATA_BALANCE_SHEET","Total_Customer_Supplier",E$21,$C$19,ori,"TOTAL PRODUCT","B-407010",$C$20,"Amount_BS")/1000) -> 382894.78 | F29: =(_xll.DBR("CXMD:FTM_DATA_BALANCE_SHEET","Total_Customer_Supplier",F$21,$C$19,ori,"TOTAL PRODUCT","B-401010",$C$20,"Amount_BS")/1000)+(_xll.DBR("CXMD:FTM_DATA_BALANCE_SHEET","Total_Customer_Supplier",F$21,$C$19,ori,"TOTAL PRODUCT","B-401020",$C$20,"Amount_BS")/1000)+(_xll.DBR("CXMD:FTM_DATA_BALANCE_SHEET","Total_Customer_Supplier",F$21,$C$19,ori,"TOTAL PRODUCT","B-402110",$C$20,"Amount_BS")/1000)+(_xll.DBR("CXMD:FTM_DATA_BALANCE_SHEET","Total_Customer_Supplier",F$21,$C$19,ori,"TOTAL PRODUCT","B-402111",$C$20,"Amount_BS")/1000)+(_xll.DBR("CXMD:FTM_DATA_BALANCE_SHEET","Total_Customer_Supplier",F$21,$C$19,ori,"TOTAL PRODUCT","B-407010",$C$20,"Amount_BS")/1000) -> 635287.62 | G29: =(_xll.DBR("CXMD:FTM_DATA_BALANCE_SHEET","Total_Customer_Supplier",G$21,$C$19,ori,"TOTAL PRODUCT","B-401010",$C$20,"Amount_BS")/1000)+(_xll.DBR("CXMD:FTM_DATA_BALANCE_SHEET","Total_Customer_Supplier",G$21,$C$19,ori,"TOTAL PRODUCT","B-401020",$C$20,"Amount_BS")/1000)+(_xll.DBR("CXMD:FTM_DATA_BALANCE_SHEET","Total_Customer_Supplier",G$21,$C$19,ori,"TOTAL PRODUCT","B-402110",$C$20,"Amount_BS")/1000)+(_xll.DBR("CXMD:FTM_DATA_BALANCE_SHEET","Total_Customer_Supplier",G$21,$C$19,ori,"TOTAL PRODUCT","B-402111",$C$20,"Amount_BS")/1000)+(_xll.DBR("CXMD:FTM_DATA_BALANCE_SHEET","Total_Customer_Supplier",G$21,$C$19,ori,"TOTAL PRODUCT","B-407010",$C$20,"Amount_BS")/1000) -> 845428.46 | H29: =(_xll.DBR("CXMD:FTM_DATA_BALANCE_SHEET","Total_Customer_Supplier",H$21,$C$19,ori,"TOTAL PRODUCT","B-401010",$C$20,"Amount_BS")/1000)+(_xll.DBR("CXMD:FTM_DATA_BALANCE_SHEET","Total_Customer_Supplier",H$21,$C$19,ori,"TOTAL PRODUCT","B-401020",$C$20,"Amount_BS")/1000)+(_xll.DBR("CXMD:FTM_DATA_BALANCE_SHEET","Total_Customer_Supplier",H$21,$C$19,ori,"TOTAL PRODUCT","B-402110",$C$20,"Amount_BS")/1000)+(_xll.DBR("CXMD:FTM_DATA_BALANCE_SHEET","Total_Customer_Supplier",H$21,$C$19,ori,"TOTAL PRODUCT","B-402111",$C$20,"Amount_BS")/1000)+(_xll.DBR("CXMD:FTM_DATA_BALANCE_SHEET","Total_Customer_Supplier",H$21,$C$19,ori,"TOTAL PRODUCT","B-407010",$C$20,"Amount_BS")/1000) -> 1088819.2 | I29: =(_xll.DBR("CXMD:FTM_DATA_BALANCE_SHEET","Total_Customer_Supplier",I$21,$C$19,ori,"TOTAL PRODUCT","B-401010",$C$20,"Amount_BS")/1000)+(_xll.DBR("CXMD:FTM_DATA_BALANCE_SHEET","Total_Customer_Supplier",I$21,$C$19,ori,"TOTAL PRODUCT","B-401020",$C$20,"Amount_BS")/1000)+(_xll.DBR("CXMD:FTM_DATA_BALANCE_SHEET","Total_Customer_Supplier",I$21,$C$19,ori,"TOTAL PRODUCT","B-402110",$C$20,"Amount_BS")/1000)+(_xll.DBR("CXMD:FTM_DATA_BALANCE_SHEET","Total_Customer_Supplier",I$21,$C$19,ori,"TOTAL PRODUCT","B-402111",$C$20,"Amount_BS")/1000)+(_xll.DBR("CXMD:FTM_DATA_BALANCE_SHEET","Total_Customer_Supplier",I$21,$C$19,ori,"TOTAL PRODUCT","B-407010",$C$20,"Amount_BS")/1000) -> 1324032.2 | J29: =(_xll.DBR("CXMD:FTM_DATA_BALANCE_SHEET","Total_Customer_Supplier",J$21,$C$19,ori,"TOTAL PRODUCT","B-401010",$C$20,"Amount_BS")/1000)+(_xll.DBR("CXMD:FTM_DATA_BALANCE_SHEET","Total_Customer_Supplier",J$21,$C$19,ori,"TOTAL PRODUCT","B-401020",$C$20,"Amount_BS")/1000)+(_xll.DBR("CXMD:FTM_DATA_BALANCE_SHEET","Total_Customer_Supplier",J$21,$C$19,ori,"TOTAL PRODUCT","B-402110",$C$20,"Amount_BS")/1000)+(_xll.DBR("CXMD:FTM_DATA_BALANCE_SHEET","Total_Customer_Supplier",J$21,$C$19,ori,"TOTAL PRODUCT","B-402111",$C$20,"Amount_BS")/1000)+(_xll.DBR("CXMD:FTM_DATA_BALANCE_SHEET","Total_Customer_Supplier",J$21,$C$19,ori,"TOTAL PRODUCT","B-407010",$C$20,"Amount_BS")/1000) -> 1545981.6 | K29: =(_xll.DBR("CXMD:FTM_DATA_BALANCE_SHEET","Total_Customer_Supplier",K$21,$C$19,ori,"TOTAL PRODUCT","B-401010",$C$20,"Amount_BS")/1000)+(_xll.DBR("CXMD:FTM_DATA_BALANCE_SHEET","Total_Customer_Supplier",K$21,$C$19,ori,"TOTAL PRODUCT","B-401020",$C$20,"Amount_BS")/1000)+(_xll.DBR("CXMD:FTM_DATA_BALANCE_SHEET","Total_Customer_Supplier",K$21,$C$19,ori,"TOTAL PRODUCT","B-402110",$C$20,"Amount_BS")/1000)+(_xll.DBR("CXMD:FTM_DATA_BALANCE_SHEET","Total_Customer_Supplier",K$21,$C$19,ori,"TOTAL PRODUCT","B-402111",$C$20,"Amount_BS")/1000)+(_xll.DBR("CXMD:FTM_DATA_BALANCE_SHEET","Total_Customer_Supplier",K$21,$C$19,ori,"TOTAL PRODUCT","B-407010",$C$20,"Amount_BS")/1000) -> 1745045.4 | ... O29: =(_xll.DBR("CXMD:FTM_DATA_BALANCE_SHEET","Total_Customer_Supplier",O$21,$C$19,ori,"TOTAL PRODUCT","B-401010",$C$20,"Amount_BS")/1000)+(_xll.DBR("CXMD:FTM_DATA_BALANCE_SHEET","Total_Customer_Supplier",O$21,$C$19,ori,"TOTAL PRODUCT","B-401020",$C$20,"Amount_BS")/1000)+(_xll.DBR("CXMD:FTM_DATA_BALANCE_SHEET","Total_Customer_Supplier",O$21,$C$19,ori,"TOTAL PRODUCT","B-402110",$C$20,"Amount_BS")/1000)+(_xll.DBR("CXMD:FTM_DATA_BALANCE_SHEET","Total_Customer_Supplier",O$21,$C$19,ori,"TOTAL PRODUCT","B-402111",$C$20,"Amount_BS")/1000)+(_xll.DBR("CXMD:FTM_DATA_BALANCE_SHEET","Total_Customer_Supplier",O$21,$C$19,ori,"TOTAL PRODUCT","B-407010",$C$20,"Amount_BS")/1000) -> 2543662.2
C30: % of corporate output | D30: =IF(D25<>0,D29/D25,0) -> 0.57757445 | E30: =IF(E25<>0,E29/E25,0) -> 0.57866479 | F30: =IF(F25<>0,F29/F25,0) -> 0.61477284 | G30: =IF(G25<>0,G29/G25,0) -> 0.62574176 | H30: =IF(H25<>0,H29/H25,0) -> 0.62792492 | I30: =IF(I25<>0,I29/I25,0) -> 0.62890109 | J30: =IF(J25<>0,J29/J25,0) -> 0.62678958 | K30: =IF(K25<>0,K29/K25,0) -> 0.61680753 | ... O30: =IF(O25<>0,O29/O25,0) -> 0.62296765
B31: G-429999-GROSS MARGIN | D31: =D27-D29 -> 143035.46 | E31: =E27-E29 -> 287375.18 | F31: =F27-F29 -> 411513.54 | G31: =G27-G29 -> 523484 | H31: =H27-H29 -> 667389.94 | I31: =I27-I29 -> 808218.47 | J31: =J27-J29 -> 951996.12 | K31: =K27-K29 -> 1119937.9 | ... O31: =O27-O29 -> 1591650.6
C32: % of corporate output | D32: =IF(D25<>0,D31/D25,0) -> 0.43471105 | E32: =IF(E25<>0,E31/E25,0) -> 0.43430705 | F32: =IF(F25<>0,F31/F25,0) -> 0.39822489 | G32: =IF(G25<>0,G31/G25,0) -> 0.38745538 | H32: =IF(H25<>0,H31/H25,0) -> 0.38488554 | I32: =IF(I25<>0,I31/I25,0) -> 0.3838951 | J32: =IF(J25<>0,J31/J25,0) -> 0.38596919 | K32: =IF(K25<>0,K31/K25,0) -> 0.39585569 | ... O32: =IF(O25<>0,O31/O25,0) -> 0.38981073
B33: G - 439000 - PERSONNEL COSTS | C33: Profit and Loss | D33: =(_xll.DBR("CXMD:FTM_DATA_BALANCE_SHEET","Total_Customer_Supplier",D$21,$C$19,ori,"TOTAL PRODUCT","B-430010",$C$20,"Amount_BS")/1000)+(_xll.DBR("CXMD:FTM_DATA_BALANCE_SHEET","Total_Customer_Supplier",D$21,$C$19,ori,"TOTAL PRODUCT","B-430040",$C$20,"Amount_BS")/1000)+(_xll.DBR("CXMD:FTM_DATA_BALANCE_SHEET","Total_Customer_Supplier",D$21,$C$19,ori,"TOTAL PRODUCT","B-431040",$C$20,"Amount_BS")/1000)+(_xll.DBR("CXMD:FTM_DATA_BALANCE_SHEET","Total_Customer_Supplier",D$21,$C$19,ori,"TOTAL PRODUCT","B-437010",$C$20,"Amount_BS")/1000)+(_xll.DBR("CXMD:FTM_DATA_BALANCE_SHEET","Total_Customer_Supplier",D$21,$C$19,ori,"TOTAL PRODUCT","B-438010",$C$20,"Amount_BS")/1000) -> 37400.484 | E33: =(_xll.DBR("CXMD:FTM_DATA_BALANCE_SHEET","Total_Customer_Supplier",E$21,$C$19,ori,"TOTAL PRODUCT","B-430010",$C$20,"Amount_BS")/1000)+(_xll.DBR("CXMD:FTM_DATA_BALANCE_SHEET","Total_Customer_Supplier",E$21,$C$19,ori,"TOTAL PRODUCT","B-430040",$C$20,"Amount_BS")/1000)+(_xll.DBR("CXMD:FTM_DATA_BALANCE_SHEET","Total_Customer_Supplier",E$21,$C$19,ori,"TOTAL PRODUCT","B-431040",$C$20,"Amount_BS")/1000)+(_xll.DBR("CXMD:FTM_DATA_BALANCE_SHEET","Total_Customer_Supplier",E$21,$C$19,ori,"TOTAL PRODUCT","B-437010",$C$20,"Amount_BS")/1000)+(_xll.DBR("CXMD:FTM_DATA_BALANCE_SHEET","Total_Customer_Supplier",E$21,$C$19,ori,"TOTAL PRODUCT","B-438010",$C$20,"Amount_BS")/1000) -> 77642.417 | F33: =(_xll.DBR("CXMD:FTM_DATA_BALANCE_SHEET","Total_Customer_Supplier",F$21,$C$19,ori,"TOTAL PRODUCT","B-430010",$C$20,"Amount_BS")/1000)+(_xll.DBR("CXMD:FTM_DATA_BALANCE_SHEET","Total_Customer_Supplier",F$21,$C$19,ori,"TOTAL PRODUCT","B-430040",$C$20,"Amount_BS")/1000)+(_xll.DBR("CXMD:FTM_DATA_BALANCE_SHEET","Total_Customer_Supplier",F$21,$C$19,ori,"TOTAL PRODUCT","B-431040",$C$20,"Amount_BS")/1000)+(_xll.DBR("CXMD:FTM_DATA_BALANCE_SHEET","Total_Customer_Supplier",F$21,$C$19,ori,"TOTAL PRODUCT","B-437010",$C$20,"Amount_BS")/1000)+(_xll.DBR("CXMD:FTM_DATA_BALANCE_SHEET","Total_Customer_Supplier",F$21,$C$19,ori,"TOTAL PRODUCT","B-438010",$C$20,"Amount_BS")/1000) -> 119124.29 | G33: =(_xll.DBR("CXMD:FTM_DATA_BALANCE_SHEET","Total_Customer_Supplier",G$21,$C$19,ori,"TOTAL PRODUCT","B-430010",$C$20,"Amount_BS")/1000)+(_xll.DBR("CXMD:FTM_DATA_BALANCE_SHEET","Total_Customer_Supplier",G$21,$C$19,ori,"TOTAL PRODUCT","B-430040",$C$20,"Amount_BS")/1000)+(_xll.DBR("CXMD:FTM_DATA_BALANCE_SHEET","Total_Customer_Supplier",G$21,$C$19,ori,"TOTAL PRODUCT","B-431040",$C$20,"Amount_BS")/1000)+(_xll.DBR("CXMD:FTM_DATA_BALANCE_SHEET","Total_Customer_Supplier",G$21,$C$19,ori,"TOTAL PRODUCT","B-437010",$C$20,"Amount_BS")/1000)+(_xll.DBR("CXMD:FTM_DATA_BALANCE_SHEET","Total_Customer_Supplier",G$21,$C$19,ori,"TOTAL PRODUCT","B-438010",$C$20,"Amount_BS")/1000) -> 157420.15 | H33: =(_xll.DBR("CXMD:FTM_DATA_BALANCE_SHEET","Total_Customer_Supplier",H$21,$C$19,ori,"TOTAL PRODUCT","B-430010",$C$20,"Amount_BS")/1000)+(_xll.DBR("CXMD:FTM_DATA_BALANCE_SHEET","Total_Customer_Supplier",H$21,$C$19,ori,"TOTAL PRODUCT","B-430040",$C$20,"Amount_BS")/1000)+(_xll.DBR("CXMD:FTM_DATA_BALANCE_SHEET","Total_Customer_Supplier",H$21,$C$19,ori,"TOTAL PRODUCT","B-431040",$C$20,"Amount_BS")/1000)+(_xll.DBR("CXMD:FTM_DATA_BALANCE_SHEET","Total_Customer_Supplier",H$21,$C$19,ori,"TOTAL PRODUCT","B-437010",$C$20,"Amount_BS")/1000)+(_xll.DBR("CXMD:FTM_DATA_BALANCE_SHEET","Total_Customer_Supplier",H$21,$C$19,ori,"TOTAL PRODUCT","B-438010",$C$20,"Amount_BS")/1000) -> 197570.36 | I33: =(_xll.DBR("CXMD:FTM_DATA_BALANCE_SHEET","Total_Customer_Supplier",I$21,$C$19,ori,"TOTAL PRODUCT","B-430010",$C$20,"Amount_BS")/1000)+(_xll.DBR("CXMD:FTM_DATA_BALANCE_SHEET","Total_Customer_Supplier",I$21,$C$19,ori,"TOTAL PRODUCT","B-430040",$C$20,"Amount_BS")/1000)+(_xll.DBR("CXMD:FTM_DATA_BALANCE_SHEET","Total_Customer_Supplier",I$21,$C$19,ori,"TOTAL PRODUCT","B-431040",$C$20,"Amount_BS")/1000)+(_xll.DBR("CXMD:FTM_DATA_BALANCE_SHEET","Total_Customer_Supplier",I$21,$C$19,ori,"TOTAL PRODUCT","B-437010",$C$20,"Amount_BS")/1000)+(_xll.DBR("CXMD:FTM_DATA_BALANCE_SHEET","Total_Customer_Supplier",I$21,$C$19,ori,"TOTAL PRODUCT","B-438010",$C$20,"Amount_BS")/1000) -> 241154.91 | J33: =(_xll.DBR("CXMD:FTM_DATA_BALANCE_SHEET","Total_Customer_Supplier",J$21,$C$19,ori,"TOTAL PRODUCT","B-430010",$C$20,"Amount_BS")/1000)+(_xll.DBR("CXMD:FTM_DATA_BALANCE_SHEET","Total_Customer_Supplier",J$21,$C$19,ori,"TOTAL PRODUCT","B-430040",$C$20,"Amount_BS")/1000)+(_xll.DBR("CXMD:FTM_DATA_BALANCE_SHEET","Total_Customer_Supplier",J$21,$C$19,ori,"TOTAL PRODUCT","B-431040",$C$20,"Amount_BS")/1000)+(_xll.DBR("CXMD:FTM_DATA_BALANCE_SHEET","Total_Customer_Supplier",J$21,$C$19,ori,"TOTAL PRODUCT","B-437010",$C$20,"Amount_BS")/1000)+(_xll.DBR("CXMD:FTM_DATA_BALANCE_SHEET","Total_Customer_Supplier",J$21,$C$19,ori,"TOTAL PRODUCT","B-438010",$C$20,"Amount_BS")/1000) -> 278723.48 | K33: =(_xll.DBR("CXMD:FTM_DATA_BALANCE_SHEET","Total_Customer_Supplier",K$21,$C$19,ori,"TOTAL PRODUCT","B-430010",$C$20,"Amount_BS")/1000)+(_xll.DBR("CXMD:FTM_DATA_BALANCE_SHEET","Total_Customer_Supplier",K$21,$C$19,ori,"TOTAL PRODUCT","B-430040",$C$20,"Amount_BS")/1000)+(_xll.DBR("CXMD:FTM_DATA_BALANCE_SHEET","Total_Customer_Supplier",K$21,$C$19,ori,"TOTAL PRODUCT","B-431040",$C$20,"Amount_BS")/1000)+(_xll.DBR("CXMD:FTM_DATA_BALANCE_SHEET","Total_Customer_Supplier",K$21,$C$19,ori,"TOTAL PRODUCT","B-437010",$C$20,"Amount_BS")/1000)+(_xll.DBR("CXMD:FTM_DATA_BALANCE_SHEET","Total_Customer_Supplier",K$21,$C$19,ori,"TOTAL PRODUCT","B-438010",$C$20,"Amount_BS")/1000) -> 310282.64 | ... O33: =(_xll.DBR("CXMD:FTM_DATA_BALANCE_SHEET","Total_Customer_Supplier",O$21,$C$19,ori,"TOTAL PRODUCT","B-430010",$C$20,"Amount_BS")/1000)+(_xll.DBR("CXMD:FTM_DATA_BALANCE_SHEET","Total_Customer_Supplier",O$21,$C$19,ori,"TOTAL PRODUCT","B-430040",$C$20,"Amount_BS")/1000)+(_xll.DBR("CXMD:FTM_DATA_BALANCE_SHEET","Total_Customer_Supplier",O$21,$C$19,ori,"TOTAL PRODUCT","B-431040",$C$20,"Amount_BS")/1000)+(_xll.DBR("CXMD:FTM_DATA_BALANCE_SHEET","Total_Customer_Supplier",O$21,$C$19,ori,"TOTAL PRODUCT","B-437010",$C$20,"Amount_BS")/1000)+(_xll.DBR("CXMD:FTM_DATA_BALANCE_SHEET","Total_Customer_Supplier",O$21,$C$19,ori,"TOTAL PRODUCT","B-438010",$C$20,"Amount_BS")/1000) -> 460087.47
C34: % of corporate output | D34: =IF(D25<>0,D33/D25,0) -> 0.11366694 | E34: =IF(E25<>0,E33/E25,0) -> 0.11734016 | F34: =IF(F25<>0,F33/F25,0) -> 0.11527751 | G34: =IF(G25<>0,G33/G25,0) -> 0.11651413 | H34: =IF(H25<>0,H33/H25,0) -> 0.11393935 | I34: =IF(I25<>0,I33/I25,0) -> 0.11454599 | J34: =IF(J25<>0,J33/J25,0) -> 0.11300327 | K34: =IF(K25<>0,K33/K25,0) -> 0.10967317 | ... O34: =IF(O25<>0,O33/O25,0) -> 0.1126799
B35: G - 459000 - OTHER EXPENSES | C35: Profit and Loss | D35: =(_xll.DBR("CXMD:FTM_DATA_BALANCE_SHEET","Total_Customer_Supplier",D$21,$C$19,ori,"TOTAL PRODUCT","B-451010",$C$20,"Amount_BS")/1000)+(_xll.DBR("CXMD:FTM_DATA_BALANCE_SHEET","Total_Customer_Supplier",D$21,$C$19,ori,"TOTAL PRODUCT","B-451020",$C$20,"Amount_BS")/1000)+(_xll.DBR("CXMD:FTM_DATA_BALANCE_SHEET","Total_Customer_Supplier",D$21,$C$19,ori,"TOTAL PRODUCT","B-451030",$C$20,"Amount_BS")/1000)+(_xll.DBR("CXMD:FTM_DATA_BALANCE_SHEET","Total_Customer_Supplier",D$21,$C$19,ori,"TOTAL PRODUCT","B-451110",$C$20,"Amount_BS")/1000)+(_xll.DBR("CXMD:FTM_DATA_BALANCE_SHEET","Total_Customer_Supplier",D$21,$C$19,ori,"TOTAL PRODUCT","B-451210",$C$20,"Amount_BS")/1000)+(_xll.DBR("CXMD:FTM_DATA_BALANCE_SHEET","Total_Customer_Supplier",D$21,$C$19,ori,"TOTAL PRODUCT","B-451220",$C$20,"Amount_BS")/1000)+(_xll.DBR("CXMD:FTM_DATA_BALANCE_SHEET","Total_Customer_Supplier",D$21,$C$19,ori,"TOTAL PRODUCT","B-451310",$C$20,"Amount_BS")/1000)+(_xll.DBR("CXMD:FTM_DATA_BALANCE_SHEET","Total_Customer_Supplier",D$21,$C$19,ori,"TOTAL PRODUCT","B-451450",$C$20,"Amount_BS")/1000)+(_xll.DBR("CXMD:FTM_DATA_BALANCE_SHEET","Total_Customer_Supplier",D$21,$C$19,ori,"TOTAL PRODUCT","B-451510",$C$20,"Amount_BS")/1000)+(_xll.DBR("CXMD:FTM_DATA_BALANCE_SHEET","Total_Customer_Supplier",D$21,$C$19,ori,"TOTAL PRODUCT","B-451610",$C$20,"Amount_BS")/1000)+(_xll.DBR("CXMD:FTM_DATA_BALANCE_SHEET","Total_Customer_Supplier",D$21,$C$19,ori,"TOTAL PRODUCT","B-451620",$C$20,"Amount_BS")/1000) -> 29278.132 | E35: =(_xll.DBR("CXMD:FTM_DATA_BALANCE_SHEET","Total_Customer_Supplier",E$21,$C$19,ori,"TOTAL PRODUCT","B-451010",$C$20,"Amount_BS")/1000)+(_xll.DBR("CXMD:FTM_DATA_BALANCE_SHEET","Total_Customer_Supplier",E$21,$C$19,ori,"TOTAL PRODUCT","B-451020",$C$20,"Amount_BS")/1000)+(_xll.DBR("CXMD:FTM_DATA_BALANCE_SHEET","Total_Customer_Supplier",E$21,$C$19,ori,"TOTAL PRODUCT","B-451030",$C$20,"Amount_BS")/1000)+(_xll.DBR("CXMD:FTM_DATA_BALANCE_SHEET","Total_Customer_Supplier",E$21,$C$19,ori,"TOTAL PRODUCT","B-451110",$C$20,"Amount_BS")/1000)+(_xll.DBR("CXMD:FTM_DATA_BALANCE_SHEET","Total_Customer_Supplier",E$21,$C$19,ori,"TOTAL PRODUCT","B-451210",$C$20,"Amount_BS")/1000)+(_xll.DBR("CXMD:FTM_DATA_BALANCE_SHEET","Total_Customer_Supplier",E$21,$C$19,ori,"TOTAL PRODUCT","B-451220",$C$20,"Amount_BS")/1000)+(_xll.DBR("CXMD:FTM_DATA_BALANCE_SHEET","Total_Customer_Supplier",E$21,$C$19,ori,"TOTAL PRODUCT","B-451310",$C$20,"Amount_BS")/1000)+(_xll.DBR("CXMD:FTM_DATA_BALANCE_SHEET","Total_Customer_Supplier",E$21,$C$19,ori,"TOTAL PRODUCT","B-451450",$C$20,"Amount_BS")/1000)+(_xll.DBR("CXMD:FTM_DATA_BALANCE_SHEET","Total_Customer_Supplier",E$21,$C$19,ori,"TOTAL PRODUCT","B-451510",$C$20,"Amount_BS")/1000)+(_xll.DBR("CXMD:FTM_DATA_BALANCE_SHEET","Total_Customer_Supplier",E$21,$C$19,ori,"TOTAL PRODUCT","B-451610",$C$20,"Amount_BS")/1000)+(_xll.DBR("CXMD:FTM_DATA_BALANCE_SHEET","Total_Customer_Supplier",E$21,$C$19,ori,"TOTAL PRODUCT","B-451620",$C$20,"Amount_BS")/1000) -> 55704.349 | F35: =(_xll.DBR("CXMD:FTM_DATA_BALANCE_SHEET","Total_Customer_Supplier",F$21,$C$19,ori,"TOTAL PRODUCT","B-451010",$C$20,"Amount_BS")/1000)+(_xll.DBR("CXMD:FTM_DATA_BALANCE_SHEET","Total_Customer_Supplier",F$21,$C$19,ori,"TOTAL PRODUCT","B-451020",$C$20,"Amount_BS")/1000)+(_xll.DBR("CXMD:FTM_DATA_BALANCE_SHEET","Total_Customer_Supplier",F$21,$C$19,ori,"TOTAL PRODUCT","B-451030",$C$20,"Amount_BS")/1000)+(_xll.DBR("CXMD:FTM_DATA_BALANCE_SHEET","Total_Customer_Supplier",F$21,$C$19,ori,"TOTAL PRODUCT","B-451110",$C$20,"Amount_BS")/1000)+(_xll.DBR("CXMD:FTM_DATA_BALANCE_SHEET","Total_Customer_Supplier",F$21,$C$19,ori,"TOTAL PRODUCT","B-451210",$C$20,"Amount_BS")/1000)+(_xll.DBR("CXMD:FTM_DATA_BALANCE_SHEET","Total_Customer_Supplier",F$21,$C$19,ori,"TOTAL PRODUCT","B-451220",$C$20,"Amount_BS")/1000)+(_xll.DBR("CXMD:FTM_DATA_BALANCE_SHEET","Total_Customer_Supplier",F$21,$C$19,ori,"TOTAL PRODUCT","B-451310",$C$20,"Amount_BS")/1000)+(_xll.DBR("CXMD:FTM_DATA_BALANCE_SHEET","Total_Customer_Supplier",F$21,$C$19,ori,"TOTAL PRODUCT","B-451450",$C$20,"Amount_BS")/1000)+(_xll.DBR("CXMD:FTM_DATA_BALANCE_SHEET","Total_Customer_Supplier",F$21,$C$19,ori,"TOTAL PRODUCT","B-451510",$C$20,"Amount_BS")/1000)+(_xll.DBR("CXMD:FTM_DATA_BALANCE_SHEET","Total_Customer_Supplier",F$21,$C$19,ori,"TOTAL PRODUCT","B-451610",$C$20,"Amount_BS")/1000)+(_xll.DBR("CXMD:FTM_DATA_BALANCE_SHEET","Total_Customer_Supplier",F$21,$C$19,ori,"TOTAL PRODUCT","B-451620",$C$20,"Amount_BS")/1000) -> 88792.144 | G35: =(_xll.DBR("CXMD:FTM_DATA_BALANCE_SHEET","Total_Customer_Supplier",G$21,$C$19,ori,"TOTAL PRODUCT","B-451010",$C$20,"Amount_BS")/1000)+(_xll.DBR("CXMD:FTM_DATA_BALANCE_SHEET","Total_Customer_Supplier",G$21,$C$19,ori,"TOTAL PRODUCT","B-451020",$C$20,"Amount_BS")/1000)+(_xll.DBR("CXMD:FTM_DATA_BALANCE_SHEET","Total_Customer_Supplier",G$21,$C$19,ori,"TOTAL PRODUCT","B-451030",$C$20,"Amount_BS")/1000)+(_xll.DBR("CXMD:FTM_DATA_BALANCE_SHEET","Total_Customer_Supplier",G$21,$C$19,ori,"TOTAL PRODUCT","B-451110",$C$20,"Amount_BS")/1000)+(_xll.DBR("CXMD:FTM_DATA_BALANCE_SHEET","Total_Customer_Supplier",G$21,$C$19,ori,"TOTAL PRODUCT","B-451210",$C$20,"Amount_BS")/1000)+(_xll.DBR("CXMD:FTM_DATA_BALANCE_SHEET","Total_Customer_Supplier",G$21,$C$19,ori,"TOTAL PRODUCT","B-451220",$C$20,"Amount_BS")/1000)+(_xll.DBR("CXMD:FTM_DATA_BALANCE_SHEET","Total_Customer_Supplier",G$21,$C$19,ori,"TOTAL PRODUCT","B-451310",$C$20,"Amount_BS")/1000)+(_xll.DBR("CXMD:FTM_DATA_BALANCE_SHEET","Total_Customer_Supplier",G$21,$C$19,ori,"TOTAL PRODUCT","B-451450",$C$20,"Amount_BS")/1000)+(_xll.DBR("CXMD:FTM_DATA_BALANCE_SHEET","Total_Customer_Supplier",G$21,$C$19,ori,"TOTAL PRODUCT","B-451510",$C$20,"Amount_BS")/1000)+(_xll.DBR("CXMD:FTM_DATA_BALANCE_SHEET","Total_Customer_Supplier",G$21,$C$19,ori,"TOTAL PRODUCT","B-451610",$C$20,"Amount_BS")/1000)+(_xll.DBR("CXMD:FTM_DATA_BALANCE_SHEET","Total_Customer_Supplier",G$21,$C$19,ori,"TOTAL PRODUCT","B-451620",$C$20,"Amount_BS")/1000) -> 120559.83 | H35: =(_xll.DBR("CXMD:FTM_DATA_BALANCE_SHEET","Total_Customer_Supplier",H$21,$C$19,ori,"TOTAL PRODUCT","B-451010",$C$20,"Amount_BS")/1000)+(_xll.DBR("CXMD:FTM_DATA_BALANCE_SHEET","Total_Customer_Supplier",H$21,$C$19,ori,"TOTAL PRODUCT","B-451020",$C$20,"Amount_BS")/1000)+(_xll.DBR("CXMD:FTM_DATA_BALANCE_SHEET","Total_Customer_Supplier",H$21,$C$19,ori,"TOTAL PRODUCT","B-451030",$C$20,"Amount_BS")/1000)+(_xll.DBR("CXMD:FTM_DATA_BALANCE_SHEET","Total_Customer_Supplier",H$21,$C$19,ori,"TOTAL PRODUCT","B-451110",$C$20,"Amount_BS")/1000)+(_xll.DBR("CXMD:FTM_DATA_BALANCE_SHEET","Total_Customer_Supplier",H$21,$C$19,ori,"TOTAL PRODUCT","B-451210",$C$20,"Amount_BS")/1000)+(_xll.DBR("CXMD:FTM_DATA_BALANCE_SHEET","Total_Customer_Supplier",H$21,$C$19,ori,"TOTAL PRODUCT","B-451220",$C$20,"Amount_BS")/1000)+(_xll.DBR("CXMD:FTM_DATA_BALANCE_SHEET","Total_Customer_Supplier",H$21,$C$19,ori,"TOTAL PRODUCT","B-451310",$C$20,"Amount_BS")/1000)+(_xll.DBR("CXMD:FTM_DATA_BALANCE_SHEET","Total_Customer_Supplier",H$21,$C$19,ori,"TOTAL PRODUCT","B-451450",$C$20,"Amount_BS")/1000)+(_xll.DBR("CXMD:FTM_DATA_BALANCE_SHEET","Total_Customer_Supplier",H$21,$C$19,ori,"TOTAL PRODUCT","B-451510",$C$20,"Amount_BS")/1000)+(_xll.DBR("CXMD:FTM_DATA_BALANCE_SHEET","Total_Customer_Supplier",H$21,$C$19,ori,"TOTAL PRODUCT","B-451610",$C$20,"Amount_BS")/1000)+(_xll.DBR("CXMD:FTM_DATA_BALANCE_SHEET","Total_Customer_Supplier",H$21,$C$19,ori,"TOTAL PRODUCT","B-451620",$C$20,"Amount_BS")/1000) -> 153093.76 | I35: =(_xll.DBR("CXMD:FTM_DATA_BALANCE_SHEET","Total_Customer_Supplier",I$21,$C$19,ori,"TOTAL PRODUCT","B-451010",$C$20,"Amount_BS")/1000)+(_xll.DBR("CXMD:FTM_DATA_BALANCE_SHEET","Total_Customer_Supplier",I$21,$C$19,ori,"TOTAL PRODUCT","B-451020",$C$20,"Amount_BS")/1000)+(_xll.DBR("CXMD:FTM_DATA_BALANCE_SHEET","Total_Customer_Supplier",I$21,$C$19,ori,"TOTAL PRODUCT","B-451030",$C$20,"Amount_BS")/1000)+(_xll.DBR("CXMD:FTM_DATA_BALANCE_SHEET","Total_Customer_Supplier",I$21,$C$19,ori,"TOTAL PRODUCT","B-451110",$C$20,"Amount_BS")/1000)+(_xll.DBR("CXMD:FTM_DATA_BALANCE_SHEET","Total_Customer_Supplier",I$21,$C$19,ori,"TOTAL PRODUCT","B-451210",$C$20,"Amount_BS")/1000)+(_xll.DBR("CXMD:FTM_DATA_BALANCE_SHEET","Total_Customer_Supplier",I$21,$C$19,ori,"TOTAL PRODUCT","B-451220",$C$20,"Amount_BS")/1000)+(_xll.DBR("CXMD:FTM_DATA_BALANCE_SHEET","Total_Customer_Supplier",I$21,$C$19,ori,"TOTAL PRODUCT","B-451310",$C$20,"Amount_BS")/1000)+(_xll.DBR("CXMD:FTM_DATA_BALANCE_SHEET","Total_Customer_Supplier",I$21,$C$19,ori,"TOTAL PRODUCT","B-451450",$C$20,"Amount_BS")/1000)+(_xll.DBR("CXMD:FTM_DATA_BALANCE_SHEET","Total_Customer_Supplier",I$21,$C$19,ori,"TOTAL PRODUCT","B-451510",$C$20,"Amount_BS")/1000)+(_xll.DBR("CXMD:FTM_DATA_BALANCE_SHEET","Total_Customer_Supplier",I$21,$C$19,ori,"TOTAL PRODUCT","B-451610",$C$20,"Amount_BS")/1000)+(_xll.DBR("CXMD:FTM_DATA_BALANCE_SHEET","Total_Customer_Supplier",I$21,$C$19,ori,"TOTAL PRODUCT","B-451620",$C$20,"Amount_BS")/1000) -> 183999.1 | J35: =(_xll.DBR("CXMD:FTM_DATA_BALANCE_SHEET","Total_Customer_Supplier",J$21,$C$19,ori,"TOTAL PRODUCT","B-451010",$C$20,"Amount_BS")/1000)+(_xll.DBR("CXMD:FTM_DATA_BALANCE_SHEET","Total_Customer_Supplier",J$21,$C$19,ori,"TOTAL PRODUCT","B-451020",$C$20,"Amount_BS")/1000)+(_xll.DBR("CXMD:FTM_DATA_BALANCE_SHEET","Total_Customer_Supplier",J$21,$C$19,ori,"TOTAL PRODUCT","B-451030",$C$20,"Amount_BS")/1000)+(_xll.DBR("CXMD:FTM_DATA_BALANCE_SHEET","Total_Customer_Supplier",J$21,$C$19,ori,"TOTAL PRODUCT","B-451110",$C$20,"Amount_BS")/1000)+(_xll.DBR("CXMD:FTM_DATA_BALANCE_SHEET","Total_Customer_Supplier",J$21,$C$19,ori,"TOTAL PRODUCT","B-451210",$C$20,"Amount_BS")/1000)+(_xll.DBR("CXMD:FTM_DATA_BALANCE_SHEET","Total_Customer_Supplier",J$21,$C$19,ori,"TOTAL PRODUCT","B-451220",$C$20,"Amount_BS")/1000)+(_xll.DBR("CXMD:FTM_DATA_BALANCE_SHEET","Total_Customer_Supplier",J$21,$C$19,ori,"TOTAL PRODUCT","B-451310",$C$20,"Amount_BS")/1000)+(_xll.DBR("CXMD:FTM_DATA_BALANCE_SHEET","Total_Customer_Supplier",J$21,$C$19,ori,"TOTAL PRODUCT","B-451450",$C$20,"Amount_BS")/1000)+(_xll.DBR("CXMD:FTM_DATA_BALANCE_SHEET","Total_Customer_Supplier",J$21,$C$19,ori,"TOTAL PRODUCT","B-451510",$C$20,"Amount_BS")/1000)+(_xll.DBR("CXMD:FTM_DATA_BALANCE_SHEET","Total_Customer_Supplier",J$21,$C$19,ori,"TOTAL PRODUCT","B-451610",$C$20,"Amount_BS")/1000)+(_xll.DBR("CXMD:FTM_DATA_BALANCE_SHEET","Total_Customer_Supplier",J$21,$C$19,ori,"TOTAL PRODUCT","B-451620",$C$20,"Amount_BS")/1000) -> 212624.51 | K35: =(_xll.DBR("CXMD:FTM_DATA_BALANCE_SHEET","Total_Customer_Supplier",K$21,$C$19,ori,"TOTAL PRODUCT","B-451010",$C$20,"Amount_BS")/1000)+(_xll.DBR("CXMD:FTM_DATA_BALANCE_SHEET","Total_Customer_Supplier",K$21,$C$19,ori,"TOTAL PRODUCT","B-451020",$C$20,"Amount_BS")/1000)+(_xll.DBR("CXMD:FTM_DATA_BALANCE_SHEET","Total_Customer_Supplier",K$21,$C$19,ori,"TOTAL PRODUCT","B-451030",$C$20,"Amount_BS")/1000)+(_xll.DBR("CXMD:FTM_DATA_BALANCE_SHEET","Total_Customer_Supplier",K$21,$C$19,ori,"TOTAL PRODUCT","B-451110",$C$20,"Amount_BS")/1000)+(_xll.DBR("CXMD:FTM_DATA_BALANCE_SHEET","Total_Customer_Supplier",K$21,$C$19,ori,"TOTAL PRODUCT","B-451210",$C$20,"Amount_BS")/1000)+(_xll.DBR("CXMD:FTM_DATA_BALANCE_SHEET","Total_Customer_Supplier",K$21,$C$19,ori,"TOTAL PRODUCT","B-451220",$C$20,"Amount_BS")/1000)+(_xll.DBR("CXMD:FTM_DATA_BALANCE_SHEET","Total_Customer_Supplier",K$21,$C$19,ori,"TOTAL PRODUCT","B-451310",$C$20,"Amount_BS")/1000)+(_xll.DBR("CXMD:FTM_DATA_BALANCE_SHEET","Total_Customer_Supplier",K$21,$C$19,ori,"TOTAL PRODUCT","B-451450",$C$20,"Amount_BS")/1000)+(_xll.DBR("CXMD:FTM_DATA_BALANCE_SHEET","Total_Customer_Supplier",K$21,$C$19,ori,"TOTAL PRODUCT","B-451510",$C$20,"Amount_BS")/1000)+(_xll.DBR("CXMD:FTM_DATA_BALANCE_SHEET","Total_Customer_Supplier",K$21,$C$19,ori,"TOTAL PRODUCT","B-451610",$C$20,"Amount_BS")/1000)+(_xll.DBR("CXMD:FTM_DATA_BALANCE_SHEET","Total_Customer_Supplier",K$21,$C$19,ori,"TOTAL PRODUCT","B-451620",$C$20,"Amount_BS")/1000) -> 239387.39 | ... O35: =(_xll.DBR("CXMD:FTM_DATA_BALANCE_SHEET","Total_Customer_Supplier",O$21,$C$19,ori,"TOTAL PRODUCT","B-451010",$C$20,"Amount_BS")/1000)+(_xll.DBR("CXMD:FTM_DATA_BALANCE_SHEET","Total_Customer_Supplier",O$21,$C$19,ori,"TOTAL PRODUCT","B-451020",$C$20,"Amount_BS")/1000)+(_xll.DBR("CXMD:FTM_DATA_BALANCE_SHEET","Total_Customer_Supplier",O$21,$C$19,ori,"TOTAL PRODUCT","B-451030",$C$20,"Amount_BS")/1000)+(_xll.DBR("CXMD:FTM_DATA_BALANCE_SHEET","Total_Customer_Supplier",O$21,$C$19,ori,"TOTAL PRODUCT","B-451110",$C$20,"Amount_BS")/1000)+(_xll.DBR("CXMD:FTM_DATA_BALANCE_SHEET","Total_Customer_Supplier",O$21,$C$19,ori,"TOTAL PRODUCT","B-451210",$C$20,"Amount_BS")/1000)+(_xll.DBR("CXMD:FTM_DATA_BALANCE_SHEET","Total_Customer_Supplier",O$21,$C$19,ori,"TOTAL PRODUCT","B-451220",$C$20,"Amount_BS")/1000)+(_xll.DBR("CXMD:FTM_DATA_BALANCE_SHEET","Total_Customer_Supplier",O$21,$C$19,ori,"TOTAL PRODUCT","B-451310",$C$20,"Amount_BS")/1000)+(_xll.DBR("CXMD:FTM_DATA_BALANCE_SHEET","Total_Customer_Supplier",O$21,$C$19,ori,"TOTAL PRODUCT","B-451450",$C$20,"Amount_BS")/1000)+(_xll.DBR("CXMD:FTM_DATA_BALANCE_SHEET","Total_Customer_Supplier",O$21,$C$19,ori,"TOTAL PRODUCT","B-451510",$C$20,"Amount_BS")/1000)+(_xll.DBR("CXMD:FTM_DATA_BALANCE_SHEET","Total_Customer_Supplier",O$21,$C$19,ori,"TOTAL PRODUCT","B-451610",$C$20,"Amount_BS")/1000)+(_xll.DBR("CXMD:FTM_DATA_BALANCE_SHEET","Total_Customer_Supplier",O$21,$C$19,ori,"TOTAL PRODUCT","B-451620",$C$20,"Amount_BS")/1000) -> 371754.65
C36: % of corporate output | D36: =IF(D25<>0,D35/D25,0) -> 0.088981621 | E36: =IF(E25<>0,E35/E25,0) -> 0.084185388 | F36: =IF(F25<>0,F35/F25,0) -> 0.085924858 | G36: =IF(G25<>0,G35/G25,0) -> 0.089232058 | H36: =IF(H25<>0,H35/H25,0) -> 0.088289574 | I36: =IF(I25<>0,I35/I25,0) -> 0.087397597 | J36: =IF(J25<>0,J35/J25,0) -> 0.086204668 | K36: =IF(K25<>0,K35/K25,0) -> 0.084614383 | ... O36: =IF(O25<>0,O35/O25,0) -> 0.091046334
B37: G - 453900 - FX GAIN/LOSS | C37: Profit and Loss | D37: =_xll.DBR("CXMD:FTM_DATA_BALANCE_SHEET","Total_Customer_Supplier",D$21,$C$19,ori,"TOTAL PRODUCT","B-453010",$C$20,"Amount_BS")/1000 -> -14389.183 | E37: =_xll.DBR("CXMD:FTM_DATA_BALANCE_SHEET","Total_Customer_Supplier",E$21,$C$19,ori,"TOTAL PRODUCT","B-453010",$C$20,"Amount_BS")/1000 -> -10142.121 | F37: =_xll.DBR("CXMD:FTM_DATA_BALANCE_SHEET","Total_Customer_Supplier",F$21,$C$19,ori,"TOTAL PRODUCT","B-453010",$C$20,"Amount_BS")/1000 -> -7633.4782 | G37: =_xll.DBR("CXMD:FTM_DATA_BALANCE_SHEET","Total_Customer_Supplier",G$21,$C$19,ori,"TOTAL PRODUCT","B-453010",$C$20,"Amount_BS")/1000 -> -7034.1854 | H37: =_xll.DBR("CXMD:FTM_DATA_BALANCE_SHEET","Total_Customer_Supplier",H$21,$C$19,ori,"TOTAL PRODUCT","B-453010",$C$20,"Amount_BS")/1000 -> -7500.5074 | I37: =_xll.DBR("CXMD:FTM_DATA_BALANCE_SHEET","Total_Customer_Supplier",I$21,$C$19,ori,"TOTAL PRODUCT","B-453010",$C$20,"Amount_BS")/1000 -> -7403.8317 | J37: =_xll.DBR("CXMD:FTM_DATA_BALANCE_SHEET","Total_Customer_Supplier",J$21,$C$19,ori,"TOTAL PRODUCT","B-453010",$C$20,"Amount_BS")/1000 -> -5362.5918 | K37: =_xll.DBR("CXMD:FTM_DATA_BALANCE_SHEET","Total_Customer_Supplier",K$21,$C$19,ori,"TOTAL PRODUCT","B-453010",$C$20,"Amount_BS")/1000 -> -6890.0215 | ... O37: =_xll.DBR("CXMD:FTM_DATA_BALANCE_SHEET","Total_Customer_Supplier",O$21,$C$19,ori,"TOTAL PRODUCT","B-453010",$C$20,"Amount_BS")/1000 -> -3499.1707
B38: G - 479000 - DEPREC. PROV. | C38: Profit and Loss | D38: =(_xll.DBR("CXMD:FTM_DATA_BALANCE_SHEET","Total_Customer_Supplier",D$21,$C$19,ori,"TOTAL PRODUCT","B-470010",$C$20,"Amount_BS")/1000)+(_xll.DBR("CXMD:FTM_DATA_BALANCE_SHEET","Total_Customer_Supplier",D$21,$C$19,ori,"TOTAL PRODUCT","B-475010",$C$20,"Amount_BS")/1000) -> 3386.485 | E38: =(_xll.DBR("CXMD:FTM_DATA_BALANCE_SHEET","Total_Customer_Supplier",E$21,$C$19,ori,"TOTAL PRODUCT","B-470010",$C$20,"Amount_BS")/1000)+(_xll.DBR("CXMD:FTM_DATA_BALANCE_SHEET","Total_Customer_Supplier",E$21,$C$19,ori,"TOTAL PRODUCT","B-475010",$C$20,"Amount_BS")/1000) -> 6832.8671 | F38: =(_xll.DBR("CXMD:FTM_DATA_BALANCE_SHEET","Total_Customer_Supplier",F$21,$C$19,ori,"TOTAL PRODUCT","B-470010",$C$20,"Amount_BS")/1000)+(_xll.DBR("CXMD:FTM_DATA_BALANCE_SHEET","Total_Customer_Supplier",F$21,$C$19,ori,"TOTAL PRODUCT","B-475010",$C$20,"Amount_BS")/1000) -> 10081.45 | G38: =(_xll.DBR("CXMD:FTM_DATA_BALANCE_SHEET","Total_Customer_Supplier",G$21,$C$19,ori,"TOTAL PRODUCT","B-470010",$C$20,"Amount_BS")/1000)+(_xll.DBR("CXMD:FTM_DATA_BALANCE_SHEET","Total_Customer_Supplier",G$21,$C$19,ori,"TOTAL PRODUCT","B-475010",$C$20,"Amount_BS")/1000) -> 13396.615 | H38: =(_xll.DBR("CXMD:FTM_DATA_BALANCE_SHEET","Total_Customer_Supplier",H$21,$C$19,ori,"TOTAL PRODUCT","B-470010",$C$20,"Amount_BS")/1000)+(_xll.DBR("CXMD:FTM_DATA_BALANCE_SHEET","Total_Customer_Supplier",H$21,$C$19,ori,"TOTAL PRODUCT","B-475010",$C$20,"Amount_BS")/1000) -> 16752.691 | I38: =(_xll.DBR("CXMD:FTM_DATA_BALANCE_SHEET","Total_Customer_Supplier",I$21,$C$19,ori,"TOTAL PRODUCT","B-470010",$C$20,"Amount_BS")/1000)+(_xll.DBR("CXMD:FTM_DATA_BALANCE_SHEET","Total_Customer_Supplier",I$21,$C$19,ori,"TOTAL PRODUCT","B-475010",$C$20,"Amount_BS")/1000) -> 20142.831 | J38: =(_xll.DBR("CXMD:FTM_DATA_BALANCE_SHEET","Total_Customer_Supplier",J$21,$C$19,ori,"TOTAL PRODUCT","B-470010",$C$20,"Amount_BS")/1000)+(_xll.DBR("CXMD:FTM_DATA_BALANCE_SHEET","Total_Customer_Supplier",J$21,$C$19,ori,"TOTAL PRODUCT","B-475010",$C$20,"Amount_BS")/1000) -> 23528.673 | K38: =(_xll.DBR("CXMD:FTM_DATA_BALANCE_SHEET","Total_Customer_Supplier",K$21,$C$19,ori,"TOTAL PRODUCT","B-470010",$C$20,"Amount_BS")/1000)+(_xll.DBR("CXMD:FTM_DATA_BALANCE_SHEET","Total_Customer_Supplier",K$21,$C$19,ori,"TOTAL PRODUCT","B-475010",$C$20,"Amount_BS")/1000) -> 26961.496 | ... O38: =(_xll.DBR("CXMD:FTM_DATA_BALANCE_SHEET","Total_Customer_Supplier",O$21,$C$19,ori,"TOTAL PRODUCT","B-470010",$C$20,"Amount_BS")/1000)+(_xll.DBR("CXMD:FTM_DATA_BALANCE_SHEET","Total_Customer_Supplier",O$21,$C$19,ori,"TOTAL PRODUCT","B-475010",$C$20,"Amount_BS")/1000) -> 39702.352
B39: Ebit without Management fees | D39: =D27-D29-D33-D35-D37-D38-D28 -> 86917.47 | E39: =E27-E29-E33-E35-E37-E38-E28 -> 157090.51 | F39: =F27-F29-F33-F35-F37-F38-F28 -> 199288.57 | G39: =G27-G29-G33-G35-G37-G38-G28 -> 236023.2 | H39: =H27-H29-H33-H35-H37-H38-H28 -> 304421.54 | I39: =I27-I29-I33-I35-I37-I38-I28 -> 366728.61 | J39: =J27-J29-J33-J35-J37-J38-J28 -> 437408.05 | K39: =K27-K29-K33-K35-K37-K38-K28 -> 544213.46 | ... O39: =O27-O29-O33-O35-O37-O38-O28 -> 693916.26
C40: % of net sales | D40: =IF(D23<>0,D39/D23,0) -> 0.24154242 | E40: =IF(E23<>0,E39/E23,0) -> 0.22435241 | F40: =IF(F23<>0,F39/F23,0) -> 0.1890673 | G40: =IF(G23<>0,G39/G23,0) -> 0.17136665 | H40: =IF(H23<>0,H39/H23,0) -> 0.17528394 | I40: =IF(I23<>0,I39/I23,0) -> 0.17326082 | J40: =IF(J23<>0,J39/J23,0) -> 0.17519294 | K40: =IF(K23<>0,K39/K23,0) -> 0.19031134 | ... O40: =IF(O23<>0,O39/O23,0) -> 0.170384
B41: G - 569199 - OTHER INCOME/EXPENSES | C41: Profit and Loss | D41: =(_xll.DBR("CXMD:FTM_DATA_BALANCE_SHEET","Total_Customer_Supplier",D$21,$C$19,ori,"TOTAL PRODUCT","B-560020",$C$20,"Amount_BS")/1000)+(_xll.DBR("CXMD:FTM_DATA_BALANCE_SHEET","Total_Customer_Supplier",D$21,$C$19,ori,"TOTAL PRODUCT","B-561010",$C$20,"Amount_BS")/1000) -> 462.46413 | E41: =(_xll.DBR("CXMD:FTM_DATA_BALANCE_SHEET","Total_Customer_Supplier",E$21,$C$19,ori,"TOTAL PRODUCT","B-560020",$C$20,"Amount_BS")/1000)+(_xll.DBR("CXMD:FTM_DATA_BALANCE_SHEET","Total_Customer_Supplier",E$21,$C$19,ori,"TOTAL PRODUCT","B-561010",$C$20,"Amount_BS")/1000) -> 924.92826 | F41: =(_xll.DBR("CXMD:FTM_DATA_BALANCE_SHEET","Total_Customer_Supplier",F$21,$C$19,ori,"TOTAL PRODUCT","B-560020",$C$20,"Amount_BS")/1000)+(_xll.DBR("CXMD:FTM_DATA_BALANCE_SHEET","Total_Customer_Supplier",F$21,$C$19,ori,"TOTAL PRODUCT","B-561010",$C$20,"Amount_BS")/1000) -> 1387.3924 | G41: =(_xll.DBR("CXMD:FTM_DATA_BALANCE_SHEET","Total_Customer_Supplier",G$21,$C$19,ori,"TOTAL PRODUCT","B-560020",$C$20,"Amount_BS")/1000)+(_xll.DBR("CXMD:FTM_DATA_BALANCE_SHEET","Total_Customer_Supplier",G$21,$C$19,ori,"TOTAL PRODUCT","B-561010",$C$20,"Amount_BS")/1000) -> 2186.8195 | H41: =(_xll.DBR("CXMD:FTM_DATA_BALANCE_SHEET","Total_Customer_Supplier",H$21,$C$19,ori,"TOTAL PRODUCT","B-560020",$C$20,"Amount_BS")/1000)+(_xll.DBR("CXMD:FTM_DATA_BALANCE_SHEET","Total_Customer_Supplier",H$21,$C$19,ori,"TOTAL PRODUCT","B-561010",$C$20,"Amount_BS")/1000) -> 2649.2836 | I41: =(_xll.DBR("CXMD:FTM_DATA_BALANCE_SHEET","Total_Customer_Supplier",I$21,$C$19,ori,"TOTAL PRODUCT","B-560020",$C$20,"Amount_BS")/1000)+(_xll.DBR("CXMD:FTM_DATA_BALANCE_SHEET","Total_Customer_Supplier",I$21,$C$19,ori,"TOTAL PRODUCT","B-561010",$C$20,"Amount_BS")/1000) -> 3111.7478 | J41: =(_xll.DBR("CXMD:FTM_DATA_BALANCE_SHEET","Total_Customer_Supplier",J$21,$C$19,ori,"TOTAL PRODUCT","B-560020",$C$20,"Amount_BS")/1000)+(_xll.DBR("CXMD:FTM_DATA_BALANCE_SHEET","Total_Customer_Supplier",J$21,$C$19,ori,"TOTAL PRODUCT","B-561010",$C$20,"Amount_BS")/1000) -> 3574.2119 | K41: =(_xll.DBR("CXMD:FTM_DATA_BALANCE_SHEET","Total_Customer_Supplier",K$21,$C$19,ori,"TOTAL PRODUCT","B-560020",$C$20,"Amount_BS")/1000)+(_xll.DBR("CXMD:FTM_DATA_BALANCE_SHEET","Total_Customer_Supplier",K$21,$C$19,ori,"TOTAL PRODUCT","B-561010",$C$20,"Amount_BS")/1000) -> 4036.676 | ... O41: =(_xll.DBR("CXMD:FTM_DATA_BALANCE_SHEET","Total_Customer_Supplier",O$21,$C$19,ori,"TOTAL PRODUCT","B-560020",$C$20,"Amount_BS")/1000)+(_xll.DBR("CXMD:FTM_DATA_BALANCE_SHEET","Total_Customer_Supplier",O$21,$C$19,ori,"TOTAL PRODUCT","B-561010",$C$20,"Amount_BS")/1000) -> 5895.958
B42: Ebit including Management fees | D42: =D39-D41 -> 86455.006 | E42: =E39-E41 -> 156165.59 | F42: =F39-F41 -> 197901.18 | G42: =G39-G41 -> 233836.38 | H42: =H39-H41 -> 301772.26 | I42: =I39-I41 -> 363616.86 | J42: =J39-J41 -> 433833.84 | K42: =K39-K41 -> 540176.79 | ... O42: =O39-O41 -> 688020.3
C43: % of net sales | D43: =IF(D23<>0,D42/D23,0) -> 0.24025724 | E43: =IF(E23<>0,E42/E23,0) -> 0.22303145 | F43: =IF(F23<>0,F42/F23,0) -> 0.18775107 | G43: =IF(G23<>0,G42/G23,0) -> 0.16977889 | H43: =IF(H23<>0,H42/H23,0) -> 0.1737585 | I43: =IF(I23<>0,I42/I23,0) -> 0.17179067 | J43: =IF(J23<>0,J42/J23,0) -> 0.17376138 | K43: =IF(K23<>0,K42/K23,0) -> 0.18889971 | ... O43: =IF(O23<>0,O42/O23,0) -> 0.1689363

Sheet P&L Month by CC detailed
B18: Origin_Company | C18: =origine -> Total Origin Company
B19: Actuality | C19: ='P&L Month by CC summary'!C19 -> AC2022 | F19: P&L Month _ detailed
B20: Allocation | C20: ='P&L Month by CC summary'!C20 -> Total Allocation
C22: in K Local Currency | D22: January | E22: February | F22: March | G22: April | H22: May | I22: June | J22: July | K22: August | L22: September | M22: October | N22: November | O22: December | P22: TOTAL YEAR
B23: Bucher Account | C23: Chart of Account
D24: Amount_BS | E24: Amount_BS | H24: Amount_BS
B25: G - 309000 - NET SALES | C25: Profit and Loss | D25: =_xll.DBR("CXMD:FTM_DATA_BALANCE_SHEET","Total_Customer_Supplier",D$22,$C$19,ori,"TOTAL PRODUCT","B-300010",$C$20,"Amount_BS")*-1/1000 -> 359843.49 | E25: =_xll.DBR("CXMD:FTM_DATA_BALANCE_SHEET","Total_Customer_Supplier",E$22,$C$19,ori,"TOTAL PRODUCT","B-300010",$C$20,"Amount_BS")*-1/1000 -> 340351.87 | F25: =_xll.DBR("CXMD:FTM_DATA_BALANCE_SHEET","Total_Customer_Supplier",F$22,$C$19,ori,"TOTAL PRODUCT","B-300010",$C$20,"Amount_BS")*-1/1000 -> 353866.18 | G25: =_xll.DBR("CXMD:FTM_DATA_BALANCE_SHEET","Total_Customer_Supplier",G$22,$C$19,ori,"TOTAL PRODUCT","B-300010",$C$20,"Amount_BS")*-1/1000 -> 323237.93 | H25: =_xll.DBR("CXMD:FTM_DATA_BALANCE_SHEET","Total_Customer_Supplier",H$22,$C$19,ori,"TOTAL PRODUCT","B-300010",$C$20,"Amount_BS")*-1/1000 -> 359434.3 | I25: =_xll.DBR("CXMD:FTM_DATA_BALANCE_SHEET","Total_Customer_Supplier",I$22,$C$19,ori,"TOTAL PRODUCT","B-300010",$C$20,"Amount_BS")*-1/1000 -> 379893.72 | J25: =_xll.DBR("CXMD:FTM_DATA_BALANCE_SHEET","Total_Customer_Supplier",J$22,$C$19,ori,"TOTAL PRODUCT","B-300010",$C$20,"Amount_BS")*-1/1000 -> 380094.44 | K25: =_xll.DBR("CXMD:FTM_DATA_BALANCE_SHEET","Total_Customer_Supplier",K$22,$C$19,ori,"TOTAL PRODUCT","B-300010",$C$20,"Amount_BS")*-1/1000 -> 362873.71 | ... O25: =_xll.DBR("CXMD:FTM_DATA_BALANCE_SHEET","Total_Customer_Supplier",O$22,$C$19,ori,"TOTAL PRODUCT","B-300010",$C$20,"Amount_BS")*-1/1000 -> 252037.44 | P25: =SUM(D25:O25) -> 4072661.1
B26: G - 319000 - NET VARIATION OF STOCK | C26: Profit and Loss | D26: =_xll.DBR("CXMD:FTM_DATA_BALANCE_SHEET","Total_Customer_Supplier",D$22,$C$19,ori,"TOTAL PRODUCT","B-310010",$C$20,"Amount_BS")*-1/1000 -> -30807.778 | E26: =_xll.DBR("CXMD:FTM_DATA_BALANCE_SHEET","Total_Customer_Supplier",E$22,$C$19,ori,"TOTAL PRODUCT","B-310010",$C$20,"Amount_BS")*-1/1000 -> -7700.917 | F26: =_xll.DBR("CXMD:FTM_DATA_BALANCE_SHEET","Total_Customer_Supplier",F$22,$C$19,ori,"TOTAL PRODUCT","B-310010",$C$20,"Amount_BS")*-1/1000 -> 17816.846 | G26: =_xll.DBR("CXMD:FTM_DATA_BALANCE_SHEET","Total_Customer_Supplier",G$22,$C$19,ori,"TOTAL PRODUCT","B-310010",$C$20,"Amount_BS")*-1/1000 -> -5525.5791 | H26: =_xll.DBR("CXMD:FTM_DATA_BALANCE_SHEET","Total_Customer_Supplier",H$22,$C$19,ori,"TOTAL PRODUCT","B-310010",$C$20,"Amount_BS")*-1/1000 -> 23479.517 | I26: =_xll.DBR("CXMD:FTM_DATA_BALANCE_SHEET","Total_Customer_Supplier",I$22,$C$19,ori,"TOTAL PRODUCT","B-310010",$C$20,"Amount_BS")*-1/1000 -> -8578.8464 | J26: =_xll.DBR("CXMD:FTM_DATA_BALANCE_SHEET","Total_Customer_Supplier",J$22,$C$19,ori,"TOTAL PRODUCT","B-310010",$C$20,"Amount_BS")*-1/1000 -> -18897.088 | K26: =_xll.DBR("CXMD:FTM_DATA_BALANCE_SHEET","Total_Customer_Supplier",K$22,$C$19,ori,"TOTAL PRODUCT","B-310010",$C$20,"Amount_BS")*-1/1000 -> -224.62734 | ... O26: =_xll.DBR("CXMD:FTM_DATA_BALANCE_SHEET","Total_Customer_Supplier",O$22,$C$19,ori,"TOTAL PRODUCT","B-310010",$C$20,"Amount_BS")*-1/1000 -> 3887.5685 | P26: =SUM(D26:O26) -> 10475.845
B27: G-329000 Corporate output | D27: =D25+D26 -> 329035.72 | E27: =E25+E26 -> 332650.95 | F27: =F25+F26 -> 371683.02 | G27: =G25+G26 -> 317712.35 | H27: =H25+H26 -> 382913.81 | I27: =I25+I26 -> 371314.88 | J27: =J25+J26 -> 361197.35 | K27: =K25+K26 -> 362649.08 | ... O27: =O25+O26 -> 255925.01 | P27: =P23+P25 -> 4072661.1
B28: G - 339000 - OPERATING INCOME | C28: Profit and Loss | D28: =_xll.DBR("CXMD:FTM_DATA_BALANCE_SHEET","Total_Customer_Supplier",D$22,$C$19,ori,"TOTAL PRODUCT","B-330010",$C$20,"Amount_BS")*-1/1000 -> 4042.3655 | E28: =_xll.DBR("CXMD:FTM_DATA_BALANCE_SHEET","Total_Customer_Supplier",E$22,$C$19,ori,"TOTAL PRODUCT","B-330010",$C$20,"Amount_BS")*-1/1000 -> 4540.9253 | F28: =_xll.DBR("CXMD:FTM_DATA_BALANCE_SHEET","Total_Customer_Supplier",F$22,$C$19,ori,"TOTAL PRODUCT","B-330010",$C$20,"Amount_BS")*-1/1000 -> 4848.1721 | G28: =_xll.DBR("CXMD:FTM_DATA_BALANCE_SHEET","Total_Customer_Supplier",G$22,$C$19,ori,"TOTAL PRODUCT","B-330010",$C$20,"Amount_BS")*-1/1000 -> 4398.9568 | H28: =_xll.DBR("CXMD:FTM_DATA_BALANCE_SHEET","Total_Customer_Supplier",H$22,$C$19,ori,"TOTAL PRODUCT","B-330010",$C$20,"Amount_BS")*-1/1000 -> 4382.8768 | I28: =_xll.DBR("CXMD:FTM_DATA_BALANCE_SHEET","Total_Customer_Supplier",I$22,$C$19,ori,"TOTAL PRODUCT","B-330010",$C$20,"Amount_BS")*-1/1000 -> 4726.6561 | J28: =_xll.DBR("CXMD:FTM_DATA_BALANCE_SHEET","Total_Customer_Supplier",J$22,$C$19,ori,"TOTAL PRODUCT","B-330010",$C$20,"Amount_BS")*-1/1000 -> 4529.6568 | K28: =_xll.DBR("CXMD:FTM_DATA_BALANCE_SHEET","Total_Customer_Supplier",K$22,$C$19,ori,"TOTAL PRODUCT","B-330010",$C$20,"Amount_BS")*-1/1000 -> 4356.6035 | ... O28: =_xll.DBR("CXMD:FTM_DATA_BALANCE_SHEET","Total_Customer_Supplier",O$22,$C$19,ori,"TOTAL PRODUCT","B-330010",$C$20,"Amount_BS")*-1/1000 -> 2890.2751 | P28: =SUM(D28:O28) -> 52175.87
B29: REVENUE | D29: =D27+D28 -> 333078.08 | E29: =E27+E28 -> 337191.88 | F29: =F27+F28 -> 376531.2 | G29: =G27+G28 -> 322111.3 | H29: =H27+H28 -> 387296.69 | I29: =I27+I28 -> 376041.53 | J29: =J27+J28 -> 365727.01 | K29: =K27+K28 -> 367005.68 | ... O29: =O27+O28 -> 258815.28 | P29: =P26+P27 -> 4083136.9
B30: G - 452000 - VARIATION OF PROVISIONS | C30: Profit and Loss | D30: =D32+D33 -> 442.07326 | E30: =E32+E33 -> -194.91658 | F30: =F32+F33 -> 1613.4027 | G30: =G32+G33 -> 1257.8317 | H30: =H32+H33 -> -66.29061 | I30: =I32+I33 -> 544.75837 | J30: =J32+J33 -> 1477.1387 | K30: =K32+K33 -> 908.98217 | ... O30: =O32+O33 -> 9764.6165 | P30: =SUM(D30:O30) -> 29689.028
B31: G - 452000 - VARIATION OF PROVISIONS | C31: R-0-R-P-959000-OTHER EXPENSES | D31: =D32+D33 -> 442.07326 | E31: =E32+E33 -> -194.91658 | F31: =F32+F33 -> 1613.4027 | G31: =G32+G33 -> 1257.8317 | H31: =H32+H33 -> -66.29061 | I31: =I32+I33 -> 544.75837 | J31: =J32+J33 -> 1477.1387 | K31: =K32+K33 -> 908.98217 | ... O31: =O32+O33 -> 9764.6165 | P31: =SUM(D31:O31) -> 29689.028
B32: G - 452000 - VARIATION OF PROVISIONS | C32: B-0-B-P-452010-Allowances / value adj. | D32: =(_xll.DBR("CXMD:FTM_DATA_BALANCE_SHEET","Total_Customer_Supplier",D$22,$C$19,ori,"TOTAL PRODUCT","B-452010",$C$20,"Amount_BS")/1000) -> -83.31825 | E32: =(_xll.DBR("CXMD:FTM_DATA_BALANCE_SHEET","Total_Customer_Supplier",E$22,$C$19,ori,"TOTAL PRODUCT","B-452010",$C$20,"Amount_BS")/1000) -> -519 | F32: =(_xll.DBR("CXMD:FTM_DATA_BALANCE_SHEET","Total_Customer_Supplier",F$22,$C$19,ori,"TOTAL PRODUCT","B-452010",$C$20,"Amount_BS")/1000) -> 26.4192 | G32: =(_xll.DBR("CXMD:FTM_DATA_BALANCE_SHEET","Total_Customer_Supplier",G$22,$C$19,ori,"TOTAL PRODUCT","B-452010",$C$20,"Amount_BS")/1000) -> -67.354 | H32: =(_xll.DBR("CXMD:FTM_DATA_BALANCE_SHEET","Total_Customer_Supplier",H$22,$C$19,ori,"TOTAL PRODUCT","B-452010",$C$20,"Amount_BS")/1000) -> -21 | I32: =(_xll.DBR("CXMD:FTM_DATA_BALANCE_SHEET","Total_Customer_Supplier",I$22,$C$19,ori,"TOTAL PRODUCT","B-452010",$C$20,"Amount_BS")/1000) -> -1171.3866 | J32: =(_xll.DBR("CXMD:FTM_DATA_BALANCE_SHEET","Total_Customer_Supplier",J$22,$C$19,ori,"TOTAL PRODUCT","B-452010",$C$20,"Amount_BS")/1000) -> 67.37276 | K32: =(_xll.DBR("CXMD:FTM_DATA_BALANCE_SHEET","Total_Customer_Supplier",K$22,$C$19,ori,"TOTAL PRODUCT","B-452010",$C$20,"Amount_BS")/1000) -> -154.3 | ... O32: =(_xll.DBR("CXMD:FTM_DATA_BALANCE_SHEET","Total_Customer_Supplier",O$22,$C$19,ori,"TOTAL PRODUCT","B-452010",$C$20,"Amount_BS")/1000) -> 4812.0851 | P32: =SUM(D32:O32) -> 2871.1198
B33: G - 452000 - VARIATION OF PROVISIONS | C33: B-0-B-P-452210-Changes - provisions - | D33: =(_xll.DBR("CXMD:FTM_DATA_BALANCE_SHEET","Total_Customer_Supplier",D$22,$C$19,ori,"TOTAL PRODUCT","B-452210",$C$20,"Amount_BS")/1000) -> 525.39151 | E33: =(_xll.DBR("CXMD:FTM_DATA_BALANCE_SHEET","Total_Customer_Supplier",E$22,$C$19,ori,"TOTAL PRODUCT","B-452210",$C$20,"Amount_BS")/1000) -> 324.08342 | F33: =(_xll.DBR("CXMD:FTM_DATA_BALANCE_SHEET","Total_Customer_Supplier",F$22,$C$19,ori,"TOTAL PRODUCT","B-452210",$C$20,"Amount_BS")/1000) -> 1586.9835 | G33: =(_xll.DBR("CXMD:FTM_DATA_BALANCE_SHEET","Total_Customer_Supplier",G$22,$C$19,ori,"TOTAL PRODUCT","B-452210",$C$20,"Amount_BS")/1000) -> 1325.1857 | H33: =(_xll.DBR("CXMD:FTM_DATA_BALANCE_SHEET","Total_Customer_Supplier",H$22,$C$19,ori,"TOTAL PRODUCT","B-452210",$C$20,"Amount_BS")/1000) -> -45.29061 | I33: =(_xll.DBR("CXMD:FTM_DATA_BALANCE_SHEET","Total_Customer_Supplier",I$22,$C$19,ori,"TOTAL PRODUCT","B-452210",$C$20,"Amount_BS")/1000) -> 1716.145 | J33: =(_xll.DBR("CXMD:FTM_DATA_BALANCE_SHEET","Total_Customer_Supplier",J$22,$C$19,ori,"TOTAL PRODUCT","B-452210",$C$20,"Amount_BS")/1000) -> 1409.7659 | K33: =(_xll.DBR("CXMD:FTM_DATA_BALANCE_SHEET","Total_Customer_Supplier",K$22,$C$19,ori,"TOTAL PRODUCT","B-452210",$C$20,"Amount_BS")/1000) -> 1063.2822 | ... O33: =(_xll.DBR("CXMD:FTM_DATA_BALANCE_SHEET","Total_Customer_Supplier",O$22,$C$19,ori,"TOTAL PRODUCT","B-452210",$C$20,"Amount_BS")/1000) -> 4952.5314 | P33: =SUM(D33:O33) -> 26817.908
B34: Total Material expenses + net var. stock | C34: Profit and Loss | D34: =(_xll.DBR("CXMD:FTM_DATA_BALANCE_SHEET","Total_Customer_Supplier",D$22,$C$19,ori,"TOTAL PRODUCT","B-401010",$C$20,"Amount_BS")/1000)+(_xll.DBR("CXMD:FTM_DATA_BALANCE_SHEET","Total_Customer_Supplier",D$22,$C$19,ori,"TOTAL PRODUCT","B-401020",$C$20,"Amount_BS")/1000)+(_xll.DBR("CXMD:FTM_DATA_BALANCE_SHEET","Total_Customer_Supplier",D$22,$C$19,ori,"TOTAL PRODUCT","B-402110",$C$20,"Amount_BS")/1000)+(_xll.DBR("CXMD:FTM_DATA_BALANCE_SHEET","Total_Customer_Supplier",D$22,$C$19,ori,"TOTAL PRODUCT","B-402111",$C$20,"Amount_BS")/1000)+(_xll.DBR("CXMD:FTM_DATA_BALANCE_SHEET","Total_Customer_Supplier",D$22,$C$19,ori,"TOTAL PRODUCT","B-407010",$C$20,"Amount_BS")/1000) -> 190042.62 | E34: =(_xll.DBR("CXMD:FTM_DATA_BALANCE_SHEET","Total_Customer_Supplier",E$22,$C$19,ori,"TOTAL PRODUCT","B-401010",$C$20,"Amount_BS")/1000)+(_xll.DBR("CXMD:FTM_DATA_BALANCE_SHEET","Total_Customer_Supplier",E$22,$C$19,ori,"TOTAL PRODUCT","B-401020",$C$20,"Amount_BS")/1000)+(_xll.DBR("CXMD:FTM_DATA_BALANCE_SHEET","Total_Customer_Supplier",E$22,$C$19,ori,"TOTAL PRODUCT","B-402110",$C$20,"Amount_BS")/1000)+(_xll.DBR("CXMD:FTM_DATA_BALANCE_SHEET","Total_Customer_Supplier",E$22,$C$19,ori,"TOTAL PRODUCT","B-402111",$C$20,"Amount_BS")/1000)+(_xll.DBR("CXMD:FTM_DATA_BALANCE_SHEET","Total_Customer_Supplier",E$22,$C$19,ori,"TOTAL PRODUCT","B-407010",$C$20,"Amount_BS")/1000) -> 192852.16 | F34: =(_xll.DBR("CXMD:FTM_DATA_BALANCE_SHEET","Total_Customer_Supplier",F$22,$C$19,ori,"TOTAL PRODUCT","B-401010",$C$20,"Amount_BS")/1000)+(_xll.DBR("CXMD:FTM_DATA_BALANCE_SHEET","Total_Customer_Supplier",F$22,$C$19,ori,"TOTAL PRODUCT","B-401020",$C$20,"Amount_BS")/1000)+(_xll.DBR("CXMD:FTM_DATA_BALANCE_SHEET","Total_Customer_Supplier",F$22,$C$19,ori,"TOTAL PRODUCT","B-402110",$C$20,"Amount_BS")/1000)+(_xll.DBR("CXMD:FTM_DATA_BALANCE_SHEET","Total_Customer_Supplier",F$22,$C$19,ori,"TOTAL PRODUCT","B-402111",$C$20,"Amount_BS")/1000)+(_xll.DBR("CXMD:FTM_DATA_BALANCE_SHEET","Total_Customer_Supplier",F$22,$C$19,ori,"TOTAL PRODUCT","B-407010",$C$20,"Amount_BS")/1000) -> 252392.84 | G34: =(_xll.DBR("CXMD:FTM_DATA_BALANCE_SHEET","Total_Customer_Supplier",G$22,$C$19,ori,"TOTAL PRODUCT","B-401010",$C$20,"Amount_BS")/1000)+(_xll.DBR("CXMD:FTM_DATA_BALANCE_SHEET","Total_Customer_Supplier",G$22,$C$19,ori,"TOTAL PRODUCT","B-401020",$C$20,"Amount_BS")/1000)+(_xll.DBR("CXMD:FTM_DATA_BALANCE_SHEET","Total_Customer_Supplier",G$22,$C$19,ori,"TOTAL PRODUCT","B-402110",$C$20,"Amount_BS")/1000)+(_xll.DBR("CXMD:FTM_DATA_BALANCE_SHEET","Total_Customer_Supplier",G$22,$C$19,ori,"TOTAL PRODUCT","B-402111",$C$20,"Amount_BS")/1000)+(_xll.DBR("CXMD:FTM_DATA_BALANCE_SHEET","Total_Customer_Supplier",G$22,$C$19,ori,"TOTAL PRODUCT","B-407010",$C$20,"Amount_BS")/1000) -> 210140.84 | H34: =(_xll.DBR("CXMD:FTM_DATA_BALANCE_SHEET","Total_Customer_Supplier",H$22,$C$19,ori,"TOTAL PRODUCT","B-401010",$C$20,"Amount_BS")/1000)+(_xll.DBR("CXMD:FTM_DATA_BALANCE_SHEET","Total_Customer_Supplier",H$22,$C$19,ori,"TOTAL PRODUCT","B-401020",$C$20,"Amount_BS")/1000)+(_xll.DBR("CXMD:FTM_DATA_BALANCE_SHEET","Total_Customer_Supplier",H$22,$C$19,ori,"TOTAL PRODUCT","B-402110",$C$20,"Amount_BS")/1000)+(_xll.DBR("CXMD:FTM_DATA_BALANCE_SHEET","Total_Customer_Supplier",H$22,$C$19,ori,"TOTAL PRODUCT","B-402111",$C$20,"Amount_BS")/1000)+(_xll.DBR("CXMD:FTM_DATA_BALANCE_SHEET","Total_Customer_Supplier",H$22,$C$19,ori,"TOTAL PRODUCT","B-407010",$C$20,"Amount_BS")/1000) -> 243390.75 | I34: =(_xll.DBR("CXMD:FTM_DATA_BALANCE_SHEET","Total_Customer_Supplier",I$22,$C$19,ori,"TOTAL PRODUCT","B-401010",$C$20,"Amount_BS")/1000)+(_xll.DBR("CXMD:FTM_DATA_BALANCE_SHEET","Total_Customer_Supplier",I$22,$C$19,ori,"TOTAL PRODUCT","B-401020",$C$20,"Amount_BS")/1000)+(_xll.DBR("CXMD:FTM_DATA_BALANCE_SHEET","Total_Customer_Supplier",I$22,$C$19,ori,"TOTAL PRODUCT","B-402110",$C$20,"Amount_BS")/1000)+(_xll.DBR("CXMD:FTM_DATA_BALANCE_SHEET","Total_Customer_Supplier",I$22,$C$19,ori,"TOTAL PRODUCT","B-402111",$C$20,"Amount_BS")/1000)+(_xll.DBR("CXMD:FTM_DATA_BALANCE_SHEET","Total_Customer_Supplier",I$22,$C$19,ori,"TOTAL PRODUCT","B-407010",$C$20,"Amount_BS")/1000) -> 235213 | J34: =(_xll.DBR("CXMD:FTM_DATA_BALANCE_SHEET","Total_Customer_Supplier",J$22,$C$19,ori,"TOTAL PRODUCT","B-401010",$C$20,"Amount_BS")/1000)+(_xll.DBR("CXMD:FTM_DATA_BALANCE_SHEET","Total_Customer_Supplier",J$22,$C$19,ori,"TOTAL PRODUCT","B-401020",$C$20,"Amount_BS")/1000)+(_xll.DBR("CXMD:FTM_DATA_BALANCE_SHEET","Total_Customer_Supplier",J$22,$C$19,ori,"TOTAL PRODUCT","B-402110",$C$20,"Amount_BS")/1000)+(_xll.DBR("CXMD:FTM_DATA_BALANCE_SHEET","Total_Customer_Supplier",J$22,$C$19,ori,"TOTAL PRODUCT","B-402111",$C$20,"Amount_BS")/1000)+(_xll.DBR("CXMD:FTM_DATA_BALANCE_SHEET","Total_Customer_Supplier",J$22,$C$19,ori,"TOTAL PRODUCT","B-407010",$C$20,"Amount_BS")/1000) -> 221949.36 | K34: =(_xll.DBR("CXMD:FTM_DATA_BALANCE_SHEET","Total_Customer_Supplier",K$22,$C$19,ori,"TOTAL PRODUCT","B-401010",$C$20,"Amount_BS")/1000)+(_xll.DBR("CXMD:FTM_DATA_BALANCE_SHEET","Total_Customer_Supplier",K$22,$C$19,ori,"TOTAL PRODUCT","B-401020",$C$20,"Amount_BS")/1000)+(_xll.DBR("CXMD:FTM_DATA_BALANCE_SHEET","Total_Customer_Supplier",K$22,$C$19,ori,"TOTAL PRODUCT","B-402110",$C$20,"Amount_BS")/1000)+(_xll.DBR("CXMD:FTM_DATA_BALANCE_SHEET","Total_Customer_Supplier",K$22,$C$19,ori,"TOTAL PRODUCT","B-402111",$C$20,"Amount_BS")/1000)+(_xll.DBR("CXMD:FTM_DATA_BALANCE_SHEET","Total_Customer_Supplier",K$22,$C$19,ori,"TOTAL PRODUCT","B-407010",$C$20,"Amount_BS")/1000) -> 199063.85 | ... O34: =(_xll.DBR("CXMD:FTM_DATA_BALANCE_SHEET","Total_Customer_Supplier",O$22,$C$19,ori,"TOTAL PRODUCT","B-401010",$C$20,"Amount_BS")/1000)+(_xll.DBR("CXMD:FTM_DATA_BALANCE_SHEET","Total_Customer_Supplier",O$22,$C$19,ori,"TOTAL PRODUCT","B-401020",$C$20,"Amount_BS")/1000)+(_xll.DBR("CXMD:FTM_DATA_BALANCE_SHEET","Total_Customer_Supplier",O$22,$C$19,ori,"TOTAL PRODUCT","B-402110",$C$20,"Amount_BS")/1000)+(_xll.DBR("CXMD:FTM_DATA_BALANCE_SHEET","Total_Customer_Supplier",O$22,$C$19,ori,"TOTAL PRODUCT","B-402111",$C$20,"Amount_BS")/1000)+(_xll.DBR("CXMD:FTM_DATA_BALANCE_SHEET","Total_Customer_Supplier",O$22,$C$19,ori,"TOTAL PRODUCT","B-407010",$C$20,"Amount_BS")/1000) -> 161641.24 | P34: =SUM(D34:O34) -> 2543662.2
C35: % of corporate output | D35: =IF(D27<>0,D34/D27,0) -> 0.57757445 | E35: =IF(E27<>0,E34/E27,0) -> 0.57974328 | F35: =IF(F27<>0,F34/F27,0) -> 0.679054 | G35: =IF(G27<>0,G34/G27,0) -> 0.66141854 | H35: =IF(H27<>0,H34/H27,0) -> 0.63562803 | I35: =IF(I27<>0,I34/I27,0) -> 0.63345967 | J35: =IF(J27<>0,J34/J27,0) -> 0.61448226 | K35: =IF(K27<>0,K34/K27,0) -> 0.54891592 | ... O35: =IF(O27<>0,O34/O27,0) -> 0.63159611 | P35: =IF(P26<>0,P34/P26,0) -> 242.81212
B36: G - 415000 - MATERIAL & OUTSIDE COSTS | C36: R-0-R-P-901000-MATERIAL EXPENSES | D36: =(_xll.DBR("CXMD:FTM_DATA_BALANCE_SHEET","Total_Customer_Supplier",D$22,$C$19,ori,"TOTAL PRODUCT","R-901000",$C$20,"Amount_BS")/1000) -> 190042.62 | E36: =(_xll.DBR("CXMD:FTM_DATA_BALANCE_SHEET","Total_Customer_Supplier",E$22,$C$19,ori,"TOTAL PRODUCT","R-901000",$C$20,"Amount_BS")/1000) -> 192852.16 | F36: =(_xll.DBR("CXMD:FTM_DATA_BALANCE_SHEET","Total_Customer_Supplier",F$22,$C$19,ori,"TOTAL PRODUCT","R-901000",$C$20,"Amount_BS")/1000) -> 252392.84 | G36: =(_xll.DBR("CXMD:FTM_DATA_BALANCE_SHEET","Total_Customer_Supplier",G$22,$C$19,ori,"TOTAL PRODUCT","R-901000",$C$20,"Amount_BS")/1000) -> 210140.84 | H36: =(_xll.DBR("CXMD:FTM_DATA_BALANCE_SHEET","Total_Customer_Supplier",H$22,$C$19,ori,"TOTAL PRODUCT","R-901000",$C$20,"Amount_BS")/1000) -> 243390.75 | I36: =(_xll.DBR("CXMD:FTM_DATA_BALANCE_SHEET","Total_Customer_Supplier",I$22,$C$19,ori,"TOTAL PRODUCT","R-901000",$C$20,"Amount_BS")/1000) -> 235213 | J36: =(_xll.DBR("CXMD:FTM_DATA_BALANCE_SHEET","Total_Customer_Supplier",J$22,$C$19,ori,"TOTAL PRODUCT","R-901000",$C$20,"Amount_BS")/1000) -> 221949.36 | K36: =(_xll.DBR("CXMD:FTM_DATA_BALANCE_SHEET","Total_Customer_Supplier",K$22,$C$19,ori,"TOTAL PRODUCT","R-901000",$C$20,"Amount_BS")/1000) -> 199063.85 | ... O36: =(_xll.DBR("CXMD:FTM_DATA_BALANCE_SHEET","Total_Customer_Supplier",O$22,$C$19,ori,"TOTAL PRODUCT","R-901000",$C$20,"Amount_BS")/1000) -> 161641.24 | P36: =SUM(D36:O36) -> 2543662.2
B37: G - 415000 - MATERIAL & OUTSIDE COSTS | C37: B-0-B-P-401010-Purchase expense - 3rd p | D37: =(_xll.DBR("CXMD:FTM_DATA_BALANCE_SHEET","Total_Customer_Supplier",D$22,$C$19,ori,"TOTAL PRODUCT","B-401010",$C$20,"Amount_BS")/1000) -> 72512.263 | E37: =(_xll.DBR("CXMD:FTM_DATA_BALANCE_SHEET","Total_Customer_Supplier",E$22,$C$19,ori,"TOTAL PRODUCT","B-401010",$C$20,"Amount_BS")/1000) -> 91171.248 | F37: =(_xll.DBR("CXMD:FTM_DATA_BALANCE_SHEET","Total_Customer_Supplier",F$22,$C$19,ori,"TOTAL PRODUCT","B-401010",$C$20,"Amount_BS")/1000) -> 109526.19 | G37: =(_xll.DBR("CXMD:FTM_DATA_BALANCE_SHEET","Total_Customer_Supplier",G$22,$C$19,ori,"TOTAL PRODUCT","B-401010",$C$20,"Amount_BS")/1000) -> 86644.048 | H37: =(_xll.DBR("CXMD:FTM_DATA_BALANCE_SHEET","Total_Customer_Supplier",H$22,$C$19,ori,"TOTAL PRODUCT","B-401010",$C$20,"Amount_BS")/1000) -> 117977.35 | I37: =(_xll.DBR("CXMD:FTM_DATA_BALANCE_SHEET","Total_Customer_Supplier",I$22,$C$19,ori,"TOTAL PRODUCT","B-401010",$C$20,"Amount_BS")/1000) -> 106691.98 | J37: =(_xll.DBR("CXMD:FTM_DATA_BALANCE_SHEET","Total_Customer_Supplier",J$22,$C$19,ori,"TOTAL PRODUCT","B-401010",$C$20,"Amount_BS")/1000) -> 109483.73 | K37: =(_xll.DBR("CXMD:FTM_DATA_BALANCE_SHEET","Total_Customer_Supplier",K$22,$C$19,ori,"TOTAL PRODUCT","B-401010",$C$20,"Amount_BS")/1000) -> 108477.08 | ... O37: =(_xll.DBR("CXMD:FTM_DATA_BALANCE_SHEET","Total_Customer_Supplier",O$22,$C$19,ori,"TOTAL PRODUCT","B-401010",$C$20,"Amount_BS")/1000) -> 69232.503 | P37: =SUM(D37:O37) -> 1204713.2
B38: G - 415000 - MATERIAL & OUTSIDE COSTS | C38: B-0-B-P-407010-Outside suppliers / serv | D38: =(_xll.DBR("CXMD:FTM_DATA_BALANCE_SHEET","Total_Customer_Supplier",D$22,$C$19,ori,"TOTAL PRODUCT","B-407010",$C$20,"Amount_BS")/1000) -> 22443.169 | E38: =(_xll.DBR("CXMD:FTM_DATA_BALANCE_SHEET","Total_Customer_Supplier",E$22,$C$19,ori,"TOTAL PRODUCT","B-407010",$C$20,"Amount_BS")/1000) -> 23140.054 | F38: =(_xll.DBR("CXMD:FTM_DATA_BALANCE_SHEET","Total_Customer_Supplier",F$22,$C$19,ori,"TOTAL PRODUCT","B-407010",$C$20,"Amount_BS")/1000) -> 25473.465 | G38: =(_xll.DBR("CXMD:FTM_DATA_BALANCE_SHEET","Total_Customer_Supplier",G$22,$C$19,ori,"TOTAL PRODUCT","B-407010",$C$20,"Amount_BS")/1000) -> 22108.669 | H38: =(_xll.DBR("CXMD:FTM_DATA_BALANCE_SHEET","Total_Customer_Supplier",H$22,$C$19,ori,"TOTAL PRODUCT","B-407010",$C$20,"Amount_BS")/1000) -> 21441.586 | I38: =(_xll.DBR("CXMD:FTM_DATA_BALANCE_SHEET","Total_Customer_Supplier",I$22,$C$19,ori,"TOTAL PRODUCT","B-407010",$C$20,"Amount_BS")/1000) -> 20699.129 | J38: =(_xll.DBR("CXMD:FTM_DATA_BALANCE_SHEET","Total_Customer_Supplier",J$22,$C$19,ori,"TOTAL PRODUCT","B-407010",$C$20,"Amount_BS")/1000) -> 14473.98 | K38: =(_xll.DBR("CXMD:FTM_DATA_BALANCE_SHEET","Total_Customer_Supplier",K$22,$C$19,ori,"TOTAL PRODUCT","B-407010",$C$20,"Amount_BS")/1000) -> 10355.237 | ... O38: =(_xll.DBR("CXMD:FTM_DATA_BALANCE_SHEET","Total_Customer_Supplier",O$22,$C$19,ori,"TOTAL PRODUCT","B-407010",$C$20,"Amount_BS")/1000) -> 15903.05 | P38: =SUM(D38:O38) -> 234604.31
B39: G - 415000 - MATERIAL & OUTSIDE COSTS | C39: B-0-B-P-402110-VALUE ADJ PURCHASED ITEMS | D39: =(_xll.DBR("CXMD:FTM_DATA_BALANCE_SHEET","Total_Customer_Supplier",D$22,$C$19,ori,"TOTAL PRODUCT","B-402110",$C$20,"Amount_BS")/1000) -> 879.40244 | E39: =(_xll.DBR("CXMD:FTM_DATA_BALANCE_SHEET","Total_Customer_Supplier",E$22,$C$19,ori,"TOTAL PRODUCT","B-402110",$C$20,"Amount_BS")/1000) -> 572.56528 | F39: =(_xll.DBR("CXMD:FTM_DATA_BALANCE_SHEET","Total_Customer_Supplier",F$22,$C$19,ori,"TOTAL PRODUCT","B-402110",$C$20,"Amount_BS")/1000) -> 2615.1559 | G39: =(_xll.DBR("CXMD:FTM_DATA_BALANCE_SHEET","Total_Customer_Supplier",G$22,$C$19,ori,"TOTAL PRODUCT","B-402110",$C$20,"Amount_BS")/1000) -> 9161.3965 | H39: =(_xll.DBR("CXMD:FTM_DATA_BALANCE_SHEET","Total_Customer_Supplier",H$22,$C$19,ori,"TOTAL PRODUCT","B-402110",$C$20,"Amount_BS")/1000) -> -3906.9356 | I39: =(_xll.DBR("CXMD:FTM_DATA_BALANCE_SHEET","Total_Customer_Supplier",I$22,$C$19,ori,"TOTAL PRODUCT","B-402110",$C$20,"Amount_BS")/1000) -> -886.24674 | J39: =(_xll.DBR("CXMD:FTM_DATA_BALANCE_SHEET","Total_Customer_Supplier",J$22,$C$19,ori,"TOTAL PRODUCT","B-402110",$C$20,"Amount_BS")/1000) -> -622.85441 | K39: =(_xll.DBR("CXMD:FTM_DATA_BALANCE_SHEET","Total_Customer_Supplier",K$22,$C$19,ori,"TOTAL PRODUCT","B-402110",$C$20,"Amount_BS")/1000) -> 2744.3925 | ... O39: =(_xll.DBR("CXMD:FTM_DATA_BALANCE_SHEET","Total_Customer_Supplier",O$22,$C$19,ori,"TOTAL PRODUCT","B-402110",$C$20,"Amount_BS")/1000) -> -384.62694 | P39: =SUM(D39:O39) -> 11433.648
B40: G - 415000 - MATERIAL & OUTSIDE COSTS | C40: B-0-B-P-402111-VALUE ADJ-RESALE OTHER. | D40: =(_xll.DBR("CXMD:FTM_DATA_BALANCE_SHEET","Total_Customer_Supplier",D$22,$C$19,ori,"TOTAL PRODUCT","B-402111",$C$20,"Amount_BS")/1000) -> -98.02402 | E40: =(_xll.DBR("CXMD:FTM_DATA_BALANCE_SHEET","Total_Customer_Supplier",E$22,$C$19,ori,"TOTAL PRODUCT","B-402111",$C$20,"Amount_BS")/1000) -> 87.5648 | F40: =(_xll.DBR("CXMD:FTM_DATA_BALANCE_SHEET","Total_Customer_Supplier",F$22,$C$19,ori,"TOTAL PRODUCT","B-402111",$C$20,"Amount_BS")/1000) -> -57.40492 | G40: =(_xll.DBR("CXMD:FTM_DATA_BALANCE_SHEET","Total_Customer_Supplier",G$22,$C$19,ori,"TOTAL PRODUCT","B-402111",$C$20,"Amount_BS")/1000) -> -19.15553 | H40: =(_xll.DBR("CXMD:FTM_DATA_BALANCE_SHEET","Total_Customer_Supplier",H$22,$C$19,ori,"TOTAL PRODUCT","B-402111",$C$20,"Amount_BS")/1000) -> -1.60024 | I40: =(_xll.DBR("CXMD:FTM_DATA_BALANCE_SHEET","Total_Customer_Supplier",I$22,$C$19,ori,"TOTAL PRODUCT","B-402111",$C$20,"Amount_BS")/1000) -> 47.71892 | J40: =(_xll.DBR("CXMD:FTM_DATA_BALANCE_SHEET","Total_Customer_Supplier",J$22,$C$19,ori,"TOTAL PRODUCT","B-402111",$C$20,"Amount_BS")/1000) -> 31.91721 | K40: =(_xll.DBR("CXMD:FTM_DATA_BALANCE_SHEET","Total_Customer_Supplier",K$22,$C$19,ori,"TOTAL PRODUCT","B-402111",$C$20,"Amount_BS")/1000) -> -92.55371 | ... O40: =(_xll.DBR("CXMD:FTM_DATA_BALANCE_SHEET","Total_Customer_Supplier",O$22,$C$19,ori,"TOTAL PRODUCT","B-402111",$C$20,"Amount_BS")/1000) -> -85.09845 | P40: =SUM(D40:O40) -> -96.38179
C41: B-0-B-P-401020-Purchase expense - IC | D41: =(_xll.DBR("CXMD:FTM_DATA_BALANCE_SHEET","Total_Customer_Supplier",D$22,$C$19,ori,"TOTAL PRODUCT","B-401020",$C$20,"Amount_BS")/1000) -> 94305.811 | E41: =(_xll.DBR("CXMD:FTM_DATA_BALANCE_SHEET","Total_Customer_Supplier",E$22,$C$19,ori,"TOTAL PRODUCT","B-401020",$C$20,"Amount_BS")/1000) -> 77880.725 | F41: =(_xll.DBR("CXMD:FTM_DATA_BALANCE_SHEET","Total_Customer_Supplier",F$22,$C$19,ori,"TOTAL PRODUCT","B-401020",$C$20,"Amount_BS")/1000) -> 114835.44 | G41: =(_xll.DBR("CXMD:FTM_DATA_BALANCE_SHEET","Total_Customer_Supplier",G$22,$C$19,ori,"TOTAL PRODUCT","B-401020",$C$20,"Amount_BS")/1000) -> 92245.88 | H41: =(_xll.DBR("CXMD:FTM_DATA_BALANCE_SHEET","Total_Customer_Supplier",H$22,$C$19,ori,"TOTAL PRODUCT","B-401020",$C$20,"Amount_BS")/1000) -> 107880.35 | I41: =(_xll.DBR("CXMD:FTM_DATA_BALANCE_SHEET","Total_Customer_Supplier",I$22,$C$19,ori,"TOTAL PRODUCT","B-401020",$C$20,"Amount_BS")/1000) -> 108660.42 | J41: =(_xll.DBR("CXMD:FTM_DATA_BALANCE_SHEET","Total_Customer_Supplier",J$22,$C$19,ori,"TOTAL PRODUCT","B-401020",$C$20,"Amount_BS")/1000) -> 98582.588 | K41: =(_xll.DBR("CXMD:FTM_DATA_BALANCE_SHEET","Total_Customer_Supplier",K$22,$C$19,ori,"TOTAL PRODUCT","B-401020",$C$20,"Amount_BS")/1000) -> 77579.693 | ... O41: =(_xll.DBR("CXMD:FTM_DATA_BALANCE_SHEET","Total_Customer_Supplier",O$22,$C$19,ori,"TOTAL PRODUCT","B-401020",$C$20,"Amount_BS")/1000) -> 76975.412 | P41: =SUM(D41:O41) -> 1093007.4
C42: R-0-R-P-959000-OTHER EXPENSES | D42: =D43 -> 0 | E42: =E43 -> 0 | F42: =F43 -> 0 | G42: =G43 -> 0 | H42: =H43 -> 0 | I42: =I43 -> 0 | J42: =J43 -> 0 | K42: =K43 -> 0 | ... O42: =O43 -> 0 | P42: =SUM(D42:O42) -> 0
B43: G - 415000 - MATERIAL & OUTSIDE COSTS | C43: B-0-B-P-451020-Repair / maintenance / r | D43: =0 -> 0 | E43: =0 -> 0 | F43: =0 -> 0 | G43: =0 -> 0 | H43: =0 -> 0 | I43: =0 -> 0 | J43: =0 -> 0 | K43: =0 -> 0 | ... O43: =0 -> 0 | P43: =SUM(D43:O43) -> 0
B44: G-429999-GROSS MARGIN | D44: =D29-D34 -> 143035.46 | E44: =E29-E34 -> 144339.72 | F44: =F29-F34 -> 124138.35 | G44: =G29-G34 -> 111970.47 | H44: =H29-H34 -> 143905.94 | I44: =I29-I34 -> 140828.54 | J44: =J29-J34 -> 143777.64 | K44: =K29-K34 -> 167941.83 | ... P44: =P29-P34 -> 1539474.7
C45: % of corporate output | D45: =IF(D27<>0,D44/D27,0) -> 0.43471105 | E45: =IF(E27<>0,E44/E27,0) -> 0.43390744 | F45: =IF(F27<>0,F44/F27,0) -> 0.33398984 | G45: =IF(G27<>0,G44/G27,0) -> 0.35242718 | H45: =IF(H27<>0,H44/H27,0) -> 0.37581809 | I45: =IF(I27<>0,I44/I27,0) -> 0.37926984 | J45: =IF(J27<>0,J44/J27,0) -> 0.39805841 | K45: =IF(K27<>0,K44/K27,0) -> 0.46309736 | ... O45: =IF(O27<>0,O44/O27,0) -> 0.37969734 | P45: =IF(P26<>0,P44/P26,0) -> 146.9547
B46: G - 439000 - PERSONNEL COSTS | C46: Profit and Loss | D46: =(_xll.DBR("CXMD:FTM_DATA_BALANCE_SHEET","Total_Customer_Supplier",D$22,$C$19,ori,"TOTAL PRODUCT","B-430010",$C$20,"Amount_BS")/1000)+(_xll.DBR("CXMD:FTM_DATA_BALANCE_SHEET","Total_Customer_Supplier",D$22,$C$19,ori,"TOTAL PRODUCT","B-430040",$C$20,"Amount_BS")/1000)+(_xll.DBR("CXMD:FTM_DATA_BALANCE_SHEET","Total_Customer_Supplier",D$22,$C$19,ori,"TOTAL PRODUCT","B-431040",$C$20,"Amount_BS")/1000)+(_xll.DBR("CXMD:FTM_DATA_BALANCE_SHEET","Total_Customer_Supplier",D$22,$C$19,ori,"TOTAL PRODUCT","B-437010",$C$20,"Amount_BS")/1000)+(_xll.DBR("CXMD:FTM_DATA_BALANCE_SHEET","Total_Customer_Supplier",D$22,$C$19,ori,"TOTAL PRODUCT","B-438010",$C$20,"Amount_BS")/1000) -> 37400.484 | E46: =(_xll.DBR("CXMD:FTM_DATA_BALANCE_SHEET","Total_Customer_Supplier",E$22,$C$19,ori,"TOTAL PRODUCT","B-430010",$C$20,"Amount_BS")/1000)+(_xll.DBR("CXMD:FTM_DATA_BALANCE_SHEET","Total_Customer_Supplier",E$22,$C$19,ori,"TOTAL PRODUCT","B-430040",$C$20,"Amount_BS")/1000)+(_xll.DBR("CXMD:FTM_DATA_BALANCE_SHEET","Total_Customer_Supplier",E$22,$C$19,ori,"TOTAL PRODUCT","B-431040",$C$20,"Amount_BS")/1000)+(_xll.DBR("CXMD:FTM_DATA_BALANCE_SHEET","Total_Customer_Supplier",E$22,$C$19,ori,"TOTAL PRODUCT","B-437010",$C$20,"Amount_BS")/1000)+(_xll.DBR("CXMD:FTM_DATA_BALANCE_SHEET","Total_Customer_Supplier",E$22,$C$19,ori,"TOTAL PRODUCT","B-438010",$C$20,"Amount_BS")/1000) -> 40241.933 | F46: =(_xll.DBR("CXMD:FTM_DATA_BALANCE_SHEET","Total_Customer_Supplier",F$22,$C$19,ori,"TOTAL PRODUCT","B-430010",$C$20,"Amount_BS")/1000)+(_xll.DBR("CXMD:FTM_DATA_BALANCE_SHEET","Total_Customer_Supplier",F$22,$C$19,ori,"TOTAL PRODUCT","B-430040",$C$20,"Amount_BS")/1000)+(_xll.DBR("CXMD:FTM_DATA_BALANCE_SHEET","Total_Customer_Supplier",F$22,$C$19,ori,"TOTAL PRODUCT","B-431040",$C$20,"Amount_BS")/1000)+(_xll.DBR("CXMD:FTM_DATA_BALANCE_SHEET","Total_Customer_Supplier",F$22,$C$19,ori,"TOTAL PRODUCT","B-437010",$C$20,"Amount_BS")/1000)+(_xll.DBR("CXMD:FTM_DATA_BALANCE_SHEET","Total_Customer_Supplier",F$22,$C$19,ori,"TOTAL PRODUCT","B-438010",$C$20,"Amount_BS")/1000) -> 41481.869 | G46: =(_xll.DBR("CXMD:FTM_DATA_BALANCE_SHEET","Total_Customer_Supplier",G$22,$C$19,ori,"TOTAL PRODUCT","B-430010",$C$20,"Amount_BS")/1000)+(_xll.DBR("CXMD:FTM_DATA_BALANCE_SHEET","Total_Customer_Supplier",G$22,$C$19,ori,"TOTAL PRODUCT","B-430040",$C$20,"Amount_BS")/1000)+(_xll.DBR("CXMD:FTM_DATA_BALANCE_SHEET","Total_Customer_Supplier",G$22,$C$19,ori,"TOTAL PRODUCT","B-431040",$C$20,"Amount_BS")/1000)+(_xll.DBR("CXMD:FTM_DATA_BALANCE_SHEET","Total_Customer_Supplier",G$22,$C$19,ori,"TOTAL PRODUCT","B-437010",$C$20,"Amount_BS")/1000)+(_xll.DBR("CXMD:FTM_DATA_BALANCE_SHEET","Total_Customer_Supplier",G$22,$C$19,ori,"TOTAL PRODUCT","B-438010",$C$20,"Amount_BS")/1000) -> 38295.867 | H46: =(_xll.DBR("CXMD:FTM_DATA_BALANCE_SHEET","Total_Customer_Supplier",H$22,$C$19,ori,"TOTAL PRODUCT","B-430010",$C$20,"Amount_BS")/1000)+(_xll.DBR("CXMD:FTM_DATA_BALANCE_SHEET","Total_Customer_Supplier",H$22,$C$19,ori,"TOTAL PRODUCT","B-430040",$C$20,"Amount_BS")/1000)+(_xll.DBR("CXMD:FTM_DATA_BALANCE_SHEET","Total_Customer_Supplier",H$22,$C$19,ori,"TOTAL PRODUCT","B-431040",$C$20,"Amount_BS")/1000)+(_xll.DBR("CXMD:FTM_DATA_BALANCE_SHEET","Total_Customer_Supplier",H$22,$C$19,ori,"TOTAL PRODUCT","B-437010",$C$20,"Amount_BS")/1000)+(_xll.DBR("CXMD:FTM_DATA_BALANCE_SHEET","Total_Customer_Supplier",H$22,$C$19,ori,"TOTAL PRODUCT","B-438010",$C$20,"Amount_BS")/1000) -> 40150.205 | I46: =(_xll.DBR("CXMD:FTM_DATA_BALANCE_SHEET","Total_Customer_Supplier",I$22,$C$19,ori,"TOTAL PRODUCT","B-430010",$C$20,"Amount_BS")/1000)+(_xll.DBR("CXMD:FTM_DATA_BALANCE_SHEET","Total_Customer_Supplier",I$22,$C$19,ori,"TOTAL PRODUCT","B-430040",$C$20,"Amount_BS")/1000)+(_xll.DBR("CXMD:FTM_DATA_BALANCE_SHEET","Total_Customer_Supplier",I$22,$C$19,ori,"TOTAL PRODUCT","B-431040",$C$20,"Amount_BS")/1000)+(_xll.DBR("CXMD:FTM_DATA_BALANCE_SHEET","Total_Customer_Supplier",I$22,$C$19,ori,"TOTAL PRODUCT","B-437010",$C$20,"Amount_BS")/1000)+(_xll.DBR("CXMD:FTM_DATA_BALANCE_SHEET","Total_Customer_Supplier",I$22,$C$19,ori,"TOTAL PRODUCT","B-438010",$C$20,"Amount_BS")/1000) -> 43584.553 | J46: =(_xll.DBR("CXMD:FTM_DATA_BALANCE_SHEET","Total_Customer_Supplier",J$22,$C$19,ori,"TOTAL PRODUCT","B-430010",$C$20,"Amount_BS")/1000)+(_xll.DBR("CXMD:FTM_DATA_BALANCE_SHEET","Total_Customer_Supplier",J$22,$C$19,ori,"TOTAL PRODUCT","B-430040",$C$20,"Amount_BS")/1000)+(_xll.DBR("CXMD:FTM_DATA_BALANCE_SHEET","Total_Customer_Supplier",J$22,$C$19,ori,"TOTAL PRODUCT","B-431040",$C$20,"Amount_BS")/1000)+(_xll.DBR("CXMD:FTM_DATA_BALANCE_SHEET","Total_Customer_Supplier",J$22,$C$19,ori,"TOTAL PRODUCT","B-437010",$C$20,"Amount_BS")/1000)+(_xll.DBR("CXMD:FTM_DATA_BALANCE_SHEET","Total_Customer_Supplier",J$22,$C$19,ori,"TOTAL PRODUCT","B-438010",$C$20,"Amount_BS")/1000) -> 37568.565 | K46: =(_xll.DBR("CXMD:FTM_DATA_BALANCE_SHEET","Total_Customer_Supplier",K$22,$C$19,ori,"TOTAL PRODUCT","B-430010",$C$20,"Amount_BS")/1000)+(_xll.DBR("CXMD:FTM_DATA_BALANCE_SHEET","Total_Customer_Supplier",K$22,$C$19,ori,"TOTAL PRODUCT","B-430040",$C$20,"Amount_BS")/1000)+(_xll.DBR("CXMD:FTM_DATA_BALANCE_SHEET","Total_Customer_Supplier",K$22,$C$19,ori,"TOTAL PRODUCT","B-431040",$C$20,"Amount_BS")/1000)+(_xll.DBR("CXMD:FTM_DATA_BALANCE_SHEET","Total_Customer_Supplier",K$22,$C$19,ori,"TOTAL PRODUCT","B-437010",$C$20,"Amount_BS")/1000)+(_xll.DBR("CXMD:FTM_DATA_BALANCE_SHEET","Total_Customer_Supplier",K$22,$C$19,ori,"TOTAL PRODUCT","B-438010",$C$20,"Amount_BS")/1000) -> 31559.169 | ... O46: =(_xll.DBR("CXMD:FTM_DATA_BALANCE_SHEET","Total_Customer_Supplier",O$22,$C$19,ori,"TOTAL PRODUCT","B-430010",$C$20,"Amount_BS")/1000)+(_xll.DBR("CXMD:FTM_DATA_BALANCE_SHEET","Total_Customer_Supplier",O$22,$C$19,ori,"TOTAL PRODUCT","B-430040",$C$20,"Amount_BS")/1000)+(_xll.DBR("CXMD:FTM_DATA_BALANCE_SHEET","Total_Customer_Supplier",O$22,$C$19,ori,"TOTAL PRODUCT","B-431040",$C$20,"Amount_BS")/1000)+(_xll.DBR("CXMD:FTM_DATA_BALANCE_SHEET","Total_Customer_Supplier",O$22,$C$19,ori,"TOTAL PRODUCT","B-437010",$C$20,"Amount_BS")/1000)+(_xll.DBR("CXMD:FTM_DATA_BALANCE_SHEET","Total_Customer_Supplier",O$22,$C$19,ori,"TOTAL PRODUCT","B-438010",$C$20,"Amount_BS")/1000) -> 33483.778 | P46: =SUM(D46:O46) -> 460087.47
C47: % of corporate output | D47: =IF(D27<>0,D46/D27,0) -> 0.11366694 | E47: =IF(E27<>0,E46/E27,0) -> 0.12097345 | F47: =IF(F27<>0,F46/F27,0) -> 0.1116055 | G47: =IF(G27<>0,G46/G27,0) -> 0.12053629 | H47: =IF(H27<>0,H46/H27,0) -> 0.10485442 | I47: =IF(I27<>0,I46/I27,0) -> 0.11737896 | J47: =IF(J27<>0,J46/J27,0) -> 0.10401119 | K47: =IF(K27<>0,K46/K27,0) -> 0.087023987 | ... O47: =IF(O27<>0,O46/O27,0) -> 0.13083434 | P47: =IF(P26<>0,P46/P26,0) -> 43.918887
B48: G - 439000 - PERSONNEL COSTS | C48: R-0-R-P-940000-PERSONEL EXPENSES | D48: =(_xll.DBR("CXMD:FTM_DATA_BALANCE_SHEET","Total_Customer_Supplier",D$22,$C$19,ori,"TOTAL PRODUCT","R-940000",$C$20,"Amount_BS")/1000) -> 37622.697 | E48: =(_xll.DBR("CXMD:FTM_DATA_BALANCE_SHEET","Total_Customer_Supplier",E$22,$C$19,ori,"TOTAL PRODUCT","R-940000",$C$20,"Amount_BS")/1000) -> 40357.724 | F48: =(_xll.DBR("CXMD:FTM_DATA_BALANCE_SHEET","Total_Customer_Supplier",F$22,$C$19,ori,"TOTAL PRODUCT","R-940000",$C$20,"Amount_BS")/1000) -> 41681.825 | G48: =(_xll.DBR("CXMD:FTM_DATA_BALANCE_SHEET","Total_Customer_Supplier",G$22,$C$19,ori,"TOTAL PRODUCT","R-940000",$C$20,"Amount_BS")/1000) -> 38470.116 | H48: =(_xll.DBR("CXMD:FTM_DATA_BALANCE_SHEET","Total_Customer_Supplier",H$22,$C$19,ori,"TOTAL PRODUCT","R-940000",$C$20,"Amount_BS")/1000) -> 40316.552 | I48: =(_xll.DBR("CXMD:FTM_DATA_BALANCE_SHEET","Total_Customer_Supplier",I$22,$C$19,ori,"TOTAL PRODUCT","R-940000",$C$20,"Amount_BS")/1000) -> 43787.77 | J48: =(_xll.DBR("CXMD:FTM_DATA_BALANCE_SHEET","Total_Customer_Supplier",J$22,$C$19,ori,"TOTAL PRODUCT","R-940000",$C$20,"Amount_BS")/1000) -> 37764.495 | K48: =(_xll.DBR("CXMD:FTM_DATA_BALANCE_SHEET","Total_Customer_Supplier",K$22,$C$19,ori,"TOTAL PRODUCT","R-940000",$C$20,"Amount_BS")/1000) -> 31722.953 | ... O48: =(_xll.DBR("CXMD:FTM_DATA_BALANCE_SHEET","Total_Customer_Supplier",O$22,$C$19,ori,"TOTAL PRODUCT","R-940000",$C$20,"Amount_BS")/1000) -> 33655.088 | P48: =SUM(D48:O48) -> 462090.92
B49: G - 439000 - PERSONNEL COSTS | C49: B-0-B-P-430040-Social security / pensio | D49: =(_xll.DBR("CXMD:FTM_DATA_BALANCE_SHEET","Total_Customer_Supplier",D$22,$C$19,ori,"TOTAL PRODUCT","B-430040",$C$20,"Amount_BS")/1000) -> 6922.5498 | E49: =(_xll.DBR("CXMD:FTM_DATA_BALANCE_SHEET","Total_Customer_Supplier",E$22,$C$19,ori,"TOTAL PRODUCT","B-430040",$C$20,"Amount_BS")/1000) -> 6697.3731 | F49: =(_xll.DBR("CXMD:FTM_DATA_BALANCE_SHEET","Total_Customer_Supplier",F$22,$C$19,ori,"TOTAL PRODUCT","B-430040",$C$20,"Amount_BS")/1000) -> 7214.9111 | G49: =(_xll.DBR("CXMD:FTM_DATA_BALANCE_SHEET","Total_Customer_Supplier",G$22,$C$19,ori,"TOTAL PRODUCT","B-430040",$C$20,"Amount_BS")/1000) -> 7069.1185 | H49: =(_xll.DBR("CXMD:FTM_DATA_BALANCE_SHEET","Total_Customer_Supplier",H$22,$C$19,ori,"TOTAL PRODUCT","B-430040",$C$20,"Amount_BS")/1000) -> 7161.0211 | I49: =(_xll.DBR("CXMD:FTM_DATA_BALANCE_SHEET","Total_Customer_Supplier",I$22,$C$19,ori,"TOTAL PRODUCT","B-430040",$C$20,"Amount_BS")/1000) -> 7782.3911 | J49: =(_xll.DBR("CXMD:FTM_DATA_BALANCE_SHEET","Total_Customer_Supplier",J$22,$C$19,ori,"TOTAL PRODUCT","B-430040",$C$20,"Amount_BS")/1000) -> 6256.4855 | K49: =(_xll.DBR("CXMD:FTM_DATA_BALANCE_SHEET","Total_Customer_Supplier",K$22,$C$19,ori,"TOTAL PRODUCT","B-430040",$C$20,"Amount_BS")/1000) -> 4938.0739 | ... O49: =(_xll.DBR("CXMD:FTM_DATA_BALANCE_SHEET","Total_Customer_Supplier",O$22,$C$19,ori,"TOTAL PRODUCT","B-430040",$C$20,"Amount_BS")/1000) -> 5773.6269 | P49: =SUM(D49:O49) -> 79658.608
B50: G - 439000 - PERSONNEL COSTS | C50: B-0-B-P-438010-Temporary staff - 3rd pa | D50: =(_xll.DBR("CXMD:FTM_DATA_BALANCE_SHEET","Total_Customer_Supplier",D$22,$C$19,ori,"TOTAL PRODUCT","B-438010",$C$20,"Amount_BS")/1000) -> 4741.4324 | E50: =(_xll.DBR("CXMD:FTM_DATA_BALANCE_SHEET","Total_Customer_Supplier",E$22,$C$19,ori,"TOTAL PRODUCT","B-438010",$C$20,"Amount_BS")/1000) -> 5094.1607 | F50: =(_xll.DBR("CXMD:FTM_DATA_BALANCE_SHEET","Total_Customer_Supplier",F$22,$C$19,ori,"TOTAL PRODUCT","B-438010",$C$20,"Amount_BS")/1000) -> 5965.8277 | G50: =(_xll.DBR("CXMD:FTM_DATA_BALANCE_SHEET","Total_Customer_Supplier",G$22,$C$19,ori,"TOTAL PRODUCT","B-438010",$C$20,"Amount_BS")/1000) -> 4807.535 | H50: =(_xll.DBR("CXMD:FTM_DATA_BALANCE_SHEET","Total_Customer_Supplier",H$22,$C$19,ori,"TOTAL PRODUCT","B-438010",$C$20,"Amount_BS")/1000) -> 5709.1304 | I50: =(_xll.DBR("CXMD:FTM_DATA_BALANCE_SHEET","Total_Customer_Supplier",I$22,$C$19,ori,"TOTAL PRODUCT","B-438010",$C$20,"Amount_BS")/1000) -> 5165.7926 | J50: =(_xll.DBR("CXMD:FTM_DATA_BALANCE_SHEET","Total_Customer_Supplier",J$22,$C$19,ori,"TOTAL PRODUCT","B-438010",$C$20,"Amount_BS")/1000) -> 5021.6867 | K50: =(_xll.DBR("CXMD:FTM_DATA_BALANCE_SHEET","Total_Customer_Supplier",K$22,$C$19,ori,"TOTAL PRODUCT","B-438010",$C$20,"Amount_BS")/1000) -> 2975.077 | ... O50: =(_xll.DBR("CXMD:FTM_DATA_BALANCE_SHEET","Total_Customer_Supplier",O$22,$C$19,ori,"TOTAL PRODUCT","B-438010",$C$20,"Amount_BS")/1000) -> 5122.6264 | P50: =SUM(D50:O50) -> 58980.992
B51: G - 439000 - PERSONNEL COSTS | C51: B-0-B-P-430010-Wages and salaries | D51: =(_xll.DBR("CXMD:FTM_DATA_BALANCE_SHEET","Total_Customer_Supplier",D$22,$C$19,ori,"TOTAL PRODUCT","B-430010",$C$20,"Amount_BS")/1000) -> 24166.696 | E51: =(_xll.DBR("CXMD:FTM_DATA_BALANCE_SHEET","Total_Customer_Supplier",E$22,$C$19,ori,"TOTAL PRODUCT","B-430010",$C$20,"Amount_BS")/1000) -> 26771.202 | F51: =(_xll.DBR("CXMD:FTM_DATA_BALANCE_SHEET","Total_Customer_Supplier",F$22,$C$19,ori,"TOTAL PRODUCT","B-430010",$C$20,"Amount_BS")/1000) -> 25952.813 | G51: =(_xll.DBR("CXMD:FTM_DATA_BALANCE_SHEET","Total_Customer_Supplier",G$22,$C$19,ori,"TOTAL PRODUCT","B-430010",$C$20,"Amount_BS")/1000) -> 24489.648 | H51: =(_xll.DBR("CXMD:FTM_DATA_BALANCE_SHEET","Total_Customer_Supplier",H$22,$C$19,ori,"TOTAL PRODUCT","B-430010",$C$20,"Amount_BS")/1000) -> 24993.283 | I51: =(_xll.DBR("CXMD:FTM_DATA_BALANCE_SHEET","Total_Customer_Supplier",I$22,$C$19,ori,"TOTAL PRODUCT","B-430010",$C$20,"Amount_BS")/1000) -> 28415.992 | J51: =(_xll.DBR("CXMD:FTM_DATA_BALANCE_SHEET","Total_Customer_Supplier",J$22,$C$19,ori,"TOTAL PRODUCT","B-430010",$C$20,"Amount_BS")/1000) -> 24403.596 | K51: =(_xll.DBR("CXMD:FTM_DATA_BALANCE_SHEET","Total_Customer_Supplier",K$22,$C$19,ori,"TOTAL PRODUCT","B-430010",$C$20,"Amount_BS")/1000) -> 21624.645 | ... O51: =(_xll.DBR("CXMD:FTM_DATA_BALANCE_SHEET","Total_Customer_Supplier",O$22,$C$19,ori,"TOTAL PRODUCT","B-430010",$C$20,"Amount_BS")/1000) -> 22571.938 | P51: =SUM(D51:O51) -> 298923.98
B52: G - 439000 - PERSONNEL COSTS | C52: B-0-B-P-431040-Pension expenses - defin | D52: =(_xll.DBR("CXMD:FTM_DATA_BALANCE_SHEET","Total_Customer_Supplier",D$22,$C$19,ori,"TOTAL PRODUCT","B-431040",$C$20,"Amount_BS")/1000) -> 100.78999 | E52: =(_xll.DBR("CXMD:FTM_DATA_BALANCE_SHEET","Total_Customer_Supplier",E$22,$C$19,ori,"TOTAL PRODUCT","B-431040",$C$20,"Amount_BS")/1000) -> 100.71355 | F52: =(_xll.DBR("CXMD:FTM_DATA_BALANCE_SHEET","Total_Customer_Supplier",F$22,$C$19,ori,"TOTAL PRODUCT","B-431040",$C$20,"Amount_BS")/1000) -> 100 | G52: =(_xll.DBR("CXMD:FTM_DATA_BALANCE_SHEET","Total_Customer_Supplier",G$22,$C$19,ori,"TOTAL PRODUCT","B-431040",$C$20,"Amount_BS")/1000) -> 100.61355 | H52: =(_xll.DBR("CXMD:FTM_DATA_BALANCE_SHEET","Total_Customer_Supplier",H$22,$C$19,ori,"TOTAL PRODUCT","B-431040",$C$20,"Amount_BS")/1000) -> 101.2271 | I52: =(_xll.DBR("CXMD:FTM_DATA_BALANCE_SHEET","Total_Customer_Supplier",I$22,$C$19,ori,"TOTAL PRODUCT","B-431040",$C$20,"Amount_BS")/1000) -> 101.51355 | J52: =(_xll.DBR("CXMD:FTM_DATA_BALANCE_SHEET","Total_Customer_Supplier",J$22,$C$19,ori,"TOTAL PRODUCT","B-431040",$C$20,"Amount_BS")/1000) -> 119.89485 | K52: =(_xll.DBR("CXMD:FTM_DATA_BALANCE_SHEET","Total_Customer_Supplier",K$22,$C$19,ori,"TOTAL PRODUCT","B-431040",$C$20,"Amount_BS")/1000) -> 103.26775 | ... O52: =(_xll.DBR("CXMD:FTM_DATA_BALANCE_SHEET","Total_Customer_Supplier",O$22,$C$19,ori,"TOTAL PRODUCT","B-431040",$C$20,"Amount_BS")/1000) -> -1894.8714 | P52: =SUM(D52:O52) -> -634.81532
B53: G - 439000 - PERSONNEL COSTS | C53: B-0-B-P-437010-Other personnel costs | D53: =(_xll.DBR("CXMD:FTM_DATA_BALANCE_SHEET","Total_Customer_Supplier",D$22,$C$19,ori,"TOTAL PRODUCT","B-437010",$C$20,"Amount_BS")/1000) -> 1469.0158 | E53: =(_xll.DBR("CXMD:FTM_DATA_BALANCE_SHEET","Total_Customer_Supplier",E$22,$C$19,ori,"TOTAL PRODUCT","B-437010",$C$20,"Amount_BS")/1000) -> 1578.4839 | F53: =(_xll.DBR("CXMD:FTM_DATA_BALANCE_SHEET","Total_Customer_Supplier",F$22,$C$19,ori,"TOTAL PRODUCT","B-437010",$C$20,"Amount_BS")/1000) -> 2248.3166 | G53: =(_xll.DBR("CXMD:FTM_DATA_BALANCE_SHEET","Total_Customer_Supplier",G$22,$C$19,ori,"TOTAL PRODUCT","B-437010",$C$20,"Amount_BS")/1000) -> 1828.9515 | H53: =(_xll.DBR("CXMD:FTM_DATA_BALANCE_SHEET","Total_Customer_Supplier",H$22,$C$19,ori,"TOTAL PRODUCT","B-437010",$C$20,"Amount_BS")/1000) -> 2185.5425 | I53: =(_xll.DBR("CXMD:FTM_DATA_BALANCE_SHEET","Total_Customer_Supplier",I$22,$C$19,ori,"TOTAL PRODUCT","B-437010",$C$20,"Amount_BS")/1000) -> 2118.8629 | J53: =(_xll.DBR("CXMD:FTM_DATA_BALANCE_SHEET","Total_Customer_Supplier",J$22,$C$19,ori,"TOTAL PRODUCT","B-437010",$C$20,"Amount_BS")/1000) -> 1766.9019 | K53: =(_xll.DBR("CXMD:FTM_DATA_BALANCE_SHEET","Total_Customer_Supplier",K$22,$C$19,ori,"TOTAL PRODUCT","B-437010",$C$20,"Amount_BS")/1000) -> 1918.1052 | ... O53: =(_xll.DBR("CXMD:FTM_DATA_BALANCE_SHEET","Total_Customer_Supplier",O$22,$C$19,ori,"TOTAL PRODUCT","B-437010",$C$20,"Amount_BS")/1000) -> 1910.4585 | P53: =SUM(D53:O53) -> 23158.708
B54: G - 459000 - OTHER EXPENSES | C54: Profit and Loss | D54: =(_xll.DBR("CXMD:FTM_DATA_BALANCE_SHEET","Total_Customer_Supplier",D$22,$C$19,ori,"TOTAL PRODUCT","B-451010",$C$20,"Amount_BS")/1000)+(_xll.DBR("CXMD:FTM_DATA_BALANCE_SHEET","Total_Customer_Supplier",D$22,$C$19,ori,"TOTAL PRODUCT","B-451020",$C$20,"Amount_BS")/1000)+(_xll.DBR("CXMD:FTM_DATA_BALANCE_SHEET","Total_Customer_Supplier",D$22,$C$19,ori,"TOTAL PRODUCT","B-451030",$C$20,"Amount_BS")/1000)+(_xll.DBR("CXMD:FTM_DATA_BALANCE_SHEET","Total_Customer_Supplier",D$22,$C$19,ori,"TOTAL PRODUCT","B-451110",$C$20,"Amount_BS")/1000)+(_xll.DBR("CXMD:FTM_DATA_BALANCE_SHEET","Total_Customer_Supplier",D$22,$C$19,ori,"TOTAL PRODUCT","B-451210",$C$20,"Amount_BS")/1000)+(_xll.DBR("CXMD:FTM_DATA_BALANCE_SHEET","Total_Customer_Supplier",D$22,$C$19,ori,"TOTAL PRODUCT","B-451220",$C$20,"Amount_BS")/1000)+(_xll.DBR("CXMD:FTM_DATA_BALANCE_SHEET","Total_Customer_Supplier",D$22,$C$19,ori,"TOTAL PRODUCT","B-451310",$C$20,"Amount_BS")/1000)+(_xll.DBR("CXMD:FTM_DATA_BALANCE_SHEET","Total_Customer_Supplier",D$22,$C$19,ori,"TOTAL PRODUCT","B-451450",$C$20,"Amount_BS")/1000)+(_xll.DBR("CXMD:FTM_DATA_BALANCE_SHEET","Total_Customer_Supplier",D$22,$C$19,ori,"TOTAL PRODUCT","B-451510",$C$20,"Amount_BS")/1000)+(_xll.DBR("CXMD:FTM_DATA_BALANCE_SHEET","Total_Customer_Supplier",D$22,$C$19,ori,"TOTAL PRODUCT","B-451610",$C$20,"Amount_BS")/1000)+(_xll.DBR("CXMD:FTM_DATA_BALANCE_SHEET","Total_Customer_Supplier",D$22,$C$19,ori,"TOTAL PRODUCT","B-451620",$C$20,"Amount_BS")/1000) -> 29278.132 | E54: =(_xll.DBR("CXMD:FTM_DATA_BALANCE_SHEET","Total_Customer_Supplier",E$22,$C$19,ori,"TOTAL PRODUCT","B-451010",$C$20,"Amount_BS")/1000)+(_xll.DBR("CXMD:FTM_DATA_BALANCE_SHEET","Total_Customer_Supplier",E$22,$C$19,ori,"TOTAL PRODUCT","B-451020",$C$20,"Amount_BS")/1000)+(_xll.DBR("CXMD:FTM_DATA_BALANCE_SHEET","Total_Customer_Supplier",E$22,$C$19,ori,"TOTAL PRODUCT","B-451030",$C$20,"Amount_BS")/1000)+(_xll.DBR("CXMD:FTM_DATA_BALANCE_SHEET","Total_Customer_Supplier",E$22,$C$19,ori,"TOTAL PRODUCT","B-451110",$C$20,"Amount_BS")/1000)+(_xll.DBR("CXMD:FTM_DATA_BALANCE_SHEET","Total_Customer_Supplier",E$22,$C$19,ori,"TOTAL PRODUCT","B-451210",$C$20,"Amount_BS")/1000)+(_xll.DBR("CXMD:FTM_DATA_BALANCE_SHEET","Total_Customer_Supplier",E$22,$C$19,ori,"TOTAL PRODUCT","B-451220",$C$20,"Amount_BS")/1000)+(_xll.DBR("CXMD:FTM_DATA_BALANCE_SHEET","Total_Customer_Supplier",E$22,$C$19,ori,"TOTAL PRODUCT","B-451310",$C$20,"Amount_BS")/1000)+(_xll.DBR("CXMD:FTM_DATA_BALANCE_SHEET","Total_Customer_Supplier",E$22,$C$19,ori,"TOTAL PRODUCT","B-451450",$C$20,"Amount_BS")/1000)+(_xll.DBR("CXMD:FTM_DATA_BALANCE_SHEET","Total_Customer_Supplier",E$22,$C$19,ori,"TOTAL PRODUCT","B-451510",$C$20,"Amount_BS")/1000)+(_xll.DBR("CXMD:FTM_DATA_BALANCE_SHEET","Total_Customer_Supplier",E$22,$C$19,ori,"TOTAL PRODUCT","B-451610",$C$20,"Amount_BS")/1000)+(_xll.DBR("CXMD:FTM_DATA_BALANCE_SHEET","Total_Customer_Supplier",E$22,$C$19,ori,"TOTAL PRODUCT","B-451620",$C$20,"Amount_BS")/1000) -> 26426.217 | F54: =(_xll.DBR("CXMD:FTM_DATA_BALANCE_SHEET","Total_Customer_Supplier",F$22,$C$19,ori,"TOTAL PRODUCT","B-451010",$C$20,"Amount_BS")/1000)+(_xll.DBR("CXMD:FTM_DATA_BALANCE_SHEET","Total_Customer_Supplier",F$22,$C$19,ori,"TOTAL PRODUCT","B-451020",$C$20,"Amount_BS")/1000)+(_xll.DBR("CXMD:FTM_DATA_BALANCE_SHEET","Total_Customer_Supplier",F$22,$C$19,ori,"TOTAL PRODUCT","B-451030",$C$20,"Amount_BS")/1000)+(_xll.DBR("CXMD:FTM_DATA_BALANCE_SHEET","Total_Customer_Supplier",F$22,$C$19,ori,"TOTAL PRODUCT","B-451110",$C$20,"Amount_BS")/1000)+(_xll.DBR("CXMD:FTM_DATA_BALANCE_SHEET","Total_Customer_Supplier",F$22,$C$19,ori,"TOTAL PRODUCT","B-451210",$C$20,"Amount_BS")/1000)+(_xll.DBR("CXMD:FTM_DATA_BALANCE_SHEET","Total_Customer_Supplier",F$22,$C$19,ori,"TOTAL PRODUCT","B-451220",$C$20,"Amount_BS")/1000)+(_xll.DBR("CXMD:FTM_DATA_BALANCE_SHEET","Total_Customer_Supplier",F$22,$C$19,ori,"TOTAL PRODUCT","B-451310",$C$20,"Amount_BS")/1000)+(_xll.DBR("CXMD:FTM_DATA_BALANCE_SHEET","Total_Customer_Supplier",F$22,$C$19,ori,"TOTAL PRODUCT","B-451450",$C$20,"Amount_BS")/1000)+(_xll.DBR("CXMD:FTM_DATA_BALANCE_SHEET","Total_Customer_Supplier",F$22,$C$19,ori,"TOTAL PRODUCT","B-451510",$C$20,"Amount_BS")/1000)+(_xll.DBR("CXMD:FTM_DATA_BALANCE_SHEET","Total_Customer_Supplier",F$22,$C$19,ori,"TOTAL PRODUCT","B-451610",$C$20,"Amount_BS")/1000)+(_xll.DBR("CXMD:FTM_DATA_BALANCE_SHEET","Total_Customer_Supplier",F$22,$C$19,ori,"TOTAL PRODUCT","B-451620",$C$20,"Amount_BS")/1000) -> 33087.795 | G54: =(_xll.DBR("CXMD:FTM_DATA_BALANCE_SHEET","Total_Customer_Supplier",G$22,$C$19,ori,"TOTAL PRODUCT","B-451010",$C$20,"Amount_BS")/1000)+(_xll.DBR("CXMD:FTM_DATA_BALANCE_SHEET","Total_Customer_Supplier",G$22,$C$19,ori,"TOTAL PRODUCT","B-451020",$C$20,"Amount_BS")/1000)+(_xll.DBR("CXMD:FTM_DATA_BALANCE_SHEET","Total_Customer_Supplier",G$22,$C$19,ori,"TOTAL PRODUCT","B-451030",$C$20,"Amount_BS")/1000)+(_xll.DBR("CXMD:FTM_DATA_BALANCE_SHEET","Total_Customer_Supplier",G$22,$C$19,ori,"TOTAL PRODUCT","B-451110",$C$20,"Amount_BS")/1000)+(_xll.DBR("CXMD:FTM_DATA_BALANCE_SHEET","Total_Customer_Supplier",G$22,$C$19,ori,"TOTAL PRODUCT","B-451210",$C$20,"Amount_BS")/1000)+(_xll.DBR("CXMD:FTM_DATA_BALANCE_SHEET","Total_Customer_Supplier",G$22,$C$19,ori,"TOTAL PRODUCT","B-451220",$C$20,"Amount_BS")/1000)+(_xll.DBR("CXMD:FTM_DATA_BALANCE_SHEET","Total_Customer_Supplier",G$22,$C$19,ori,"TOTAL PRODUCT","B-451310",$C$20,"Amount_BS")/1000)+(_xll.DBR("CXMD:FTM_DATA_BALANCE_SHEET","Total_Customer_Supplier",G$22,$C$19,ori,"TOTAL PRODUCT","B-451450",$C$20,"Amount_BS")/1000)+(_xll.DBR("CXMD:FTM_DATA_BALANCE_SHEET","Total_Customer_Supplier",G$22,$C$19,ori,"TOTAL PRODUCT","B-451510",$C$20,"Amount_BS")/1000)+(_xll.DBR("CXMD:FTM_DATA_BALANCE_SHEET","Total_Customer_Supplier",G$22,$C$19,ori,"TOTAL PRODUCT","B-451610",$C$20,"Amount_BS")/1000)+(_xll.DBR("CXMD:FTM_DATA_BALANCE_SHEET","Total_Customer_Supplier",G$22,$C$19,ori,"TOTAL PRODUCT","B-451620",$C$20,"Amount_BS")/1000) -> 31767.686 | H54: =(_xll.DBR("CXMD:FTM_DATA_BALANCE_SHEET","Total_Customer_Supplier",H$22,$C$19,ori,"TOTAL PRODUCT","B-451010",$C$20,"Amount_BS")/1000)+(_xll.DBR("CXMD:FTM_DATA_BALANCE_SHEET","Total_Customer_Supplier",H$22,$C$19,ori,"TOTAL PRODUCT","B-451020",$C$20,"Amount_BS")/1000)+(_xll.DBR("CXMD:FTM_DATA_BALANCE_SHEET","Total_Customer_Supplier",H$22,$C$19,ori,"TOTAL PRODUCT","B-451030",$C$20,"Amount_BS")/1000)+(_xll.DBR("CXMD:FTM_DATA_BALANCE_SHEET","Total_Customer_Supplier",H$22,$C$19,ori,"TOTAL PRODUCT","B-451110",$C$20,"Amount_BS")/1000)+(_xll.DBR("CXMD:FTM_DATA_BALANCE_SHEET","Total_Customer_Supplier",H$22,$C$19,ori,"TOTAL PRODUCT","B-451210",$C$20,"Amount_BS")/1000)+(_xll.DBR("CXMD:FTM_DATA_BALANCE_SHEET","Total_Customer_Supplier",H$22,$C$19,ori,"TOTAL PRODUCT","B-451220",$C$20,"Amount_BS")/1000)+(_xll.DBR("CXMD:FTM_DATA_BALANCE_SHEET","Total_Customer_Supplier",H$22,$C$19,ori,"TOTAL PRODUCT","B-451310",$C$20,"Amount_BS")/1000)+(_xll.DBR("CXMD:FTM_DATA_BALANCE_SHEET","Total_Customer_Supplier",H$22,$C$19,ori,"TOTAL PRODUCT","B-451450",$C$20,"Amount_BS")/1000)+(_xll.DBR("CXMD:FTM_DATA_BALANCE_SHEET","Total_Customer_Supplier",H$22,$C$19,ori,"TOTAL PRODUCT","B-451510",$C$20,"Amount_BS")/1000)+(_xll.DBR("CXMD:FTM_DATA_BALANCE_SHEET","Total_Customer_Supplier",H$22,$C$19,ori,"TOTAL PRODUCT","B-451610",$C$20,"Amount_BS")/1000)+(_xll.DBR("CXMD:FTM_DATA_BALANCE_SHEET","Total_Customer_Supplier",H$22,$C$19,ori,"TOTAL PRODUCT","B-451620",$C$20,"Amount_BS")/1000) -> 32533.924 | I54: =(_xll.DBR("CXMD:FTM_DATA_BALANCE_SHEET","Total_Customer_Supplier",I$22,$C$19,ori,"TOTAL PRODUCT","B-451010",$C$20,"Amount_BS")/1000)+(_xll.DBR("CXMD:FTM_DATA_BALANCE_SHEET","Total_Customer_Supplier",I$22,$C$19,ori,"TOTAL PRODUCT","B-451020",$C$20,"Amount_BS")/1000)+(_xll.DBR("CXMD:FTM_DATA_BALANCE_SHEET","Total_Customer_Supplier",I$22,$C$19,ori,"TOTAL PRODUCT","B-451030",$C$20,"Amount_BS")/1000)+(_xll.DBR("CXMD:FTM_DATA_BALANCE_SHEET","Total_Customer_Supplier",I$22,$C$19,ori,"TOTAL PRODUCT","B-451110",$C$20,"Amount_BS")/1000)+(_xll.DBR("CXMD:FTM_DATA_BALANCE_SHEET","Total_Customer_Supplier",I$22,$C$19,ori,"TOTAL PRODUCT","B-451210",$C$20,"Amount_BS")/1000)+(_xll.DBR("CXMD:FTM_DATA_BALANCE_SHEET","Total_Customer_Supplier",I$22,$C$19,ori,"TOTAL PRODUCT","B-451220",$C$20,"Amount_BS")/1000)+(_xll.DBR("CXMD:FTM_DATA_BALANCE_SHEET","Total_Customer_Supplier",I$22,$C$19,ori,"TOTAL PRODUCT","B-451310",$C$20,"Amount_BS")/1000)+(_xll.DBR("CXMD:FTM_DATA_BALANCE_SHEET","Total_Customer_Supplier",I$22,$C$19,ori,"TOTAL PRODUCT","B-451450",$C$20,"Amount_BS")/1000)+(_xll.DBR("CXMD:FTM_DATA_BALANCE_SHEET","Total_Customer_Supplier",I$22,$C$19,ori,"TOTAL PRODUCT","B-451510",$C$20,"Amount_BS")/1000)+(_xll.DBR("CXMD:FTM_DATA_BALANCE_SHEET","Total_Customer_Supplier",I$22,$C$19,ori,"TOTAL PRODUCT","B-451610",$C$20,"Amount_BS")/1000)+(_xll.DBR("CXMD:FTM_DATA_BALANCE_SHEET","Total_Customer_Supplier",I$22,$C$19,ori,"TOTAL PRODUCT","B-451620",$C$20,"Amount_BS")/1000) -> 30905.344 | J54: =(_xll.DBR("CXMD:FTM_DATA_BALANCE_SHEET","Total_Customer_Supplier",J$22,$C$19,ori,"TOTAL PRODUCT","B-451010",$C$20,"Amount_BS")/1000)+(_xll.DBR("CXMD:FTM_DATA_BALANCE_SHEET","Total_Customer_Supplier",J$22,$C$19,ori,"TOTAL PRODUCT","B-451020",$C$20,"Amount_BS")/1000)+(_xll.DBR("CXMD:FTM_DATA_BALANCE_SHEET","Total_Customer_Supplier",J$22,$C$19,ori,"TOTAL PRODUCT","B-451030",$C$20,"Amount_BS")/1000)+(_xll.DBR("CXMD:FTM_DATA_BALANCE_SHEET","Total_Customer_Supplier",J$22,$C$19,ori,"TOTAL PRODUCT","B-451110",$C$20,"Amount_BS")/1000)+(_xll.DBR("CXMD:FTM_DATA_BALANCE_SHEET","Total_Customer_Supplier",J$22,$C$19,ori,"TOTAL PRODUCT","B-451210",$C$20,"Amount_BS")/1000)+(_xll.DBR("CXMD:FTM_DATA_BALANCE_SHEET","Total_Customer_Supplier",J$22,$C$19,ori,"TOTAL PRODUCT","B-451220",$C$20,"Amount_BS")/1000)+(_xll.DBR("CXMD:FTM_DATA_BALANCE_SHEET","Total_Customer_Supplier",J$22,$C$19,ori,"TOTAL PRODUCT","B-451310",$C$20,"Amount_BS")/1000)+(_xll.DBR("CXMD:FTM_DATA_BALANCE_SHEET","Total_Customer_Supplier",J$22,$C$19,ori,"TOTAL PRODUCT","B-451450",$C$20,"Amount_BS")/1000)+(_xll.DBR("CXMD:FTM_DATA_BALANCE_SHEET","Total_Customer_Supplier",J$22,$C$19,ori,"TOTAL PRODUCT","B-451510",$C$20,"Amount_BS")/1000)+(_xll.DBR("CXMD:FTM_DATA_BALANCE_SHEET","Total_Customer_Supplier",J$22,$C$19,ori,"TOTAL PRODUCT","B-451610",$C$20,"Amount_BS")/1000)+(_xll.DBR("CXMD:FTM_DATA_BALANCE_SHEET","Total_Customer_Supplier",J$22,$C$19,ori,"TOTAL PRODUCT","B-451620",$C$20,"Amount_BS")/1000) -> 28625.412 | K54: =(_xll.DBR("CXMD:FTM_DATA_BALANCE_SHEET","Total_Customer_Supplier",K$22,$C$19,ori,"TOTAL PRODUCT","B-451010",$C$20,"Amount_BS")/1000)+(_xll.DBR("CXMD:FTM_DATA_BALANCE_SHEET","Total_Customer_Supplier",K$22,$C$19,ori,"TOTAL PRODUCT","B-451020",$C$20,"Amount_BS")/1000)+(_xll.DBR("CXMD:FTM_DATA_BALANCE_SHEET","Total_Customer_Supplier",K$22,$C$19,ori,"TOTAL PRODUCT","B-451030",$C$20,"Amount_BS")/1000)+(_xll.DBR("CXMD:FTM_DATA_BALANCE_SHEET","Total_Customer_Supplier",K$22,$C$19,ori,"TOTAL PRODUCT","B-451110",$C$20,"Amount_BS")/1000)+(_xll.DBR("CXMD:FTM_DATA_BALANCE_SHEET","Total_Customer_Supplier",K$22,$C$19,ori,"TOTAL PRODUCT","B-451210",$C$20,"Amount_BS")/1000)+(_xll.DBR("CXMD:FTM_DATA_BALANCE_SHEET","Total_Customer_Supplier",K$22,$C$19,ori,"TOTAL PRODUCT","B-451220",$C$20,"Amount_BS")/1000)+(_xll.DBR("CXMD:FTM_DATA_BALANCE_SHEET","Total_Customer_Supplier",K$22,$C$19,ori,"TOTAL PRODUCT","B-451310",$C$20,"Amount_BS")/1000)+(_xll.DBR("CXMD:FTM_DATA_BALANCE_SHEET","Total_Customer_Supplier",K$22,$C$19,ori,"TOTAL PRODUCT","B-451450",$C$20,"Amount_BS")/1000)+(_xll.DBR("CXMD:FTM_DATA_BALANCE_SHEET","Total_Customer_Supplier",K$22,$C$19,ori,"TOTAL PRODUCT","B-451510",$C$20,"Amount_BS")/1000)+(_xll.DBR("CXMD:FTM_DATA_BALANCE_SHEET","Total_Customer_Supplier",K$22,$C$19,ori,"TOTAL PRODUCT","B-451610",$C$20,"Amount_BS")/1000)+(_xll.DBR("CXMD:FTM_DATA_BALANCE_SHEET","Total_Customer_Supplier",K$22,$C$19,ori,"TOTAL PRODUCT","B-451620",$C$20,"Amount_BS")/1000) -> 26762.875 | ... O54: =(_xll.DBR("CXMD:FTM_DATA_BALANCE_SHEET","Total_Customer_Supplier",O$22,$C$19,ori,"TOTAL PRODUCT","B-451010",$C$20,"Amount_BS")/1000)+(_xll.DBR("CXMD:FTM_DATA_BALANCE_SHEET","Total_Customer_Supplier",O$22,$C$19,ori,"TOTAL PRODUCT","B-451020",$C$20,"Amount_BS")/1000)+(_xll.DBR("CXMD:FTM_DATA_BALANCE_SHEET","Total_Customer_Supplier",O$22,$C$19,ori,"TOTAL PRODUCT","B-451030",$C$20,"Amount_BS")/1000)+(_xll.DBR("CXMD:FTM_DATA_BALANCE_SHEET","Total_Customer_Supplier",O$22,$C$19,ori,"TOTAL PRODUCT","B-451110",$C$20,"Amount_BS")/1000)+(_xll.DBR("CXMD:FTM_DATA_BALANCE_SHEET","Total_Customer_Supplier",O$22,$C$19,ori,"TOTAL PRODUCT","B-451210",$C$20,"Amount_BS")/1000)+(_xll.DBR("CXMD:FTM_DATA_BALANCE_SHEET","Total_Customer_Supplier",O$22,$C$19,ori,"TOTAL PRODUCT","B-451220",$C$20,"Amount_BS")/1000)+(_xll.DBR("CXMD:FTM_DATA_BALANCE_SHEET","Total_Customer_Supplier",O$22,$C$19,ori,"TOTAL PRODUCT","B-451310",$C$20,"Amount_BS")/1000)+(_xll.DBR("CXMD:FTM_DATA_BALANCE_SHEET","Total_Customer_Supplier",O$22,$C$19,ori,"TOTAL PRODUCT","B-451450",$C$20,"Amount_BS")/1000)+(_xll.DBR("CXMD:FTM_DATA_BALANCE_SHEET","Total_Customer_Supplier",O$22,$C$19,ori,"TOTAL PRODUCT","B-451510",$C$20,"Amount_BS")/1000)+(_xll.DBR("CXMD:FTM_DATA_BALANCE_SHEET","Total_Customer_Supplier",O$22,$C$19,ori,"TOTAL PRODUCT","B-451610",$C$20,"Amount_BS")/1000)+(_xll.DBR("CXMD:FTM_DATA_BALANCE_SHEET","Total_Customer_Supplier",O$22,$C$19,ori,"TOTAL PRODUCT","B-451620",$C$20,"Amount_BS")/1000) -> 31415.092 | P54: =SUM(D54:O54) -> 371754.65
C55: % of corporate output | D55: =IF(D27<>0,D54/D27,0) -> 0.088981621 | E55: =IF(E27<>0,E54/E27,0) -> 0.07944128 | F55: =IF(F27<>0,F54/F27,0) -> 0.089021541 | G55: =IF(G27<>0,G54/G27,0) -> 0.099988831 | H55: =IF(H27<>0,H54/H27,0) -> 0.084964092 | I55: =IF(I27<>0,I54/I27,0) -> 0.083232174 | J55: =IF(J27<>0,J54/J27,0) -> 0.079251445 | K55: =IF(K27<>0,K54/K27,0) -> 0.073798271 | ... O55: =IF(O27<>0,O54/O27,0) -> 0.12275116 | P55: =IF(P26<>0,P54/P26,0) -> 35.48684
B56: G - 459000 - OTHER EXPENSES | C56: R-0-R-P-959000-OTHER EXPENSES | D56: =D57+D58+D59+D60+D61+D62+D63+D64+D65+D66+D67+D68 -> 29278.132 | E56: =E57+E58+E59+E60+E61+E62+E63+E64+E65+E66+E67+E68 -> 26426.217 | F56: =F57+F58+F59+F60+F61+F62+F63+F64+F65+F66+F67+F68 -> 33087.795 | G56: =G57+G58+G59+G60+G61+G62+G63+G64+G65+G66+G67+G68 -> 31767.686 | H56: =H57+H58+H59+H60+H61+H62+H63+H64+H65+H66+H67+H68 -> 32533.924 | I56: =I57+I58+I59+I60+I61+I62+I63+I64+I65+I66+I67+I68 -> 30905.344 | J56: =J57+J58+J59+J60+J61+J62+J63+J64+J65+J66+J67+J68 -> 28625.412 | K56: =K57+K58+K59+K60+K61+K62+K63+K64+K65+K66+K67+K68 -> 26762.875 | ... O56: =O57+O58+O59+O60+O61+O62+O63+O64+O65+O66+O67+O68 -> 31415.092 | P56: =SUM(D56:O56) -> 371754.65
B57: G - 459000 - OTHER EXPENSES | C57: B-0-B-P-451020-Repair / maintenance / r | D57: =(_xll.DBR("CXMD:FTM_DATA_BALANCE_SHEET","Total_Customer_Supplier",D$22,$C$19,ori,"TOTAL PRODUCT","B-451020",$C$20,"Amount_BS")/1000) -> 4342.9436 | E57: =(_xll.DBR("CXMD:FTM_DATA_BALANCE_SHEET","Total_Customer_Supplier",E$22,$C$19,ori,"TOTAL PRODUCT","B-451020",$C$20,"Amount_BS")/1000) -> 4768.9063 | F57: =(_xll.DBR("CXMD:FTM_DATA_BALANCE_SHEET","Total_Customer_Supplier",F$22,$C$19,ori,"TOTAL PRODUCT","B-451020",$C$20,"Amount_BS")/1000) -> 5452.3295 | G57: =(_xll.DBR("CXMD:FTM_DATA_BALANCE_SHEET","Total_Customer_Supplier",G$22,$C$19,ori,"TOTAL PRODUCT","B-451020",$C$20,"Amount_BS")/1000) -> 4720.5511 | H57: =(_xll.DBR("CXMD:FTM_DATA_BALANCE_SHEET","Total_Customer_Supplier",H$22,$C$19,ori,"TOTAL PRODUCT","B-451020",$C$20,"Amount_BS")/1000) -> 5305.0087 | I57: =(_xll.DBR("CXMD:FTM_DATA_BALANCE_SHEET","Total_Customer_Supplier",I$22,$C$19,ori,"TOTAL PRODUCT","B-451020",$C$20,"Amount_BS")/1000) -> 5876.6122 | J57: =(_xll.DBR("CXMD:FTM_DATA_BALANCE_SHEET","Total_Customer_Supplier",J$22,$C$19,ori,"TOTAL PRODUCT","B-451020",$C$20,"Amount_BS")/1000) -> 6119.3737 | K57: =(_xll.DBR("CXMD:FTM_DATA_BALANCE_SHEET","Total_Customer_Supplier",K$22,$C$19,ori,"TOTAL PRODUCT","B-451020",$C$20,"Amount_BS")/1000) -> 5110.0411 | ... O57: =(_xll.DBR("CXMD:FTM_DATA_BALANCE_SHEET","Total_Customer_Supplier",O$22,$C$19,ori,"TOTAL PRODUCT","B-451020",$C$20,"Amount_BS")/1000) -> 6185.45 | P57: =SUM(D57:O57) -> 64920.159
B58: G - 459000 - OTHER EXPENSES | C58: B-0-B-P-451010-Energy | D58: =(_xll.DBR("CXMD:FTM_DATA_BALANCE_SHEET","Total_Customer_Supplier",D$22,$C$19,ori,"TOTAL PRODUCT","B-451010",$C$20,"Amount_BS")/1000) -> 2390.8586 | E58: =(_xll.DBR("CXMD:FTM_DATA_BALANCE_SHEET","Total_Customer_Supplier",E$22,$C$19,ori,"TOTAL PRODUCT","B-451010",$C$20,"Amount_BS")/1000) -> 2927.1485 | F58: =(_xll.DBR("CXMD:FTM_DATA_BALANCE_SHEET","Total_Customer_Supplier",F$22,$C$19,ori,"TOTAL PRODUCT","B-451010",$C$20,"Amount_BS")/1000) -> 3251.0924 | G58: =(_xll.DBR("CXMD:FTM_DATA_BALANCE_SHEET","Total_Customer_Supplier",G$22,$C$19,ori,"TOTAL PRODUCT","B-451010",$C$20,"Amount_BS")/1000) -> 3478.5694 | H58: =(_xll.DBR("CXMD:FTM_DATA_BALANCE_SHEET","Total_Customer_Supplier",H$22,$C$19,ori,"TOTAL PRODUCT","B-451010",$C$20,"Amount_BS")/1000) -> 3100.6866 | I58: =(_xll.DBR("CXMD:FTM_DATA_BALANCE_SHEET","Total_Customer_Supplier",I$22,$C$19,ori,"TOTAL PRODUCT","B-451010",$C$20,"Amount_BS")/1000) -> 2756.4503 | J58: =(_xll.DBR("CXMD:FTM_DATA_BALANCE_SHEET","Total_Customer_Supplier",J$22,$C$19,ori,"TOTAL PRODUCT","B-451010",$C$20,"Amount_BS")/1000) -> 2279.4038 | K58: =(_xll.DBR("CXMD:FTM_DATA_BALANCE_SHEET","Total_Customer_Supplier",K$22,$C$19,ori,"TOTAL PRODUCT","B-451010",$C$20,"Amount_BS")/1000) -> 2395.5095 | ... O58: =(_xll.DBR("CXMD:FTM_DATA_BALANCE_SHEET","Total_Customer_Supplier",O$22,$C$19,ori,"TOTAL PRODUCT","B-451010",$C$20,"Amount_BS")/1000) -> 2551.7411 | P58: =SUM(D58:O58) -> 32375.591
B59: G - 459000 - OTHER EXPENSES | C59: B-0-B-P-451110-Leasing costs related to | D59: =(_xll.DBR("CXMD:FTM_DATA_BALANCE_SHEET","Total_Customer_Supplier",D$22,$C$19,ori,"TOTAL PRODUCT","B-451110",$C$20,"Amount_BS")/1000) -> 637.80258 | E59: =(_xll.DBR("CXMD:FTM_DATA_BALANCE_SHEET","Total_Customer_Supplier",E$22,$C$19,ori,"TOTAL PRODUCT","B-451110",$C$20,"Amount_BS")/1000) -> 551.20691 | F59: =(_xll.DBR("CXMD:FTM_DATA_BALANCE_SHEET","Total_Customer_Supplier",F$22,$C$19,ori,"TOTAL PRODUCT","B-451110",$C$20,"Amount_BS")/1000) -> 534.37409 | G59: =(_xll.DBR("CXMD:FTM_DATA_BALANCE_SHEET","Total_Customer_Supplier",G$22,$C$19,ori,"TOTAL PRODUCT","B-451110",$C$20,"Amount_BS")/1000) -> 697.80003 | H59: =(_xll.DBR("CXMD:FTM_DATA_BALANCE_SHEET","Total_Customer_Supplier",H$22,$C$19,ori,"TOTAL PRODUCT","B-451110",$C$20,"Amount_BS")/1000) -> 573.56464 | I59: =(_xll.DBR("CXMD:FTM_DATA_BALANCE_SHEET","Total_Customer_Supplier",I$22,$C$19,ori,"TOTAL PRODUCT","B-451110",$C$20,"Amount_BS")/1000) -> 576.37417 | J59: =(_xll.DBR("CXMD:FTM_DATA_BALANCE_SHEET","Total_Customer_Supplier",J$22,$C$19,ori,"TOTAL PRODUCT","B-451110",$C$20,"Amount_BS")/1000) -> 693.7817 | K59: =(_xll.DBR("CXMD:FTM_DATA_BALANCE_SHEET","Total_Customer_Supplier",K$22,$C$19,ori,"TOTAL PRODUCT","B-451110",$C$20,"Amount_BS")/1000) -> 532.69988 | ... O59: =(_xll.DBR("CXMD:FTM_DATA_BALANCE_SHEET","Total_Customer_Supplier",O$22,$C$19,ori,"TOTAL PRODUCT","B-451110",$C$20,"Amount_BS")/1000) -> 825.70427 | P59: =SUM(D59:O59) -> 7042.9424
B60: G - 459000 - OTHER EXPENSES | C60: B-0-B-P-451610-Other operating expense | D60: =(_xll.DBR("CXMD:FTM_DATA_BALANCE_SHEET","Total_Customer_Supplier",D$22,$C$19,ori,"TOTAL PRODUCT","B-451610",$C$20,"Amount_BS")/1000) -> 8582.6171 | E60: =(_xll.DBR("CXMD:FTM_DATA_BALANCE_SHEET","Total_Customer_Supplier",E$22,$C$19,ori,"TOTAL PRODUCT","B-451610",$C$20,"Amount_BS")/1000) -> 6472.0243 | F60: =(_xll.DBR("CXMD:FTM_DATA_BALANCE_SHEET","Total_Customer_Supplier",F$22,$C$19,ori,"TOTAL PRODUCT","B-451610",$C$20,"Amount_BS")/1000) -> 7643.4871 | G60: =(_xll.DBR("CXMD:FTM_DATA_BALANCE_SHEET","Total_Customer_Supplier",G$22,$C$19,ori,"TOTAL PRODUCT","B-451610",$C$20,"Amount_BS")/1000) -> 6064.1241 | H60: =(_xll.DBR("CXMD:FTM_DATA_BALANCE_SHEET","Total_Customer_Supplier",H$22,$C$19,ori,"TOTAL PRODUCT","B-451610",$C$20,"Amount_BS")/1000) -> 6388.2146 | I60: =(_xll.DBR("CXMD:FTM_DATA_BALANCE_SHEET","Total_Customer_Supplier",I$22,$C$19,ori,"TOTAL PRODUCT","B-451610",$C$20,"Amount_BS")/1000) -> 5452.1349 | J60: =(_xll.DBR("CXMD:FTM_DATA_BALANCE_SHEET","Total_Customer_Supplier",J$22,$C$19,ori,"TOTAL PRODUCT","B-451610",$C$20,"Amount_BS")/1000) -> 5950.7004 | K60: =(_xll.DBR("CXMD:FTM_DATA_BALANCE_SHEET","Total_Customer_Supplier",K$22,$C$19,ori,"TOTAL PRODUCT","B-451610",$C$20,"Amount_BS")/1000) -> 4719.1834 | ... O60: =(_xll.DBR("CXMD:FTM_DATA_BALANCE_SHEET","Total_Customer_Supplier",O$22,$C$19,ori,"TOTAL PRODUCT","B-451610",$C$20,"Amount_BS")/1000) -> 7960.0557 | P60: =SUM(D60:O60) -> 80207.077
B61: G - 459000 - OTHER EXPENSES | C61: B-0-B-P-451030-Insurance expenses | D61: =(_xll.DBR("CXMD:FTM_DATA_BALANCE_SHEET","Total_Customer_Supplier",D$22,$C$19,ori,"TOTAL PRODUCT","B-451030",$C$20,"Amount_BS")/1000) -> 1509.302 | E61: =(_xll.DBR("CXMD:FTM_DATA_BALANCE_SHEET","Total_Customer_Supplier",E$22,$C$19,ori,"TOTAL PRODUCT","B-451030",$C$20,"Amount_BS")/1000) -> 181.03978 | F61: =(_xll.DBR("CXMD:FTM_DATA_BALANCE_SHEET","Total_Customer_Supplier",F$22,$C$19,ori,"TOTAL PRODUCT","B-451030",$C$20,"Amount_BS")/1000) -> 287.33699 | G61: =(_xll.DBR("CXMD:FTM_DATA_BALANCE_SHEET","Total_Customer_Supplier",G$22,$C$19,ori,"TOTAL PRODUCT","B-451030",$C$20,"Amount_BS")/1000) -> 270.0388 | H61: =(_xll.DBR("CXMD:FTM_DATA_BALANCE_SHEET","Total_Customer_Supplier",H$22,$C$19,ori,"TOTAL PRODUCT","B-451030",$C$20,"Amount_BS")/1000) -> 116.53537 | I61: =(_xll.DBR("CXMD:FTM_DATA_BALANCE_SHEET","Total_Customer_Supplier",I$22,$C$19,ori,"TOTAL PRODUCT","B-451030",$C$20,"Amount_BS")/1000) -> 97.66332 | J61: =(_xll.DBR("CXMD:FTM_DATA_BALANCE_SHEET","Total_Customer_Supplier",J$22,$C$19,ori,"TOTAL PRODUCT","B-451030",$C$20,"Amount_BS")/1000) -> 304.3097 | K61: =(_xll.DBR("CXMD:FTM_DATA_BALANCE_SHEET","Total_Customer_Supplier",K$22,$C$19,ori,"TOTAL PRODUCT","B-451030",$C$20,"Amount_BS")/1000) -> 119.84835 | ... O61: =(_xll.DBR("CXMD:FTM_DATA_BALANCE_SHEET","Total_Customer_Supplier",O$22,$C$19,ori,"TOTAL PRODUCT","B-451030",$C$20,"Amount_BS")/1000) -> 152.18685 | P61: =SUM(D61:O61) -> 3430.2235
B62: G - 459000 - OTHER EXPENSES | C62: B-0-B-P-451450-SELLING EXPENSES | D62: =(_xll.DBR("CXMD:FTM_DATA_BALANCE_SHEET","Total_Customer_Supplier",D$22,$C$19,ori,"TOTAL PRODUCT","B-451450",$C$20,"Amount_BS")/1000) -> 6133.2678 | E62: =(_xll.DBR("CXMD:FTM_DATA_BALANCE_SHEET","Total_Customer_Supplier",E$22,$C$19,ori,"TOTAL PRODUCT","B-451450",$C$20,"Amount_BS")/1000) -> 7098.5787 | F62: =(_xll.DBR("CXMD:FTM_DATA_BALANCE_SHEET","Total_Customer_Supplier",F$22,$C$19,ori,"TOTAL PRODUCT","B-451450",$C$20,"Amount_BS")/1000) -> 9195.5069 | G62: =(_xll.DBR("CXMD:FTM_DATA_BALANCE_SHEET","Total_Customer_Supplier",G$22,$C$19,ori,"TOTAL PRODUCT","B-451450",$C$20,"Amount_BS")/1000) -> 9744.7817 | H62: =(_xll.DBR("CXMD:FTM_DATA_BALANCE_SHEET","Total_Customer_Supplier",H$22,$C$19,ori,"TOTAL PRODUCT","B-451450",$C$20,"Amount_BS")/1000) -> 9543.0558 | I62: =(_xll.DBR("CXMD:FTM_DATA_BALANCE_SHEET","Total_Customer_Supplier",I$22,$C$19,ori,"TOTAL PRODUCT","B-451450",$C$20,"Amount_BS")/1000) -> 8949.5396 | J62: =(_xll.DBR("CXMD:FTM_DATA_BALANCE_SHEET","Total_Customer_Supplier",J$22,$C$19,ori,"TOTAL PRODUCT","B-451450",$C$20,"Amount_BS")/1000) -> 7254.4149 | K62: =(_xll.DBR("CXMD:FTM_DATA_BALANCE_SHEET","Total_Customer_Supplier",K$22,$C$19,ori,"TOTAL PRODUCT","B-451450",$C$20,"Amount_BS")/1000) -> 7688.251 | ... O62: =(_xll.DBR("CXMD:FTM_DATA_BALANCE_SHEET","Total_Customer_Supplier",O$22,$C$19,ori,"TOTAL PRODUCT","B-451450",$C$20,"Amount_BS")/1000) -> 7924.1522 | P62: =SUM(D62:O62) -> 100913.82
B63: G - 459000 - OTHER EXPENSES | C63: B-0-B-P-451210-Auditor services | D63: =(_xll.DBR("CXMD:FTM_DATA_BALANCE_SHEET","Total_Customer_Supplier",D$22,$C$19,ori,"TOTAL PRODUCT","B-451210",$C$20,"Amount_BS")/1000) -> 76.26385 | E63: =(_xll.DBR("CXMD:FTM_DATA_BALANCE_SHEET","Total_Customer_Supplier",E$22,$C$19,ori,"TOTAL PRODUCT","B-451210",$C$20,"Amount_BS")/1000) -> 58.41154 | F63: =(_xll.DBR("CXMD:FTM_DATA_BALANCE_SHEET","Total_Customer_Supplier",F$22,$C$19,ori,"TOTAL PRODUCT","B-451210",$C$20,"Amount_BS")/1000) -> 37.76348 | G63: =(_xll.DBR("CXMD:FTM_DATA_BALANCE_SHEET","Total_Customer_Supplier",G$22,$C$19,ori,"TOTAL PRODUCT","B-451210",$C$20,"Amount_BS")/1000) -> 30.31634 | H63: =(_xll.DBR("CXMD:FTM_DATA_BALANCE_SHEET","Total_Customer_Supplier",H$22,$C$19,ori,"TOTAL PRODUCT","B-451210",$C$20,"Amount_BS")/1000) -> 42.08083 | I63: =(_xll.DBR("CXMD:FTM_DATA_BALANCE_SHEET","Total_Customer_Supplier",I$22,$C$19,ori,"TOTAL PRODUCT","B-451210",$C$20,"Amount_BS")/1000) -> 31 | J63: =(_xll.DBR("CXMD:FTM_DATA_BALANCE_SHEET","Total_Customer_Supplier",J$22,$C$19,ori,"TOTAL PRODUCT","B-451210",$C$20,"Amount_BS")/1000) -> 59.48425 | K63: =(_xll.DBR("CXMD:FTM_DATA_BALANCE_SHEET","Total_Customer_Supplier",K$22,$C$19,ori,"TOTAL PRODUCT","B-451210",$C$20,"Amount_BS")/1000) -> 33.99992 | ... O63: =(_xll.DBR("CXMD:FTM_DATA_BALANCE_SHEET","Total_Customer_Supplier",O$22,$C$19,ori,"TOTAL PRODUCT","B-451210",$C$20,"Amount_BS")/1000) -> 123.18817 | P63: =SUM(D63:O63) -> 613.83571
B64: G - 459000 - OTHER EXPENSES | C64: B-0-B-P-451220-Advisory services | D64: =(_xll.DBR("CXMD:FTM_DATA_BALANCE_SHEET","Total_Customer_Supplier",D$22,$C$19,ori,"TOTAL PRODUCT","B-451220",$C$20,"Amount_BS")/1000) -> 342.52475 | E64: =(_xll.DBR("CXMD:FTM_DATA_BALANCE_SHEET","Total_Customer_Supplier",E$22,$C$19,ori,"TOTAL PRODUCT","B-451220",$C$20,"Amount_BS")/1000) -> 553.91964 | F64: =(_xll.DBR("CXMD:FTM_DATA_BALANCE_SHEET","Total_Customer_Supplier",F$22,$C$19,ori,"TOTAL PRODUCT","B-451220",$C$20,"Amount_BS")/1000) -> 221.93225 | G64: =(_xll.DBR("CXMD:FTM_DATA_BALANCE_SHEET","Total_Customer_Supplier",G$22,$C$19,ori,"TOTAL PRODUCT","B-451220",$C$20,"Amount_BS")/1000) -> 351.51067 | H64: =(_xll.DBR("CXMD:FTM_DATA_BALANCE_SHEET","Total_Customer_Supplier",H$22,$C$19,ori,"TOTAL PRODUCT","B-451220",$C$20,"Amount_BS")/1000) -> 551.61096 | I64: =(_xll.DBR("CXMD:FTM_DATA_BALANCE_SHEET","Total_Customer_Supplier",I$22,$C$19,ori,"TOTAL PRODUCT","B-451220",$C$20,"Amount_BS")/1000) -> 340.68663 | J64: =(_xll.DBR("CXMD:FTM_DATA_BALANCE_SHEET","Total_Customer_Supplier",J$22,$C$19,ori,"TOTAL PRODUCT","B-451220",$C$20,"Amount_BS")/1000) -> 352.01311 | K64: =(_xll.DBR("CXMD:FTM_DATA_BALANCE_SHEET","Total_Customer_Supplier",K$22,$C$19,ori,"TOTAL PRODUCT","B-451220",$C$20,"Amount_BS")/1000) -> 301.27665 | ... O64: =(_xll.DBR("CXMD:FTM_DATA_BALANCE_SHEET","Total_Customer_Supplier",O$22,$C$19,ori,"TOTAL PRODUCT","B-451220",$C$20,"Amount_BS")/1000) -> 1604.8367 | P64: =SUM(D64:O64) -> 7441.8655
B65: G - 459000 - OTHER EXPENSES | C65: B-0-B-P-451620-OTHER OP. EXP. IC | D65: =(_xll.DBR("CXMD:FTM_DATA_BALANCE_SHEET","Total_Customer_Supplier",D$22,$C$19,ori,"TOTAL PRODUCT","B-451620",$C$20,"Amount_BS")/1000) -> 3447.9384 | E65: =(_xll.DBR("CXMD:FTM_DATA_BALANCE_SHEET","Total_Customer_Supplier",E$22,$C$19,ori,"TOTAL PRODUCT","B-451620",$C$20,"Amount_BS")/1000) -> 3418.5059 | F65: =(_xll.DBR("CXMD:FTM_DATA_BALANCE_SHEET","Total_Customer_Supplier",F$22,$C$19,ori,"TOTAL PRODUCT","B-451620",$C$20,"Amount_BS")/1000) -> 3656.4815 | G65: =(_xll.DBR("CXMD:FTM_DATA_BALANCE_SHEET","Total_Customer_Supplier",G$22,$C$19,ori,"TOTAL PRODUCT","B-451620",$C$20,"Amount_BS")/1000) -> 3646.3758 | H65: =(_xll.DBR("CXMD:FTM_DATA_BALANCE_SHEET","Total_Customer_Supplier",H$22,$C$19,ori,"TOTAL PRODUCT","B-451620",$C$20,"Amount_BS")/1000) -> 3668.2347 | I65: =(_xll.DBR("CXMD:FTM_DATA_BALANCE_SHEET","Total_Customer_Supplier",I$22,$C$19,ori,"TOTAL PRODUCT","B-451620",$C$20,"Amount_BS")/1000) -> 3692.4523 | J65: =(_xll.DBR("CXMD:FTM_DATA_BALANCE_SHEET","Total_Customer_Supplier",J$22,$C$19,ori,"TOTAL PRODUCT","B-451620",$C$20,"Amount_BS")/1000) -> 3675.0694 | K65: =(_xll.DBR("CXMD:FTM_DATA_BALANCE_SHEET","Total_Customer_Supplier",K$22,$C$19,ori,"TOTAL PRODUCT","B-451620",$C$20,"Amount_BS")/1000) -> 3637.3003 | ... O65: =(_xll.DBR("CXMD:FTM_DATA_BALANCE_SHEET","Total_Customer_Supplier",O$22,$C$19,ori,"TOTAL PRODUCT","B-451620",$C$20,"Amount_BS")/1000) -> 2554.7648 | P65: =SUM(D65:O65) -> 50299.246
B66: G - 459000 - OTHER EXPENSES | C66: B-0-B-P-451510-OTHER TAXES CAPITAL/OTH. | D66: =(_xll.DBR("CXMD:FTM_DATA_BALANCE_SHEET","Total_Customer_Supplier",D$22,$C$19,ori,"TOTAL PRODUCT","B-451510",$C$20,"Amount_BS")/1000) -> 2016.897 | E66: =(_xll.DBR("CXMD:FTM_DATA_BALANCE_SHEET","Total_Customer_Supplier",E$22,$C$19,ori,"TOTAL PRODUCT","B-451510",$C$20,"Amount_BS")/1000) -> 113.07189 | F66: =(_xll.DBR("CXMD:FTM_DATA_BALANCE_SHEET","Total_Customer_Supplier",F$22,$C$19,ori,"TOTAL PRODUCT","B-451510",$C$20,"Amount_BS")/1000) -> 2375.3511 | G66: =(_xll.DBR("CXMD:FTM_DATA_BALANCE_SHEET","Total_Customer_Supplier",G$22,$C$19,ori,"TOTAL PRODUCT","B-451510",$C$20,"Amount_BS")/1000) -> 2452.6603 | H66: =(_xll.DBR("CXMD:FTM_DATA_BALANCE_SHEET","Total_Customer_Supplier",H$22,$C$19,ori,"TOTAL PRODUCT","B-451510",$C$20,"Amount_BS")/1000) -> 2929.2107 | I66: =(_xll.DBR("CXMD:FTM_DATA_BALANCE_SHEET","Total_Customer_Supplier",I$22,$C$19,ori,"TOTAL PRODUCT","B-451510",$C$20,"Amount_BS")/1000) -> 2641.4262 | J66: =(_xll.DBR("CXMD:FTM_DATA_BALANCE_SHEET","Total_Customer_Supplier",J$22,$C$19,ori,"TOTAL PRODUCT","B-451510",$C$20,"Amount_BS")/1000) -> 1616.807 | K66: =(_xll.DBR("CXMD:FTM_DATA_BALANCE_SHEET","Total_Customer_Supplier",K$22,$C$19,ori,"TOTAL PRODUCT","B-451510",$C$20,"Amount_BS")/1000) -> 1774.7556 | ... O66: =(_xll.DBR("CXMD:FTM_DATA_BALANCE_SHEET","Total_Customer_Supplier",O$22,$C$19,ori,"TOTAL PRODUCT","B-451510",$C$20,"Amount_BS")/1000) -> 1470.1569 | P66: =SUM(D66:O66) -> 21044.604
B67: G - 459000 - OTHER EXPENSES | C67: B-0-B-P-451310-Licences/royalties expen | D67: =(_xll.DBR("CXMD:FTM_DATA_BALANCE_SHEET","Total_Customer_Supplier",D$22,$C$19,ori,"TOTAL PRODUCT","B-451310",$C$20,"Amount_BS")/1000) -> -202.28409 | E67: =(_xll.DBR("CXMD:FTM_DATA_BALANCE_SHEET","Total_Customer_Supplier",E$22,$C$19,ori,"TOTAL PRODUCT","B-451310",$C$20,"Amount_BS")/1000) -> 283.404 | F67: =(_xll.DBR("CXMD:FTM_DATA_BALANCE_SHEET","Total_Customer_Supplier",F$22,$C$19,ori,"TOTAL PRODUCT","B-451310",$C$20,"Amount_BS")/1000) -> 432.14015 | G67: =(_xll.DBR("CXMD:FTM_DATA_BALANCE_SHEET","Total_Customer_Supplier",G$22,$C$19,ori,"TOTAL PRODUCT","B-451310",$C$20,"Amount_BS")/1000) -> 310.95808 | H67: =(_xll.DBR("CXMD:FTM_DATA_BALANCE_SHEET","Total_Customer_Supplier",H$22,$C$19,ori,"TOTAL PRODUCT","B-451310",$C$20,"Amount_BS")/1000) -> 315.72139 | I67: =(_xll.DBR("CXMD:FTM_DATA_BALANCE_SHEET","Total_Customer_Supplier",I$22,$C$19,ori,"TOTAL PRODUCT","B-451310",$C$20,"Amount_BS")/1000) -> 491.00467 | J67: =(_xll.DBR("CXMD:FTM_DATA_BALANCE_SHEET","Total_Customer_Supplier",J$22,$C$19,ori,"TOTAL PRODUCT","B-451310",$C$20,"Amount_BS")/1000) -> 320.05407 | K67: =(_xll.DBR("CXMD:FTM_DATA_BALANCE_SHEET","Total_Customer_Supplier",K$22,$C$19,ori,"TOTAL PRODUCT","B-451310",$C$20,"Amount_BS")/1000) -> 450.00929 | ... O67: =(_xll.DBR("CXMD:FTM_DATA_BALANCE_SHEET","Total_Customer_Supplier",O$22,$C$19,ori,"TOTAL PRODUCT","B-451310",$C$20,"Amount_BS")/1000) -> 62.85523 | P67: =SUM(D67:O67) -> 3465.2825
B68: G - 459000 - OTHER EXPENSES | C68: B-0-B-P-999999-ALLOCAITON ACCOUNTING | D68: =(_xll.DBR("CXMD:FTM_DATA_BALANCE_SHEET","Total_Customer_Supplier",D$22,$C$19,ori,"TOTAL PRODUCT","B-999999",$C$20,"Amount_BS")/1000) -> -1.0942358e-13 | E68: =(_xll.DBR("CXMD:FTM_DATA_BALANCE_SHEET","Total_Customer_Supplier",E$22,$C$19,ori,"TOTAL PRODUCT","B-999999",$C$20,"Amount_BS")/1000) -> 2.4249402e-13 | F68: =(_xll.DBR("CXMD:FTM_DATA_BALANCE_SHEET","Total_Customer_Supplier",F$22,$C$19,ori,"TOTAL PRODUCT","B-999999",$C$20,"Amount_BS")/1000) -> -8.0478202e-13 | G68: =(_xll.DBR("CXMD:FTM_DATA_BALANCE_SHEET","Total_Customer_Supplier",G$22,$C$19,ori,"TOTAL PRODUCT","B-999999",$C$20,"Amount_BS")/1000) -> -5.0383164e-13 | H68: =(_xll.DBR("CXMD:FTM_DATA_BALANCE_SHEET","Total_Customer_Supplier",H$22,$C$19,ori,"TOTAL PRODUCT","B-999999",$C$20,"Amount_BS")/1000) -> -2.1771029e-14 | I68: =(_xll.DBR("CXMD:FTM_DATA_BALANCE_SHEET","Total_Customer_Supplier",I$22,$C$19,ori,"TOTAL PRODUCT","B-999999",$C$20,"Amount_BS")/1000) -> -8.5930196e-13 | J68: =(_xll.DBR("CXMD:FTM_DATA_BALANCE_SHEET","Total_Customer_Supplier",J$22,$C$19,ori,"TOTAL PRODUCT","B-999999",$C$20,"Amount_BS")/1000) -> -1.6768809e-13 | K68: =(_xll.DBR("CXMD:FTM_DATA_BALANCE_SHEET","Total_Customer_Supplier",K$22,$C$19,ori,"TOTAL PRODUCT","B-999999",$C$20,"Amount_BS")/1000) -> 3.6379788e-14 | ... O68: =(_xll.DBR("CXMD:FTM_DATA_BALANCE_SHEET","Total_Customer_Supplier",O$22,$C$19,ori,"TOTAL PRODUCT","B-999999",$C$20,"Amount_BS")/1000) -> 3.6313565e-12 | P68: =SUM(D68:O68) -> 5.5776539e-12
B69: G - 453900 - FX GAIN/LOSS | C69: Profit and Loss | D69: =_xll.DBR("CXMD:FTM_DATA_BALANCE_SHEET","Total_Customer_Supplier",D$22,$C$19,ori,"TOTAL PRODUCT","B-453010",$C$20,"Amount_BS")/1000 -> -14389.183 | E69: =_xll.DBR("CXMD:FTM_DATA_BALANCE_SHEET","Total_Customer_Supplier",E$22,$C$19,ori,"TOTAL PRODUCT","B-453010",$C$20,"Amount_BS")/1000 -> 4247.0622 | F69: =_xll.DBR("CXMD:FTM_DATA_BALANCE_SHEET","Total_Customer_Supplier",F$22,$C$19,ori,"TOTAL PRODUCT","B-453010",$C$20,"Amount_BS")/1000 -> 2508.6431 | G69: =_xll.DBR("CXMD:FTM_DATA_BALANCE_SHEET","Total_Customer_Supplier",G$22,$C$19,ori,"TOTAL PRODUCT","B-453010",$C$20,"Amount_BS")/1000 -> 599.29278 | H69: =_xll.DBR("CXMD:FTM_DATA_BALANCE_SHEET","Total_Customer_Supplier",H$22,$C$19,ori,"TOTAL PRODUCT","B-453010",$C$20,"Amount_BS")/1000 -> -466.32202 | I69: =_xll.DBR("CXMD:FTM_DATA_BALANCE_SHEET","Total_Customer_Supplier",I$22,$C$19,ori,"TOTAL PRODUCT","B-453010",$C$20,"Amount_BS")/1000 -> 96.67575 | J69: =_xll.DBR("CXMD:FTM_DATA_BALANCE_SHEET","Total_Customer_Supplier",J$22,$C$19,ori,"TOTAL PRODUCT","B-453010",$C$20,"Amount_BS")/1000 -> 2041.2399 | K69: =_xll.DBR("CXMD:FTM_DATA_BALANCE_SHEET","Total_Customer_Supplier",K$22,$C$19,ori,"TOTAL PRODUCT","B-453010",$C$20,"Amount_BS")/1000 -> -1527.4297 | ... O69: =_xll.DBR("CXMD:FTM_DATA_BALANCE_SHEET","Total_Customer_Supplier",O$22,$C$19,ori,"TOTAL PRODUCT","B-453010",$C$20,"Amount_BS")/1000 -> 2811.9654 | P69: =SUM(D69:O69) -> -3499.1707
B70: G - 453900 - FX GAIN/LOSS | C70: R-0-R-P-959000-OTHER EXPENSES | D70: =D71 -> -14389.183 | E70: =E71 -> 4247.0622 | F70: =F71 -> 2508.6431 | G70: =G71 -> 599.29278 | H70: =H71 -> -466.32202 | I70: =I71 -> 96.67575 | J70: =J71 -> 2041.2399 | K70: =K71 -> -1527.4297 | ... O70: =O71 -> 2811.9654 | P70: =SUM(D70:O70) -> -3499.1707
B71: G - 453900 - FX GAIN/LOSS | C71: B-0-B-P-453010-OPERAT. FX G/L REALISED | D71: =(_xll.DBR("CXMD:FTM_DATA_BALANCE_SHEET","Total_Customer_Supplier",D$22,$C$19,ori,"TOTAL PRODUCT","B-453010",$C$20,"Amount_BS")/1000) -> -14389.183 | E71: =(_xll.DBR("CXMD:FTM_DATA_BALANCE_SHEET","Total_Customer_Supplier",E$22,$C$19,ori,"TOTAL PRODUCT","B-453010",$C$20,"Amount_BS")/1000) -> 4247.0622 | F71: =(_xll.DBR("CXMD:FTM_DATA_BALANCE_SHEET","Total_Customer_Supplier",F$22,$C$19,ori,"TOTAL PRODUCT","B-453010",$C$20,"Amount_BS")/1000) -> 2508.6431 | G71: =(_xll.DBR("CXMD:FTM_DATA_BALANCE_SHEET","Total_Customer_Supplier",G$22,$C$19,ori,"TOTAL PRODUCT","B-453010",$C$20,"Amount_BS")/1000) -> 599.29278 | H71: =(_xll.DBR("CXMD:FTM_DATA_BALANCE_SHEET","Total_Customer_Supplier",H$22,$C$19,ori,"TOTAL PRODUCT","B-453010",$C$20,"Amount_BS")/1000) -> -466.32202 | I71: =(_xll.DBR("CXMD:FTM_DATA_BALANCE_SHEET","Total_Customer_Supplier",I$22,$C$19,ori,"TOTAL PRODUCT","B-453010",$C$20,"Amount_BS")/1000) -> 96.67575 | J71: =(_xll.DBR("CXMD:FTM_DATA_BALANCE_SHEET","Total_Customer_Supplier",J$22,$C$19,ori,"TOTAL PRODUCT","B-453010",$C$20,"Amount_BS")/1000) -> 2041.2399 | K71: =(_xll.DBR("CXMD:FTM_DATA_BALANCE_SHEET","Total_Customer_Supplier",K$22,$C$19,ori,"TOTAL PRODUCT","B-453010",$C$20,"Amount_BS")/1000) -> -1527.4297 | ... O71: =(_xll.DBR("CXMD:FTM_DATA_BALANCE_SHEET","Total_Customer_Supplier",O$22,$C$19,ori,"TOTAL PRODUCT","B-453010",$C$20,"Amount_BS")/1000) -> 2811.9654 | P71: =SUM(D71:O71) -> -3499.1707
B72: G - 479000 - DEPREC. PROV. | C72: Profit and Loss | D72: =(_xll.DBR("CXMD:FTM_DATA_BALANCE_SHEET","Total_Customer_Supplier",D$22,$C$19,ori,"TOTAL PRODUCT","B-470010",$C$20,"Amount_BS")/1000)+(_xll.DBR("CXMD:FTM_DATA_BALANCE_SHEET","Total_Customer_Supplier",D$22,$C$19,ori,"TOTAL PRODUCT","B-475010",$C$20,"Amount_BS")/1000) -> 3386.485 | E72: =(_xll.DBR("CXMD:FTM_DATA_BALANCE_SHEET","Total_Customer_Supplier",E$22,$C$19,ori,"TOTAL PRODUCT","B-470010",$C$20,"Amount_BS")/1000)+(_xll.DBR("CXMD:FTM_DATA_BALANCE_SHEET","Total_Customer_Supplier",E$22,$C$19,ori,"TOTAL PRODUCT","B-475010",$C$20,"Amount_BS")/1000) -> 3446.382 | F72: =(_xll.DBR("CXMD:FTM_DATA_BALANCE_SHEET","Total_Customer_Supplier",F$22,$C$19,ori,"TOTAL PRODUCT","B-470010",$C$20,"Amount_BS")/1000)+(_xll.DBR("CXMD:FTM_DATA_BALANCE_SHEET","Total_Customer_Supplier",F$22,$C$19,ori,"TOTAL PRODUCT","B-475010",$C$20,"Amount_BS")/1000) -> 3248.5829 | G72: =(_xll.DBR("CXMD:FTM_DATA_BALANCE_SHEET","Total_Customer_Supplier",G$22,$C$19,ori,"TOTAL PRODUCT","B-470010",$C$20,"Amount_BS")/1000)+(_xll.DBR("CXMD:FTM_DATA_BALANCE_SHEET","Total_Customer_Supplier",G$22,$C$19,ori,"TOTAL PRODUCT","B-475010",$C$20,"Amount_BS")/1000) -> 3315.1649 | H72: =(_xll.DBR("CXMD:FTM_DATA_BALANCE_SHEET","Total_Customer_Supplier",H$22,$C$19,ori,"TOTAL PRODUCT","B-470010",$C$20,"Amount_BS")/1000)+(_xll.DBR("CXMD:FTM_DATA_BALANCE_SHEET","Total_Customer_Supplier",H$22,$C$19,ori,"TOTAL PRODUCT","B-475010",$C$20,"Amount_BS")/1000) -> 3356.0762 | I72: =(_xll.DBR("CXMD:FTM_DATA_BALANCE_SHEET","Total_Customer_Supplier",I$22,$C$19,ori,"TOTAL PRODUCT","B-470010",$C$20,"Amount_BS")/1000)+(_xll.DBR("CXMD:FTM_DATA_BALANCE_SHEET","Total_Customer_Supplier",I$22,$C$19,ori,"TOTAL PRODUCT","B-475010",$C$20,"Amount_BS")/1000) -> 3390.1403 | J72: =(_xll.DBR("CXMD:FTM_DATA_BALANCE_SHEET","Total_Customer_Supplier",J$22,$C$19,ori,"TOTAL PRODUCT","B-470010",$C$20,"Amount_BS")/1000)+(_xll.DBR("CXMD:FTM_DATA_BALANCE_SHEET","Total_Customer_Supplier",J$22,$C$19,ori,"TOTAL PRODUCT","B-475010",$C$20,"Amount_BS")/1000) -> 3385.8418 | K72: =(_xll.DBR("CXMD:FTM_DATA_BALANCE_SHEET","Total_Customer_Supplier",K$22,$C$19,ori,"TOTAL PRODUCT","B-470010",$C$20,"Amount_BS")/1000)+(_xll.DBR("CXMD:FTM_DATA_BALANCE_SHEET","Total_Customer_Supplier",K$22,$C$19,ori,"TOTAL PRODUCT","B-475010",$C$20,"Amount_BS")/1000) -> 3432.8227 | ... O72: =(_xll.DBR("CXMD:FTM_DATA_BALANCE_SHEET","Total_Customer_Supplier",O$22,$C$19,ori,"TOTAL PRODUCT","B-470010",$C$20,"Amount_BS")/1000)+(_xll.DBR("CXMD:FTM_DATA_BALANCE_SHEET","Total_Customer_Supplier",O$22,$C$19,ori,"TOTAL PRODUCT","B-475010",$C$20,"Amount_BS")/1000) -> 3300.1832 | P72: =SUM(D72:O72) -> 39702.352
B73: G - 479000 - DEPREC. PROV. | C73: R-0-R-P-981000-DEPRECIATION | D73: =(_xll.DBR("CXMD:FTM_DATA_BALANCE_SHEET","Total_Customer_Supplier",D$22,$C$19,ori,"TOTAL PRODUCT","R-981000",$C$20,"Amount_BS")/1000) -> 3386.485 | E73: =(_xll.DBR("CXMD:FTM_DATA_BALANCE_SHEET","Total_Customer_Supplier",E$22,$C$19,ori,"TOTAL PRODUCT","R-981000",$C$20,"Amount_BS")/1000) -> 3446.382 | F73: =(_xll.DBR("CXMD:FTM_DATA_BALANCE_SHEET","Total_Customer_Supplier",F$22,$C$19,ori,"TOTAL PRODUCT","R-981000",$C$20,"Amount_BS")/1000) -> 3248.5829 | G73: =(_xll.DBR("CXMD:FTM_DATA_BALANCE_SHEET","Total_Customer_Supplier",G$22,$C$19,ori,"TOTAL PRODUCT","R-981000",$C$20,"Amount_BS")/1000) -> 3315.1649 | H73: =(_xll.DBR("CXMD:FTM_DATA_BALANCE_SHEET","Total_Customer_Supplier",H$22,$C$19,ori,"TOTAL PRODUCT","R-981000",$C$20,"Amount_BS")/1000) -> 3356.0762 | I73: =(_xll.DBR("CXMD:FTM_DATA_BALANCE_SHEET","Total_Customer_Supplier",I$22,$C$19,ori,"TOTAL PRODUCT","R-981000",$C$20,"Amount_BS")/1000) -> 3390.1403 | J73: =(_xll.DBR("CXMD:FTM_DATA_BALANCE_SHEET","Total_Customer_Supplier",J$22,$C$19,ori,"TOTAL PRODUCT","R-981000",$C$20,"Amount_BS")/1000) -> 3385.8418 | K73: =(_xll.DBR("CXMD:FTM_DATA_BALANCE_SHEET","Total_Customer_Supplier",K$22,$C$19,ori,"TOTAL PRODUCT","R-981000",$C$20,"Amount_BS")/1000) -> 3432.8227 | ... O73: =(_xll.DBR("CXMD:FTM_DATA_BALANCE_SHEET","Total_Customer_Supplier",O$22,$C$19,ori,"TOTAL PRODUCT","R-981000",$C$20,"Amount_BS")/1000) -> 3300.1832 | P73: =SUM(D73:O73) -> 39702.352
B74: Ebit without Management fees | D74: =D29-D34-D46-D54-D69-D72-D30 -> 86917.47 | E74: =E29-E34-E46-E54-E69-E72-E30 -> 70173.044 | F74: =F29-F34-F46-F54-F69-F72-F30 -> 42198.06 | G74: =G29-G34-G46-G54-G69-G72-G30 -> 36734.624 | H74: =H29-H34-H46-H54-H69-H72-H30 -> 68398.344 | I74: =I29-I34-I46-I54-I69-I72-I30 -> 62307.064 | J74: =J29-J34-J46-J54-J69-J72-J30 -> 70679.445 | K74: =K29-K34-K46-K54-K69-K72-K30 -> 106805.41 | ... O74: =O29-O34-O46-O54-O69-O72-O30 -> 16398.408 | P74: =SUM(D74:O74) -> 693916.26
C75: % of net sales | D75: =IF(D25<>0,D74/D25,0) -> 0.24154242 | E75: =IF(E25<>0,E74/E25,0) -> 0.20617793 | F75: =IF(F25<>0,F74/F25,0) -> 0.11924864 | G75: =IF(G25<>0,G74/G25,0) -> 0.11364577 | H75: =IF(H25<>0,H74/H25,0) -> 0.19029443 | I75: =IF(I25<>0,I74/I25,0) -> 0.16401183 | J75: =IF(J25<>0,J74/J25,0) -> 0.18595233 | K75: =IF(K25<>0,K74/K25,0) -> 0.29433219 | ... P75: =IF(P25<>0,P74/P25,0) -> 0.170384
B76: G - 569199 - OTHER INCOME/EXPENSES | C76: Profit and Loss | D76: =(_xll.DBR("CXMD:FTM_DATA_BALANCE_SHEET","Total_Customer_Supplier",D$22,$C$19,ori,"TOTAL PRODUCT","B-560020",$C$20,"Amount_BS")/1000)+(_xll.DBR("CXMD:FTM_DATA_BALANCE_SHEET","Total_Customer_Supplier",D$22,$C$19,ori,"TOTAL PRODUCT","B-561010",$C$20,"Amount_BS")/1000) -> 462.46413 | E76: =(_xll.DBR("CXMD:FTM_DATA_BALANCE_SHEET","Total_Customer_Supplier",E$22,$C$19,ori,"TOTAL PRODUCT","B-560020",$C$20,"Amount_BS")/1000)+(_xll.DBR("CXMD:FTM_DATA_BALANCE_SHEET","Total_Customer_Supplier",E$22,$C$19,ori,"TOTAL PRODUCT","B-561010",$C$20,"Amount_BS")/1000) -> 462.46413 | F76: =(_xll.DBR("CXMD:FTM_DATA_BALANCE_SHEET","Total_Customer_Supplier",F$22,$C$19,ori,"TOTAL PRODUCT","B-560020",$C$20,"Amount_BS")/1000)+(_xll.DBR("CXMD:FTM_DATA_BALANCE_SHEET","Total_Customer_Supplier",F$22,$C$19,ori,"TOTAL PRODUCT","B-561010",$C$20,"Amount_BS")/1000) -> 462.46413 | G76: =(_xll.DBR("CXMD:FTM_DATA_BALANCE_SHEET","Total_Customer_Supplier",G$22,$C$19,ori,"TOTAL PRODUCT","B-560020",$C$20,"Amount_BS")/1000)+(_xll.DBR("CXMD:FTM_DATA_BALANCE_SHEET","Total_Customer_Supplier",G$22,$C$19,ori,"TOTAL PRODUCT","B-561010",$C$20,"Amount_BS")/1000) -> 799.42713 | H76: =(_xll.DBR("CXMD:FTM_DATA_BALANCE_SHEET","Total_Customer_Supplier",H$22,$C$19,ori,"TOTAL PRODUCT","B-560020",$C$20,"Amount_BS")/1000)+(_xll.DBR("CXMD:FTM_DATA_BALANCE_SHEET","Total_Customer_Supplier",H$22,$C$19,ori,"TOTAL PRODUCT","B-561010",$C$20,"Amount_BS")/1000) -> 462.46413 | I76: =(_xll.DBR("CXMD:FTM_DATA_BALANCE_SHEET","Total_Customer_Supplier",I$22,$C$19,ori,"TOTAL PRODUCT","B-560020",$C$20,"Amount_BS")/1000)+(_xll.DBR("CXMD:FTM_DATA_BALANCE_SHEET","Total_Customer_Supplier",I$22,$C$19,ori,"TOTAL PRODUCT","B-561010",$C$20,"Amount_BS")/1000) -> 462.46413 | J76: =(_xll.DBR("CXMD:FTM_DATA_BALANCE_SHEET","Total_Customer_Supplier",J$22,$C$19,ori,"TOTAL PRODUCT","B-560020",$C$20,"Amount_BS")/1000)+(_xll.DBR("CXMD:FTM_DATA_BALANCE_SHEET","Total_Customer_Supplier",J$22,$C$19,ori,"TOTAL PRODUCT","B-561010",$C$20,"Amount_BS")/1000) -> 462.46413 | K76: =(_xll.DBR("CXMD:FTM_DATA_BALANCE_SHEET","Total_Customer_Supplier",K$22,$C$19,ori,"TOTAL PRODUCT","B-560020",$C$20,"Amount_BS")/1000)+(_xll.DBR("CXMD:FTM_DATA_BALANCE_SHEET","Total_Customer_Supplier",K$22,$C$19,ori,"TOTAL PRODUCT","B-561010",$C$20,"Amount_BS")/1000) -> 462.46413 | ... O76: =(_xll.DBR("CXMD:FTM_DATA_BALANCE_SHEET","Total_Customer_Supplier",O$22,$C$19,ori,"TOTAL PRODUCT","B-560020",$C$20,"Amount_BS")/1000)+(_xll.DBR("CXMD:FTM_DATA_BALANCE_SHEET","Total_Customer_Supplier",O$22,$C$19,ori,"TOTAL PRODUCT","B-561010",$C$20,"Amount_BS")/1000) -> 98.3356 | P76: =SUM(D76:O76) -> 5895.958
B77: G - 569199 - OTHER INCOME/EXPENSES | C77: R-0-R-P-959100-MANAGEMENT FEES BI | D77: =(_xll.DBR("CXMD:FTM_DATA_BALANCE_SHEET","Total_Customer_Supplier",D$22,$C$19,ori,"TOTAL PRODUCT","R-959100",$C$20,"Amount_BS")/1000) -> 329.583 | E77: =(_xll.DBR("CXMD:FTM_DATA_BALANCE_SHEET","Total_Customer_Supplier",E$22,$C$19,ori,"TOTAL PRODUCT","R-959100",$C$20,"Amount_BS")/1000) -> 329.583 | F77: =(_xll.DBR("CXMD:FTM_DATA_BALANCE_SHEET","Total_Customer_Supplier",F$22,$C$19,ori,"TOTAL PRODUCT","R-959100",$C$20,"Amount_BS")/1000) -> 329.583 | G77: =(_xll.DBR("CXMD:FTM_DATA_BALANCE_SHEET","Total_Customer_Supplier",G$22,$C$19,ori,"TOTAL PRODUCT","R-959100",$C$20,"Amount_BS")/1000) -> 666.546 | H77: =(_xll.DBR("CXMD:FTM_DATA_BALANCE_SHEET","Total_Customer_Supplier",H$22,$C$19,ori,"TOTAL PRODUCT","R-959100",$C$20,"Amount_BS")/1000) -> 329.583 | I77: =(_xll.DBR("CXMD:FTM_DATA_BALANCE_SHEET","Total_Customer_Supplier",I$22,$C$19,ori,"TOTAL PRODUCT","R-959100",$C$20,"Amount_BS")/1000) -> 329.583 | J77: =(_xll.DBR("CXMD:FTM_DATA_BALANCE_SHEET","Total_Customer_Supplier",J$22,$C$19,ori,"TOTAL PRODUCT","R-959100",$C$20,"Amount_BS")/1000) -> 329.583 | K77: =(_xll.DBR("CXMD:FTM_DATA_BALANCE_SHEET","Total_Customer_Supplier",K$22,$C$19,ori,"TOTAL PRODUCT","R-959100",$C$20,"Amount_BS")/1000) -> 329.583 | ... O77: =(_xll.DBR("CXMD:FTM_DATA_BALANCE_SHEET","Total_Customer_Supplier",O$22,$C$19,ori,"TOTAL PRODUCT","R-959100",$C$20,"Amount_BS")/1000) -> 75.158 | P77: =SUM(D77:O77) -> 4411.088
B78: G - 569199 - OTHER INCOME/EXPENSES | C78: R-0-R-P-990000-NON EBIT | D78: =(_xll.DBR("CXMD:FTM_DATA_BALANCE_SHEET","Total_Customer_Supplier",D$22,$C$19,ori,"TOTAL PRODUCT","R-990000",$C$20,"Amount_BS")/1000) -> 2239.74 | E78: =(_xll.DBR("CXMD:FTM_DATA_BALANCE_SHEET","Total_Customer_Supplier",E$22,$C$19,ori,"TOTAL PRODUCT","R-990000",$C$20,"Amount_BS")/1000) -> -771.18992 | F78: =(_xll.DBR("CXMD:FTM_DATA_BALANCE_SHEET","Total_Customer_Supplier",F$22,$C$19,ori,"TOTAL PRODUCT","R-990000",$C$20,"Amount_BS")/1000) -> 15197.677 | G78: =(_xll.DBR("CXMD:FTM_DATA_BALANCE_SHEET","Total_Customer_Supplier",G$22,$C$19,ori,"TOTAL PRODUCT","R-990000",$C$20,"Amount_BS")/1000) -> -10775.521 | H78: =(_xll.DBR("CXMD:FTM_DATA_BALANCE_SHEET","Total_Customer_Supplier",H$22,$C$19,ori,"TOTAL PRODUCT","R-990000",$C$20,"Amount_BS")/1000) -> 1366.6095 | I78: =(_xll.DBR("CXMD:FTM_DATA_BALANCE_SHEET","Total_Customer_Supplier",I$22,$C$19,ori,"TOTAL PRODUCT","R-990000",$C$20,"Amount_BS")/1000) -> 21769.968 | J78: =(_xll.DBR("CXMD:FTM_DATA_BALANCE_SHEET","Total_Customer_Supplier",J$22,$C$19,ori,"TOTAL PRODUCT","R-990000",$C$20,"Amount_BS")/1000) -> -975.49857 | K78: =(_xll.DBR("CXMD:FTM_DATA_BALANCE_SHEET","Total_Customer_Supplier",K$22,$C$19,ori,"TOTAL PRODUCT","R-990000",$C$20,"Amount_BS")/1000) -> -472.22143 | ... O78: =(_xll.DBR("CXMD:FTM_DATA_BALANCE_SHEET","Total_Customer_Supplier",O$22,$C$19,ori,"TOTAL PRODUCT","R-990000",$C$20,"Amount_BS")/1000) -> 112356.41 | P78: =SUM(D78:O78) -> 159349.24
B79: Ebit including Management fees | D79: =D74-D76 -> 86455.006 | E79: =E74-E76 -> 69710.58 | F79: =F74-F76 -> 41735.596 | G79: =G74-G76 -> 35935.197 | H79: =H74-H76 -> 67935.88 | I79: =I74-I76 -> 61844.6 | J79: =J74-J76 -> 70216.981 | K79: =K74-K76 -> 106342.95 | ... O79: =O74-O76 -> 16300.072 | P79: =SUM(D79:O79) -> 688020.3
C80: % of net sales | D80: =IF(D25<>0,D79/D25,0) -> 0.24025724 | E80: =IF(E25<>0,E79/E25,0) -> 0.20481915 | F80: =IF(F25<>0,F79/F25,0) -> 0.11794175 | G80: =IF(G25<>0,G79/G25,0) -> 0.11117259 | H80: =IF(H25<>0,H79/H25,0) -> 0.18900778 | I80: =IF(I25<>0,I79/I25,0) -> 0.16279448 | J80: =IF(J25<>0,J79/J25,0) -> 0.18473562 | K80: =IF(K25<>0,K79/K25,0) -> 0.29305774 | ... P80: =IF(P25<>0,P79/P25,0) -> 0.1689363

Sheet P&L Month YTD by CC detailed
B18: Origin_Company | C18: =origine -> Total Origin Company
B19: Actuality | C19: ='P&L Month by CC summary'!C19 -> AC2022 | F19: P&L Month YTD _ detailed
B20: Allocation | C20: ='P&L Month by CC summary'!C20 -> Total Allocation
C22: in K Local Currency | D22: YTD_January | E22: YTD_February | F22: YTD_March | G22: YTD_April | H22: YTD_May | I22: YTD_June | J22: YTD_July | K22: YTD_August | L22: YTD_September | M22: YTD_October | N22: YTD_November | O22: YTD_December
B23: Bucher Account | C23: Chart of Account
D24: Amount_BS | E24: Amount_BS | H24: Amount_BS
B25: G - 309000 - NET SALES | C25: Profit and Loss | D25: =_xll.DBR("CXMD:FTM_DATA_BALANCE_SHEET","Total_Customer_Supplier",D$22,$C$19,ori,"TOTAL PRODUCT","B-300010",$C$20,"Amount_BS")*-1/1000 -> 359843.49 | E25: =_xll.DBR("CXMD:FTM_DATA_BALANCE_SHEET","Total_Customer_Supplier",E$22,$C$19,ori,"TOTAL PRODUCT","B-300010",$C$20,"Amount_BS")*-1/1000 -> 700195.37 | F25: =_xll.DBR("CXMD:FTM_DATA_BALANCE_SHEET","Total_Customer_Supplier",F$22,$C$19,ori,"TOTAL PRODUCT","B-300010",$C$20,"Amount_BS")*-1/1000 -> 1054061.5 | G25: =_xll.DBR("CXMD:FTM_DATA_BALANCE_SHEET","Total_Customer_Supplier",G$22,$C$19,ori,"TOTAL PRODUCT","B-300010",$C$20,"Amount_BS")*-1/1000 -> 1377299.5 | H25: =_xll.DBR("CXMD:FTM_DATA_BALANCE_SHEET","Total_Customer_Supplier",H$22,$C$19,ori,"TOTAL PRODUCT","B-300010",$C$20,"Amount_BS")*-1/1000 -> 1736733.8 | I25: =_xll.DBR("CXMD:FTM_DATA_BALANCE_SHEET","Total_Customer_Supplier",I$22,$C$19,ori,"TOTAL PRODUCT","B-300010",$C$20,"Amount_BS")*-1/1000 -> 2116627.5 | J25: =_xll.DBR("CXMD:FTM_DATA_BALANCE_SHEET","Total_Customer_Supplier",J$22,$C$19,ori,"TOTAL PRODUCT","B-300010",$C$20,"Amount_BS")*-1/1000 -> 2496721.9 | K25: =_xll.DBR("CXMD:FTM_DATA_BALANCE_SHEET","Total_Customer_Supplier",K$22,$C$19,ori,"TOTAL PRODUCT","B-300010",$C$20,"Amount_BS")*-1/1000 -> 2859595.6 | ... O25: =_xll.DBR("CXMD:FTM_DATA_BALANCE_SHEET","Total_Customer_Supplier",O$22,$C$19,ori,"TOTAL PRODUCT","B-300010",$C$20,"Amount_BS")*-1/1000 -> 4072661.1
B26: G - 319000 - NET VARIATION OF STOCK | C26: Profit and Loss | D26: =_xll.DBR("CXMD:FTM_DATA_BALANCE_SHEET","Total_Customer_Supplier",D$22,$C$19,ori,"TOTAL PRODUCT","B-310010",$C$20,"Amount_BS")*-1/1000 -> -30807.778 | E26: =_xll.DBR("CXMD:FTM_DATA_BALANCE_SHEET","Total_Customer_Supplier",E$22,$C$19,ori,"TOTAL PRODUCT","B-310010",$C$20,"Amount_BS")*-1/1000 -> -38508.695 | F26: =_xll.DBR("CXMD:FTM_DATA_BALANCE_SHEET","Total_Customer_Supplier",F$22,$C$19,ori,"TOTAL PRODUCT","B-310010",$C$20,"Amount_BS")*-1/1000 -> -20691.849 | G26: =_xll.DBR("CXMD:FTM_DATA_BALANCE_SHEET","Total_Customer_Supplier",G$22,$C$19,ori,"TOTAL PRODUCT","B-310010",$C$20,"Amount_BS")*-1/1000 -> -26217.428 | H26: =_xll.DBR("CXMD:FTM_DATA_BALANCE_SHEET","Total_Customer_Supplier",H$22,$C$19,ori,"TOTAL PRODUCT","B-310010",$C$20,"Amount_BS")*-1/1000 -> -2737.9111 | I26: =_xll.DBR("CXMD:FTM_DATA_BALANCE_SHEET","Total_Customer_Supplier",I$22,$C$19,ori,"TOTAL PRODUCT","B-310010",$C$20,"Amount_BS")*-1/1000 -> -11316.758 | J26: =_xll.DBR("CXMD:FTM_DATA_BALANCE_SHEET","Total_Customer_Supplier",J$22,$C$19,ori,"TOTAL PRODUCT","B-310010",$C$20,"Amount_BS")*-1/1000 -> -30213.846 | K26: =_xll.DBR("CXMD:FTM_DATA_BALANCE_SHEET","Total_Customer_Supplier",K$22,$C$19,ori,"TOTAL PRODUCT","B-310010",$C$20,"Amount_BS")*-1/1000 -> -30438.473 | ... O26: =_xll.DBR("CXMD:FTM_DATA_BALANCE_SHEET","Total_Customer_Supplier",O$22,$C$19,ori,"TOTAL PRODUCT","B-310010",$C$20,"Amount_BS")*-1/1000 -> 10475.845
B27: G-329000 Corporate output | D27: =D25+D26 -> 329035.72 | E27: =E25+E26 -> 661686.67 | F27: =F25+F26 -> 1033369.7 | G27: =G25+G26 -> 1351082 | H27: =H25+H26 -> 1733995.9 | I27: =I25+I26 -> 2105310.7 | J27: =J25+J26 -> 2466508.1 | K27: =K25+K26 -> 2829157.2 | ... O27: =O25+O26 -> 4083136.9
B28: G - 339000 - OPERATING INCOME | C28: Profit and Loss | D28: =_xll.DBR("CXMD:FTM_DATA_BALANCE_SHEET","Total_Customer_Supplier",D$22,$C$19,ori,"TOTAL PRODUCT","B-330010",$C$20,"Amount_BS")*-1/1000 -> 4042.3655 | E28: =_xll.DBR("CXMD:FTM_DATA_BALANCE_SHEET","Total_Customer_Supplier",E$22,$C$19,ori,"TOTAL PRODUCT","B-330010",$C$20,"Amount_BS")*-1/1000 -> 8583.2908 | F28: =_xll.DBR("CXMD:FTM_DATA_BALANCE_SHEET","Total_Customer_Supplier",F$22,$C$19,ori,"TOTAL PRODUCT","B-330010",$C$20,"Amount_BS")*-1/1000 -> 13431.463 | G28: =_xll.DBR("CXMD:FTM_DATA_BALANCE_SHEET","Total_Customer_Supplier",G$22,$C$19,ori,"TOTAL PRODUCT","B-330010",$C$20,"Amount_BS")*-1/1000 -> 17830.42 | H28: =_xll.DBR("CXMD:FTM_DATA_BALANCE_SHEET","Total_Customer_Supplier",H$22,$C$19,ori,"TOTAL PRODUCT","B-330010",$C$20,"Amount_BS")*-1/1000 -> 22213.297 | I28: =_xll.DBR("CXMD:FTM_DATA_BALANCE_SHEET","Total_Customer_Supplier",I$22,$C$19,ori,"TOTAL PRODUCT","B-330010",$C$20,"Amount_BS")*-1/1000 -> 26939.953 | J28: =_xll.DBR("CXMD:FTM_DATA_BALANCE_SHEET","Total_Customer_Supplier",J$22,$C$19,ori,"TOTAL PRODUCT","B-330010",$C$20,"Amount_BS")*-1/1000 -> 31469.609 | K28: =_xll.DBR("CXMD:FTM_DATA_BALANCE_SHEET","Total_Customer_Supplier",K$22,$C$19,ori,"TOTAL PRODUCT","B-330010",$C$20,"Amount_BS")*-1/1000 -> 35826.213 | ... O28: =_xll.DBR("CXMD:FTM_DATA_BALANCE_SHEET","Total_Customer_Supplier",O$22,$C$19,ori,"TOTAL PRODUCT","B-330010",$C$20,"Amount_BS")*-1/1000 -> 52175.87
B29: REVENUE | D29: =D27+D28 -> 333078.08 | E29: =E27+E28 -> 670269.96 | F29: =F27+F28 -> 1046801.2 | G29: =G27+G28 -> 1368912.5 | H29: =H27+H28 -> 1756209.2 | I29: =I27+I28 -> 2132250.7 | J29: =J27+J28 -> 2497977.7 | K29: =K27+K28 -> 2864983.4 | ... O29: =O27+O28 -> 4135312.8
B30: G - 452000 - VARIATION OF PROVISIONS | C30: Profit and Loss | D30: =D32+D33 -> 442.07326 | E30: =E32+E33 -> 247.15668 | F30: =F32+F33 -> 1860.5594 | G30: =G32+G33 -> 3118.3911 | H30: =H32+H33 -> 3052.1005 | I30: =I32+I33 -> 3596.8589 | J30: =J32+J33 -> 5073.9976 | K30: =K32+K33 -> 5982.9797 | ... O30: =O32+O33 -> 29689.028
B31: G - 452000 - VARIATION OF PROVISIONS | C31: R-0-R-P-959000-OTHER EXPENSES | D31: =D32+D33 -> 442.07326 | E31: =E32+E33 -> 247.15668 | F31: =F32+F33 -> 1860.5594 | G31: =G32+G33 -> 3118.3911 | H31: =H32+H33 -> 3052.1005 | I31: =I32+I33 -> 3596.8589 | J31: =J32+J33 -> 5073.9976 | K31: =K32+K33 -> 5982.9797 | ... O31: =O32+O33 -> 29689.028
B32: G - 452000 - VARIATION OF PROVISIONS | C32: B-0-B-P-452010-Allowances / value adj. | D32: =(_xll.DBR("CXMD:FTM_DATA_BALANCE_SHEET","Total_Customer_Supplier",D$22,$C$19,ori,"TOTAL PRODUCT","B-452010",$C$20,"Amount_BS")/1000) -> -83.31825 | E32: =(_xll.DBR("CXMD:FTM_DATA_BALANCE_SHEET","Total_Customer_Supplier",E$22,$C$19,ori,"TOTAL PRODUCT","B-452010",$C$20,"Amount_BS")/1000) -> -602.31825 | F32: =(_xll.DBR("CXMD:FTM_DATA_BALANCE_SHEET","Total_Customer_Supplier",F$22,$C$19,ori,"TOTAL PRODUCT","B-452010",$C$20,"Amount_BS")/1000) -> -575.89905 | G32: =(_xll.DBR("CXMD:FTM_DATA_BALANCE_SHEET","Total_Customer_Supplier",G$22,$C$19,ori,"TOTAL PRODUCT","B-452010",$C$20,"Amount_BS")/1000) -> -643.25305 | H32: =(_xll.DBR("CXMD:FTM_DATA_BALANCE_SHEET","Total_Customer_Supplier",H$22,$C$19,ori,"TOTAL PRODUCT","B-452010",$C$20,"Amount_BS")/1000) -> -664.25305 | I32: =(_xll.DBR("CXMD:FTM_DATA_BALANCE_SHEET","Total_Customer_Supplier",I$22,$C$19,ori,"TOTAL PRODUCT","B-452010",$C$20,"Amount_BS")/1000) -> -1835.6397 | J32: =(_xll.DBR("CXMD:FTM_DATA_BALANCE_SHEET","Total_Customer_Supplier",J$22,$C$19,ori,"TOTAL PRODUCT","B-452010",$C$20,"Amount_BS")/1000) -> -1768.2669 | K32: =(_xll.DBR("CXMD:FTM_DATA_BALANCE_SHEET","Total_Customer_Supplier",K$22,$C$19,ori,"TOTAL PRODUCT","B-452010",$C$20,"Amount_BS")/1000) -> -1922.5669 | ... O32: =(_xll.DBR("CXMD:FTM_DATA_BALANCE_SHEET","Total_Customer_Supplier",O$22,$C$19,ori,"TOTAL PRODUCT","B-452010",$C$20,"Amount_BS")/1000) -> 2871.1198
B33: G - 452000 - VARIATION OF PROVISIONS | C33: B-0-B-P-452210-Changes - provisions - | D33: =(_xll.DBR("CXMD:FTM_DATA_BALANCE_SHEET","Total_Customer_Supplier",D$22,$C$19,ori,"TOTAL PRODUCT","B-452210",$C$20,"Amount_BS")/1000) -> 525.39151 | E33: =(_xll.DBR("CXMD:FTM_DATA_BALANCE_SHEET","Total_Customer_Supplier",E$22,$C$19,ori,"TOTAL PRODUCT","B-452210",$C$20,"Amount_BS")/1000) -> 849.47493 | F33: =(_xll.DBR("CXMD:FTM_DATA_BALANCE_SHEET","Total_Customer_Supplier",F$22,$C$19,ori,"TOTAL PRODUCT","B-452210",$C$20,"Amount_BS")/1000) -> 2436.4585 | G33: =(_xll.DBR("CXMD:FTM_DATA_BALANCE_SHEET","Total_Customer_Supplier",G$22,$C$19,ori,"TOTAL PRODUCT","B-452210",$C$20,"Amount_BS")/1000) -> 3761.6442 | H33: =(_xll.DBR("CXMD:FTM_DATA_BALANCE_SHEET","Total_Customer_Supplier",H$22,$C$19,ori,"TOTAL PRODUCT","B-452210",$C$20,"Amount_BS")/1000) -> 3716.3536 | I33: =(_xll.DBR("CXMD:FTM_DATA_BALANCE_SHEET","Total_Customer_Supplier",I$22,$C$19,ori,"TOTAL PRODUCT","B-452210",$C$20,"Amount_BS")/1000) -> 5432.4986 | J33: =(_xll.DBR("CXMD:FTM_DATA_BALANCE_SHEET","Total_Customer_Supplier",J$22,$C$19,ori,"TOTAL PRODUCT","B-452210",$C$20,"Amount_BS")/1000) -> 6842.2645 | K33: =(_xll.DBR("CXMD:FTM_DATA_BALANCE_SHEET","Total_Customer_Supplier",K$22,$C$19,ori,"TOTAL PRODUCT","B-452210",$C$20,"Amount_BS")/1000) -> 7905.5466 | ... O33: =(_xll.DBR("CXMD:FTM_DATA_BALANCE_SHEET","Total_Customer_Supplier",O$22,$C$19,ori,"TOTAL PRODUCT","B-452210",$C$20,"Amount_BS")/1000) -> 26817.908
B34: Total Material expenses + net var. stock | C34: Profit and Loss | D34: =(_xll.DBR("CXMD:FTM_DATA_BALANCE_SHEET","Total_Customer_Supplier",D$22,$C$19,ori,"TOTAL PRODUCT","B-401010",$C$20,"Amount_BS")/1000)+(_xll.DBR("CXMD:FTM_DATA_BALANCE_SHEET","Total_Customer_Supplier",D$22,$C$19,ori,"TOTAL PRODUCT","B-401020",$C$20,"Amount_BS")/1000)+(_xll.DBR("CXMD:FTM_DATA_BALANCE_SHEET","Total_Customer_Supplier",D$22,$C$19,ori,"TOTAL PRODUCT","B-402110",$C$20,"Amount_BS")/1000)+(_xll.DBR("CXMD:FTM_DATA_BALANCE_SHEET","Total_Customer_Supplier",D$22,$C$19,ori,"TOTAL PRODUCT","B-402111",$C$20,"Amount_BS")/1000)+(_xll.DBR("CXMD:FTM_DATA_BALANCE_SHEET","Total_Customer_Supplier",D$22,$C$19,ori,"TOTAL PRODUCT","B-407010",$C$20,"Amount_BS")/1000) -> 190042.62 | E34: =(_xll.DBR("CXMD:FTM_DATA_BALANCE_SHEET","Total_Customer_Supplier",E$22,$C$19,ori,"TOTAL PRODUCT","B-401010",$C$20,"Amount_BS")/1000)+(_xll.DBR("CXMD:FTM_DATA_BALANCE_SHEET","Total_Customer_Supplier",E$22,$C$19,ori,"TOTAL PRODUCT","B-401020",$C$20,"Amount_BS")/1000)+(_xll.DBR("CXMD:FTM_DATA_BALANCE_SHEET","Total_Customer_Supplier",E$22,$C$19,ori,"TOTAL PRODUCT","B-402110",$C$20,"Amount_BS")/1000)+(_xll.DBR("CXMD:FTM_DATA_BALANCE_SHEET","Total_Customer_Supplier",E$22,$C$19,ori,"TOTAL PRODUCT","B-402111",$C$20,"Amount_BS")/1000)+(_xll.DBR("CXMD:FTM_DATA_BALANCE_SHEET","Total_Customer_Supplier",E$22,$C$19,ori,"TOTAL PRODUCT","B-407010",$C$20,"Amount_BS")/1000) -> 382894.78 | F34: =(_xll.DBR("CXMD:FTM_DATA_BALANCE_SHEET","Total_Customer_Supplier",F$22,$C$19,ori,"TOTAL PRODUCT","B-401010",$C$20,"Amount_BS")/1000)+(_xll.DBR("CXMD:FTM_DATA_BALANCE_SHEET","Total_Customer_Supplier",F$22,$C$19,ori,"TOTAL PRODUCT","B-401020",$C$20,"Amount_BS")/1000)+(_xll.DBR("CXMD:FTM_DATA_BALANCE_SHEET","Total_Customer_Supplier",F$22,$C$19,ori,"TOTAL PRODUCT","B-402110",$C$20,"Amount_BS")/1000)+(_xll.DBR("CXMD:FTM_DATA_BALANCE_SHEET","Total_Customer_Supplier",F$22,$C$19,ori,"TOTAL PRODUCT","B-402111",$C$20,"Amount_BS")/1000)+(_xll.DBR("CXMD:FTM_DATA_BALANCE_SHEET","Total_Customer_Supplier",F$22,$C$19,ori,"TOTAL PRODUCT","B-407010",$C$20,"Amount_BS")/1000) -> 635287.62 | G34: =(_xll.DBR("CXMD:FTM_DATA_BALANCE_SHEET","Total_Customer_Supplier",G$22,$C$19,ori,"TOTAL PRODUCT","B-401010",$C$20,"Amount_BS")/1000)+(_xll.DBR("CXMD:FTM_DATA_BALANCE_SHEET","Total_Customer_Supplier",G$22,$C$19,ori,"TOTAL PRODUCT","B-401020",$C$20,"Amount_BS")/1000)+(_xll.DBR("CXMD:FTM_DATA_BALANCE_SHEET","Total_Customer_Supplier",G$22,$C$19,ori,"TOTAL PRODUCT","B-402110",$C$20,"Amount_BS")/1000)+(_xll.DBR("CXMD:FTM_DATA_BALANCE_SHEET","Total_Customer_Supplier",G$22,$C$19,ori,"TOTAL PRODUCT","B-402111",$C$20,"Amount_BS")/1000)+(_xll.DBR("CXMD:FTM_DATA_BALANCE_SHEET","Total_Customer_Supplier",G$22,$C$19,ori,"TOTAL PRODUCT","B-407010",$C$20,"Amount_BS")/1000) -> 845428.46 | H34: =(_xll.DBR("CXMD:FTM_DATA_BALANCE_SHEET","Total_Customer_Supplier",H$22,$C$19,ori,"TOTAL PRODUCT","B-401010",$C$20,"Amount_BS")/1000)+(_xll.DBR("CXMD:FTM_DATA_BALANCE_SHEET","Total_Customer_Supplier",H$22,$C$19,ori,"TOTAL PRODUCT","B-401020",$C$20,"Amount_BS")/1000)+(_xll.DBR("CXMD:FTM_DATA_BALANCE_SHEET","Total_Customer_Supplier",H$22,$C$19,ori,"TOTAL PRODUCT","B-402110",$C$20,"Amount_BS")/1000)+(_xll.DBR("CXMD:FTM_DATA_BALANCE_SHEET","Total_Customer_Supplier",H$22,$C$19,ori,"TOTAL PRODUCT","B-402111",$C$20,"Amount_BS")/1000)+(_xll.DBR("CXMD:FTM_DATA_BALANCE_SHEET","Total_Customer_Supplier",H$22,$C$19,ori,"TOTAL PRODUCT","B-407010",$C$20,"Amount_BS")/1000) -> 1088819.2 | I34: =(_xll.DBR("CXMD:FTM_DATA_BALANCE_SHEET","Total_Customer_Supplier",I$22,$C$19,ori,"TOTAL PRODUCT","B-401010",$C$20,"Amount_BS")/1000)+(_xll.DBR("CXMD:FTM_DATA_BALANCE_SHEET","Total_Customer_Supplier",I$22,$C$19,ori,"TOTAL PRODUCT","B-401020",$C$20,"Amount_BS")/1000)+(_xll.DBR("CXMD:FTM_DATA_BALANCE_SHEET","Total_Customer_Supplier",I$22,$C$19,ori,"TOTAL PRODUCT","B-402110",$C$20,"Amount_BS")/1000)+(_xll.DBR("CXMD:FTM_DATA_BALANCE_SHEET","Total_Customer_Supplier",I$22,$C$19,ori,"TOTAL PRODUCT","B-402111",$C$20,"Amount_BS")/1000)+(_xll.DBR("CXMD:FTM_DATA_BALANCE_SHEET","Total_Customer_Supplier",I$22,$C$19,ori,"TOTAL PRODUCT","B-407010",$C$20,"Amount_BS")/1000) -> 1324032.2 | J34: =(_xll.DBR("CXMD:FTM_DATA_BALANCE_SHEET","Total_Customer_Supplier",J$22,$C$19,ori,"TOTAL PRODUCT","B-401010",$C$20,"Amount_BS")/1000)+(_xll.DBR("CXMD:FTM_DATA_BALANCE_SHEET","Total_Customer_Supplier",J$22,$C$19,ori,"TOTAL PRODUCT","B-401020",$C$20,"Amount_BS")/1000)+(_xll.DBR("CXMD:FTM_DATA_BALANCE_SHEET","Total_Customer_Supplier",J$22,$C$19,ori,"TOTAL PRODUCT","B-402110",$C$20,"Amount_BS")/1000)+(_xll.DBR("CXMD:FTM_DATA_BALANCE_SHEET","Total_Customer_Supplier",J$22,$C$19,ori,"TOTAL PRODUCT","B-402111",$C$20,"Amount_BS")/1000)+(_xll.DBR("CXMD:FTM_DATA_BALANCE_SHEET","Total_Customer_Supplier",J$22,$C$19,ori,"TOTAL PRODUCT","B-407010",$C$20,"Amount_BS")/1000) -> 1545981.6 | K34: =(_xll.DBR("CXMD:FTM_DATA_BALANCE_SHEET","Total_Customer_Supplier",K$22,$C$19,ori,"TOTAL PRODUCT","B-401010",$C$20,"Amount_BS")/1000)+(_xll.DBR("CXMD:FTM_DATA_BALANCE_SHEET","Total_Customer_Supplier",K$22,$C$19,ori,"TOTAL PRODUCT","B-401020",$C$20,"Amount_BS")/1000)+(_xll.DBR("CXMD:FTM_DATA_BALANCE_SHEET","Total_Customer_Supplier",K$22,$C$19,ori,"TOTAL PRODUCT","B-402110",$C$20,"Amount_BS")/1000)+(_xll.DBR("CXMD:FTM_DATA_BALANCE_SHEET","Total_Customer_Supplier",K$22,$C$19,ori,"TOTAL PRODUCT","B-402111",$C$20,"Amount_BS")/1000)+(_xll.DBR("CXMD:FTM_DATA_BALANCE_SHEET","Total_Customer_Supplier",K$22,$C$19,ori,"TOTAL PRODUCT","B-407010",$C$20,"Amount_BS")/1000) -> 1745045.4 | ... O34: =(_xll.DBR("CXMD:FTM_DATA_BALANCE_SHEET","Total_Customer_Supplier",O$22,$C$19,ori,"TOTAL PRODUCT","B-401010",$C$20,"Amount_BS")/1000)+(_xll.DBR("CXMD:FTM_DATA_BALANCE_SHEET","Total_Customer_Supplier",O$22,$C$19,ori,"TOTAL PRODUCT","B-401020",$C$20,"Amount_BS")/1000)+(_xll.DBR("CXMD:FTM_DATA_BALANCE_SHEET","Total_Customer_Supplier",O$22,$C$19,ori,"TOTAL PRODUCT","B-402110",$C$20,"Amount_BS")/1000)+(_xll.DBR("CXMD:FTM_DATA_BALANCE_SHEET","Total_Customer_Supplier",O$22,$C$19,ori,"TOTAL PRODUCT","B-402111",$C$20,"Amount_BS")/1000)+(_xll.DBR("CXMD:FTM_DATA_BALANCE_SHEET","Total_Customer_Supplier",O$22,$C$19,ori,"TOTAL PRODUCT","B-407010",$C$20,"Amount_BS")/1000) -> 2543662.2
C35: % of corporate output | D35: =IF(D27<>0,D34/D27,0) -> 0.57757445 | E35: =IF(E27<>0,E34/E27,0) -> 0.57866479 | F35: =IF(F27<>0,F34/F27,0) -> 0.61477284 | G35: =IF(G27<>0,G34/G27,0) -> 0.62574176 | H35: =IF(H27<>0,H34/H27,0) -> 0.62792492 | I35: =IF(I27<>0,I34/I27,0) -> 0.62890109 | J35: =IF(J27<>0,J34/J27,0) -> 0.62678958 | K35: =IF(K27<>0,K34/K27,0) -> 0.61680753 | ... O35: =IF(O27<>0,O34/O27,0) -> 0.62296765
B36: G - 415000 - MATERIAL & OUTSIDE COSTS | C36: R-0-R-P-901000-MATERIAL EXPENSES | D36: =(_xll.DBR("CXMD:FTM_DATA_BALANCE_SHEET","Total_Customer_Supplier",D$22,$C$19,ori,"TOTAL PRODUCT","R-901000",$C$20,"Amount_BS")/1000) -> 190042.62 | E36: =(_xll.DBR("CXMD:FTM_DATA_BALANCE_SHEET","Total_Customer_Supplier",E$22,$C$19,ori,"TOTAL PRODUCT","R-901000",$C$20,"Amount_BS")/1000) -> 382894.78 | F36: =(_xll.DBR("CXMD:FTM_DATA_BALANCE_SHEET","Total_Customer_Supplier",F$22,$C$19,ori,"TOTAL PRODUCT","R-901000",$C$20,"Amount_BS")/1000) -> 635287.62 | G36: =(_xll.DBR("CXMD:FTM_DATA_BALANCE_SHEET","Total_Customer_Supplier",G$22,$C$19,ori,"TOTAL PRODUCT","R-901000",$C$20,"Amount_BS")/1000) -> 845428.46 | H36: =(_xll.DBR("CXMD:FTM_DATA_BALANCE_SHEET","Total_Customer_Supplier",H$22,$C$19,ori,"TOTAL PRODUCT","R-901000",$C$20,"Amount_BS")/1000) -> 1088819.2 | I36: =(_xll.DBR("CXMD:FTM_DATA_BALANCE_SHEET","Total_Customer_Supplier",I$22,$C$19,ori,"TOTAL PRODUCT","R-901000",$C$20,"Amount_BS")/1000) -> 1324032.2 | J36: =(_xll.DBR("CXMD:FTM_DATA_BALANCE_SHEET","Total_Customer_Supplier",J$22,$C$19,ori,"TOTAL PRODUCT","R-901000",$C$20,"Amount_BS")/1000) -> 1545981.6 | K36: =(_xll.DBR("CXMD:FTM_DATA_BALANCE_SHEET","Total_Customer_Supplier",K$22,$C$19,ori,"TOTAL PRODUCT","R-901000",$C$20,"Amount_BS")/1000) -> 1745045.4 | ... O36: =(_xll.DBR("CXMD:FTM_DATA_BALANCE_SHEET","Total_Customer_Supplier",O$22,$C$19,ori,"TOTAL PRODUCT","R-901000",$C$20,"Amount_BS")/1000) -> 2543662.2
B37: G - 415000 - MATERIAL & OUTSIDE COSTS | C37: B-0-B-P-401010-Purchase expense - 3rd p | D37: =(_xll.DBR("CXMD:FTM_DATA_BALANCE_SHEET","Total_Customer_Supplier",D$22,$C$19,ori,"TOTAL PRODUCT","B-401010",$C$20,"Amount_BS")/1000) -> 72512.263 | E37: =(_xll.DBR("CXMD:FTM_DATA_BALANCE_SHEET","Total_Customer_Supplier",E$22,$C$19,ori,"TOTAL PRODUCT","B-401010",$C$20,"Amount_BS")/1000) -> 163683.51 | F37: =(_xll.DBR("CXMD:FTM_DATA_BALANCE_SHEET","Total_Customer_Supplier",F$22,$C$19,ori,"TOTAL PRODUCT","B-401010",$C$20,"Amount_BS")/1000) -> 273209.7 | G37: =(_xll.DBR("CXMD:FTM_DATA_BALANCE_SHEET","Total_Customer_Supplier",G$22,$C$19,ori,"TOTAL PRODUCT","B-401010",$C$20,"Amount_BS")/1000) -> 359853.75 | H37: =(_xll.DBR("CXMD:FTM_DATA_BALANCE_SHEET","Total_Customer_Supplier",H$22,$C$19,ori,"TOTAL PRODUCT","B-401010",$C$20,"Amount_BS")/1000) -> 477831.1 | I37: =(_xll.DBR("CXMD:FTM_DATA_BALANCE_SHEET","Total_Customer_Supplier",I$22,$C$19,ori,"TOTAL PRODUCT","B-401010",$C$20,"Amount_BS")/1000) -> 584523.08 | J37: =(_xll.DBR("CXMD:FTM_DATA_BALANCE_SHEET","Total_Customer_Supplier",J$22,$C$19,ori,"TOTAL PRODUCT","B-401010",$C$20,"Amount_BS")/1000) -> 694006.81 | K37: =(_xll.DBR("CXMD:FTM_DATA_BALANCE_SHEET","Total_Customer_Supplier",K$22,$C$19,ori,"TOTAL PRODUCT","B-401010",$C$20,"Amount_BS")/1000) -> 802483.9 | ... O37: =(_xll.DBR("CXMD:FTM_DATA_BALANCE_SHEET","Total_Customer_Supplier",O$22,$C$19,ori,"TOTAL PRODUCT","B-401010",$C$20,"Amount_BS")/1000) -> 1204713.2
