Workbook
Name TM1REBUILDOPTION: 1
Name TM1RPTDATARNGARPT1: Detail!$25:$25
Name TM1RPTDATARNGARPT1: Recap!$25:$25
Name TM1RPTFMTIDCOL: Detail!$A$1:$A$8
Name TM1RPTFMTIDCOL: Recap!$A$1:$A$8
Name TM1RPTFMTRNG: Detail!$B$1:$AU$8
Name TM1RPTFMTRNG: Recap!$B$1:$AE$8

Sheet Recap
A1: [Begin Format Range]
A2: =0 -> 0
A3: =1 -> 1
A4: =2 -> 2
A5: =3 -> 3
A6: D
A7: N
A8: [End Format Range]
B9: =_xll.TM1RPTVIEW("CXMD:FTM_DATA_MARGIN:ARPT1", 1, _xll.TM1RPTTITLE("CXMD:DIM_Origin_Company",$C$15),_xll.TM1RPTTITLE("CXMD:FTM_Customer_Supplier",$C$16),TM1RPTFMTRNG,TM1RPTFMTIDCOL) -> CXMD:FTM_DATA_MARGIN:ARPT1
I14: =CONCATENATE(_xll.DBRA("CXMD:DIM_Origin_Company",C15,"Origin Company"),"_SALES") -> Y_SALES
B15: Origin_Company | C15: =_xll.SUBNM("CXMD:DIM_Origin_Company","","Y","Name EN") -> SILVA | I15: Sales margin
B16: Customer_Supplier | C16: =_xll.SUBNM("CXMD:DIM_Customer_Supplier","","Total_Customer_Supplier") -> Total_Customer_Supplier
C19: Local currency | F19: =_xll.SUBNM("CXMD:Actuality","","AC2022","Description EN") -> AC2022 | L19: =_xll.SUBNM("CXMD:Actuality","","AC2022","Description EN") -> AC2022 | P19: =J19 -> 0 | R19: =L19 -> AC2022 | X19: Variances YTD | AF19: =_xll.SUBNM("CXMD:Actuality","","AC2022","Description EN") -> AC2022 | AG19: Year To Go vs annual goal | AI19: Year To Go vs annual goal
F20: =_xll.SUBNM("CXMD:Month","","YTD_January","Description EN") -> YTD_January | L20: =_xll.SUBNM("CXMD:Month","","01","Description EN") -> January | P20: =D20 -> 0 | R20: =F20 -> YTD_January | AF20: =_xll.SUBNM("CXMD:Month","","YTD_December","Description EN") -> YTD_December
D22: QTY | E22: SALES | F22: SALES | G22: MARGIN | H22: MARGIN | I22: Margin % | J22: QTY | K22: SALES | L22: SALES | M22: MARGIN | N22: MARGIN | O22: Margin % | P22: QTY | Q22: SALES | R22: SALES | S22: MARGIN | T22: MARGIN | U22: Margin % | V22: QTY | X22: SALES | Y22: x | Z22: MARGIN | AD22: QTY | AE22: SALES | AF22: SALES | AG22: QTY | AI22: SALES
B23: Area / Region | C23: Product configuration | F23: (in '000) | H23: (in '000) | L23: (in '000) | N23: (in '000) | R23: (in '000) | T23: (in '000) | X23: (in '000) | Y23: x | Z23: (in '000) | AB23: in pt | AC23: (in '000) | AF23: (in '000) | AI23: (in '000)
D24: QTY | E24: SALES | G24: MARGIN_ON_TOTAL_COST | I24: MARGIN_ON_TOTAL_COST_% | J24: QTY | K24: SALES | M24: MARGIN_ON_TOTAL_COST | O24: MARGIN_ON_TOTAL_COST_% | P24: QTY | Q24: SALES | S24: MARGIN_ON_TOTAL_COST | U24: MARGIN_ON_TOTAL_COST_% | AD24: QTY | AE24: SALES | AG24: QTY | AI24: SALES | AK24: MARGIN_ON_TOTAL_COST | AL24: MARGIN_ON_TOTAL_COST_%
A25: =IF(_xll.TM1RPTELISCONSOLIDATED($C$25,$C25),IF(_xll.TM1RPTELLEV($C$25,$C25)<=3,_xll.TM1RPTELLEV($C$25,$C25),"D"),"N") -> N | B25: =_xll.TM1RPTROW($B$9,"CXMD:DIM_Allocation",,$I$14,"Allocation EN") | C25: =_xll.TM1RPTROW($B$9,"CXMD:DIM_Configuration","Sales Report",,"Description EN") | D25: =_xll.DBRW($B$9,$F$20,$F$19,$C$15,$B25,$C$16,$C25,D$24) | E25: =_xll.DBRW($B$9,$F$20,$F$19,$C$15,$B25,$C$16,$C25,E$24) | F25: =E25/1000 -> #VALUE! | G25: =_xll.DBRW($B$9,$F$20,$F$19,$C$15,$B25,$C$16,$C25,E$24) | H25: =G25/1000 -> #VALUE! | I25: =IF(E25<>0,G25/E25,0) -> #VALUE! | J25: =_xll.DBRW($B$9,$L$20,$L$19,$C$15,$B25,$C$16,$C25,J$24) | K25: =_xll.DBRW($B$9,$L$20,$L$19,$C$15,$B25,$C$16,$C25,K$24) | L25: =K25/1000 -> #VALUE! | M25: =_xll.DBRW($B$9,$L$20,$L$19,$C$15,$B25,$C$16,$C25,M$24) | N25: =M25/1000 -> #VALUE! | O25: =IF(K25<>0,M25/K25,0) -> #VALUE! | P25: =_xll.DBRW($B$9,$R$20,$R$19,$C$15,$B25,$C$16,$C25,P$24) | Q25: =_xll.DBRW($B$9,$R$20,$R$19,$C$15,$B25,$C$16,$C25,Q$24) | R25: =Q25/1000 -> #VALUE! | S25: =_xll.DBRW($B$9,$R$20,$R$19,$C$15,$B25,$C$16,$C25,S$24) | T25: =S25/1000 -> #VALUE! | U25: =IF(Q25<>0,S25/Q25,0) -> #VALUE! | V25: =P25-D25 -> #VALUE! | W25: =IF(D25<>0,(P25/D25)-1,0) -> #VALUE! | X25: =(Q25-E25)/1000 -> #VALUE! | Y25: =IF(E25<>0,(Q25/E25)-1,0) -> #VALUE! | Z25: =(S25-G25)/1000 -> #VALUE! | AA25: =IF(G25<>0,(S25/G25)-1,0) -> #VALUE! | AB25: =(U25-I25)*100 -> #VALUE! | AC25: =AB25*Q25/100/1000 -> #VALUE! | AD25: =_xll.DBRW($B$9,$AF$20,$AF$19,$C$15,$B25,$C$16,$C25,AD$24) | AE25: =_xll.DBRW($B$9,$AF$20,$AF$19,$C$15,$B25,$C$16,$C25,AE$24) | AF25: =AE25/1000 -> #VALUE! | AG25: =AD25-P25 -> #VALUE! | AH25: =IF(P25<>0,(AD25/P25)-1,0) -> #VALUE! | AI25: =(AE25-Q25)/1000 -> #VALUE! | AJ25: =IF(Q25<>0,(AE25/Q25)-1,0) -> #VALUE!

Sheet Detail
A1: [Begin Format Range]
A2: =0 -> 0
A3: =1 -> 1
A4: =2 -> 2
A5: =3 -> 3
A6: D
A7: N
A8: [End Format Range]
B9: =_xll.TM1RPTVIEW("CXMD:FTM_DATA_MARGIN:ARPT1", 1, _xll.TM1RPTTITLE("CXMD:DIM_Origin_Company",$C$14), _xll.TM1RPTTITLE("CXMD:DIM_Customer_Supplier",$C$15),TM1RPTFMTRNG,TM1RPTFMTIDCOL) -> CXMD:FTM_DATA_MARGIN:ARPT1
B14: Origin_Company | C14: =Recap!C15 -> SILVA | O14: =Recap!I15 -> Sales margin
B15: Customer_Supplier | C15: =_xll.SUBNM("CXMD:DIM_Customer_Supplier","","Total_Customer_Supplier") -> Total_Customer_Supplier
C19: Local currency | D19: =Recap!F19 -> AC2022 | O19: =D19 -> AC2022 | Z19: =Recap!R19 -> AC2022 | AK19: =Recap!AF19 -> AC2022
D20: =_xll.SUBNM("CXMD:Month","","YTD_January","Description EN") -> YTD_January | O20: =_xll.SUBNM("CXMD:Month","","YTD_December","Description EN") -> YTD_December | Z20: =D20 -> YTD_January | AK20: =D20 -> YTD_January
G21: Unit | J21: Unit | M21: Unit | R21: Unit | U21: Unit | X21: Unit | AC21: Unit | AF21: Unit | AI21: Unit | AN21: Unit | AQ21: Unit | AT21: Unit
D22: QTY | E22: SALES | F22: SALES | G22: Price | H22: COST | I22: COST | J22: Cost | K22: MARGIN | L22: MARGIN | M22: Margin | N22: Margin % | O22: QTY | P22: SALES | Q22: SALES | R22: Price | S22: COST | T22: COST | U22: Cost | V22: MARGIN | W22: MARGIN | X22: Margin | Y22: Margin % | Z22: QTY | AA22: SALES | AB22: SALES | AC22: Price | AD22: COST | AE22: COST | AF22: Cost | AG22: MARGIN | AH22: MARGIN | AI22: Margin | AJ22: Margin % | AK22: QTY | AL22: SALES | AM22: SALES | AN22: Price | AO22: COST | AP22: COST | AQ22: Cost | AR22: MARGIN | AS22: MARGIN | AT22: Margin | AU22: Margin %
B23: Area / Region | C23: Product configuration | F23: (in '000) | I23: (in '000) | L23: (in '000) | Q23: (in '000) | T23: (in '000) | W23: (in '000) | AB23: (in '000) | AE23: (in '000) | AH23: (in '000) | AM23: (in '000) | AP23: (in '000) | AS23: (in '000)
D24: QTY | E24: SALES | G24: U.Price | H24: TOTAL_COST | K24: MARGIN_ON_TOTAL_COST | N24: MARGIN_ON_TOTAL_COST_% | O24: QTY | P24: SALES | R24: U.Price | S24: TOTAL_COST | V24: MARGIN_ON_TOTAL_COST | Y24: MARGIN_ON_TOTAL_COST_% | Z24: QTY | AA24: SALES | AC24: U.Price | AD24: TOTAL_COST | AG24: MARGIN_ON_TOTAL_COST | AJ24: MARGIN_ON_TOTAL_COST_% | AK24: QTY | AL24: SALES | AN24: U.Price | AO24: TOTAL_COST | AR24: MARGIN_ON_TOTAL_COST | AU24: MARGIN_ON_TOTAL_COST_%
A25: =IF(_xll.TM1RPTELISCONSOLIDATED($C$25,$C25),IF(_xll.TM1RPTELLEV($C$25,$C25)<=3,_xll.TM1RPTELLEV($C$25,$C25),"D"),"N") -> N | B25: =_xll.TM1RPTROW($B$9,"CXMD:DIM_Allocation",,Recap!I14,"Allocation EN") | C25: =_xll.TM1RPTROW($B$9,"CXMD:DIM_Configuration","","Par défaut","Description EN",0) | D25: =_xll.DBRW($B$9,$D$20,$D$19,$C$14,$B25,$C$15,$C25,D$24) | E25: =_xll.DBRW($B$9,$D$20,$D$19,$C$14,$B25,$C$15,$C25,E$24) | F25: =E25/1000 -> #VALUE! | G25: =_xll.DBRW($B$9,$D$20,$D$19,$C$14,$B25,$C$15,$C25,G$24) | H25: =_xll.DBRW($B$9,$D$20,$D$19,$C$14,$B25,$C$15,$C25,H$24) | I25: =H25/1000 -> #VALUE! | J25: =IF(D25<>0,H25/D25,0) -> #VALUE! | K25: =_xll.DBRW($B$9,$D$20,$D$19,$C$14,$B25,$C$15,$C25,K$24) | L25: =K25/1000 -> #VALUE! | M25: =IF(D25<>0,K25/D25,0) -> #VALUE! | N25: =IF(E25<>0,K25/E25,0) -> #VALUE! | O25: =_xll.DBRW($B$9,$O$20,$O$19,$C$14,$B25,$C$15,$C25,O$24) | P25: =_xll.DBRW($B$9,$O$20,$O$19,$C$14,$B25,$C$15,$C25,P$24) | Q25: =P25/1000 -> #VALUE! | R25: =_xll.DBRW($B$9,$O$20,$O$19,$C$14,$B25,$C$15,$C25,R$24) | S25: =_xll.DBRW($B$9,$O$20,$O$19,$C$14,$B25,$C$15,$C25,S$24) | T25: =S25/1000 -> #VALUE! | U25: =IF(O25<>0,S25/O25,0) -> #VALUE! | V25: =_xll.DBRW($B$9,$O$20,$O$19,$C$14,$B25,$C$15,$C25,V$24) | W25: =V25/1000 -> #VALUE! | X25: =IF(O25<>0,V25/O25,0) -> #VALUE! | Y25: =IF(P25<>0,V25/P25,0) -> #VALUE! | Z25: =_xll.DBRW($B$9,$Z$20,$Z$19,$C$14,$B25,$C$15,$C25,Z$24) | AA25: =_xll.DBRW($B$9,$Z$20,$Z$19,$C$14,$B25,$C$15,$C25,AA$24) | AB25: =AA25/1000 -> #VALUE! | AC25: =_xll.DBRW($B$9,$Z$20,$Z$19,$C$14,$B25,$C$15,$C25,AC$24) | AD25: =_xll.DBRW($B$9,$Z$20,$Z$19,$C$14,$B25,$C$15,$C25,AD$24) | AE25: =AD25/1000 -> #VALUE! | AF25: =IF(Z25<>0,AD25/Z25,0) -> #VALUE! | AG25: =_xll.DBRW($B$9,$Z$20,$Z$19,$C$14,$B25,$C$15,$C25,AG$24) | AH25: =AG25/1000 -> #VALUE! | AI25: =IF(Z25<>0,AG25/Z25,0) -> #VALUE! | AJ25: =IF(AA25<>0,AG25/AA25,0) -> #VALUE! | AK25: =_xll.DBRW($B$9,$AK$20,$AK$19,$C$14,$B25,$C$15,$C25,AK$24) | AL25: =_xll.DBRW($B$9,$AK$20,$AK$19,$C$14,$B25,$C$15,$C25,AL$24) | AM25: =AL25/1000 -> #VALUE! | AN25: =_xll.DBRW($B$9,$AK$20,$AK$19,$C$14,$B25,$C$15,$C25,AN$24) | AO25: =_xll.DBRW($B$9,$AK$20,$AK$19,$C$14,$B25,$C$15,$C25,AO$24) | AP25: =AO25/1000 -> #VALUE! | AQ25: =IF(AK25<>0,AO25/AK25,0) -> #VALUE! | AR25: =_xll.DBRW($B$9,$AK$20,$AK$19,$C$14,$B25,$C$15,$C25,AR$24) | AS25: =AR25/1000 -> #VALUE! | AT25: =IF(AK25<>0,AR25/AK25,0) -> #VALUE! | AU25: =IF(AL25<>0,AR25/AL25,0) -> #VALUE!

Sheet {AR}01
B22: Total Allocation

Sheet {AR}11
C22: TOTAL PRODUCT
C23: L - 000 -
C24: L - 700000 - PLOUGHING
C25: L - 701000 - TILLAGE
C26: L - 702000 - SEEDING
C27: L - 703000 - FERTILISING
C28: L - 704000 - SPRAYING
C29: L - 705000 - LANDSCAPE MAINTENANCE
C30: L - 706000 - SHREDDING
C31: L - 707000 - HAY & FORAGE
C32: L - 708000 - BALERS
C33: L - 709000 - WRAPPERS
... C50: L - NA - Not Available
